{"goalHistory":[[0,0],[5,0]],"startClock":30,"gameMetaURL":"http://127.0.0.1:9140/games/gt_centipede/v0/","goalValues":[5,0],"legalMoves":[[["continue","finish"],["noop"]],[["continue","finish"],["noop"]],[["noop"],["finish","continue"]]],"randomToken":"If7CLP74Z5YedKi2MgM7eZI2omao2DgO","roles":["white","black"],"playerNamesFromHost":["Sancho","Sancho"],"states":["( ( whitePayoff 5 ) ( control white ) ( blackPayoff 0 ) )","( ( whitePayoff 5 ) ( blackPayoff 0 ) ( control black ) ( gameOver ) )"],"playClock":15,"gameName":"gt_centipede","moves":[["finish","noop"]],"startTime":1585672624721,"stateTimes":[1585672624757,1585672650225],"scrambled":false,"matchId":"optimaltraces_iggp.gt_centipede.1585672624715","errors":[["",""],["",""]],"isCompleted":true,"isAborted":false,"previewClock":-1}