{"goalHistory":[[0],[0],[0],[0],[0],[0],[0],[0],[0],[0],[0],[0],[0],[0],[0],[0],[0],[0],[0],[0],[0],[0],[0],[0],[0],[0],[0],[0],[0],[0],[0],[0],[0],[0],[0],[0],[0],[0]],"startClock":30,"gameMetaURL":"http://games.ggp.org/stanford/games/vectorracerbig/v0/","goalValues":[0],"legalMoves":[[["( dv 0 0 )","( dv n1 n1 )","( dv 0 n1 )","( dv n1 1 )","( dv 1 n1 )","( dv 1 0 )","( dv n1 0 )","( dv 0 1 )","( dv 1 1 )"]],[["( dv 0 0 )","( dv n1 n1 )","( dv 0 n1 )","( dv n1 1 )","( dv 1 n1 )","( dv 1 0 )","( dv n1 0 )","( dv 0 1 )","( dv 1 1 )"]],[["( dv 0 0 )","( dv n1 n1 )","( dv 0 n1 )","( dv n1 1 )","( dv 1 n1 )","( dv 1 0 )","( dv n1 0 )","( dv 0 1 )","( dv 1 1 )"]],[["( dv 0 0 )","( dv n1 n1 )","( dv 0 n1 )","( dv n1 1 )","( dv 1 n1 )","( dv 1 0 )","( dv n1 0 )","( dv 0 1 )","( dv 1 1 )"]],[["( dv 0 0 )","( dv n1 n1 )","( dv 0 n1 )","( dv n1 1 )","( dv 1 n1 )","( dv 1 0 )","( dv n1 0 )","( dv 0 1 )","( dv 1 1 )"]],[["( dv 0 0 )","( dv n1 n1 )","( dv 0 n1 )","( dv n1 1 )","( dv 1 n1 )","( dv 1 0 )","( dv n1 0 )","( dv 0 1 )","( dv 1 1 )"]],[["( dv 0 0 )","( dv n1 n1 )","( dv 0 n1 )","( dv n1 1 )","( dv 1 n1 )","( dv 1 0 )","( dv n1 0 )","( dv 0 1 )","( dv 1 1 )"]],[["( dv 0 0 )","( dv n1 n1 )","( dv 0 n1 )","( dv n1 1 )","( dv 1 n1 )","( dv 1 0 )","( dv n1 0 )","( dv 0 1 )","( dv 1 1 )"]],[["( dv 0 0 )","( dv n1 n1 )","( dv 0 n1 )","( dv n1 1 )","( dv 1 n1 )","( dv 1 0 )","( dv n1 0 )","( dv 0 1 )","( dv 1 1 )"]],[["( dv 0 0 )","( dv n1 n1 )","( dv 0 n1 )","( dv n1 1 )","( dv 1 n1 )","( dv 1 0 )","( dv n1 0 )","( dv 0 1 )","( dv 1 1 )"]],[["( dv 0 0 )","( dv n1 n1 )","( dv 0 n1 )","( dv n1 1 )","( dv 1 n1 )","( dv 1 0 )","( dv n1 0 )","( dv 0 1 )","( dv 1 1 )"]],[["( dv 0 0 )","( dv n1 n1 )","( dv 0 n1 )","( dv n1 1 )","( dv 1 n1 )","( dv 1 0 )","( dv n1 0 )","( dv 0 1 )","( dv 1 1 )"]],[["( dv 0 0 )","( dv n1 n1 )","( dv 0 n1 )","( dv n1 1 )","( dv 1 n1 )","( dv 1 0 )","( dv n1 0 )","( dv 0 1 )","( dv 1 1 )"]],[["( dv 0 0 )","( dv n1 n1 )","( dv 0 n1 )","( dv n1 1 )","( dv 1 n1 )","( dv 1 0 )","( dv n1 0 )","( dv 0 1 )","( dv 1 1 )"]],[["( dv 0 0 )","( dv n1 n1 )","( dv 0 n1 )","( dv n1 1 )","( dv 1 n1 )","( dv 1 0 )","( dv n1 0 )","( dv 0 1 )","( dv 1 1 )"]],[["( dv 0 0 )","( dv n1 n1 )","( dv 0 n1 )","( dv n1 1 )","( dv 1 n1 )","( dv 1 0 )","( dv n1 0 )","( dv 0 1 )","( dv 1 1 )"]],[["( dv 0 0 )","( dv n1 n1 )","( dv 0 n1 )","( dv n1 1 )","( dv 1 n1 )","( dv 1 0 )","( dv n1 0 )","( dv 0 1 )","( dv 1 1 )"]],[["( dv 0 0 )","( dv n1 n1 )","( dv 0 n1 )","( dv n1 1 )","( dv 1 n1 )","( dv 1 0 )","( dv n1 0 )","( dv 0 1 )","( dv 1 1 )"]],[["( dv 0 0 )","( dv n1 n1 )","( dv 0 n1 )","( dv n1 1 )","( dv 1 n1 )","( dv 1 0 )","( dv n1 0 )","( dv 0 1 )","( dv 1 1 )"]],[["( dv 0 0 )","( dv n1 n1 )","( dv 0 n1 )","( dv n1 1 )","( dv 1 n1 )","( dv 1 0 )","( dv n1 0 )","( dv 0 1 )","( dv 1 1 )"]],[["( dv 0 0 )","( dv n1 n1 )","( dv 0 n1 )","( dv n1 1 )","( dv 1 n1 )","( dv 1 0 )","( dv n1 0 )","( dv 0 1 )","( dv 1 1 )"]],[["( dv 0 0 )","( dv n1 n1 )","( dv 0 n1 )","( dv n1 1 )","( dv 1 n1 )","( dv 1 0 )","( dv n1 0 )","( dv 0 1 )","( dv 1 1 )"]],[["( dv 0 0 )","( dv n1 n1 )","( dv 0 n1 )","( dv n1 1 )","( dv 1 n1 )","( dv 1 0 )","( dv n1 0 )","( dv 0 1 )","( dv 1 1 )"]],[["( dv 0 0 )","( dv n1 n1 )","( dv 0 n1 )","( dv n1 1 )","( dv 1 n1 )","( dv 1 0 )","( dv n1 0 )","( dv 0 1 )","( dv 1 1 )"]],[["( dv 0 0 )","( dv n1 n1 )","( dv 0 n1 )","( dv n1 1 )","( dv 1 n1 )","( dv 1 0 )","( dv n1 0 )","( dv 0 1 )","( dv 1 1 )"]],[["( dv 0 0 )","( dv n1 n1 )","( dv 0 n1 )","( dv n1 1 )","( dv 1 n1 )","( dv 1 0 )","( dv n1 0 )","( dv 0 1 )","( dv 1 1 )"]],[["( dv 0 0 )","( dv n1 n1 )","( dv 0 n1 )","( dv n1 1 )","( dv 1 n1 )","( dv 1 0 )","( dv n1 0 )","( dv 0 1 )","( dv 1 1 )"]],[["( dv 0 0 )","( dv n1 n1 )","( dv 0 n1 )","( dv n1 1 )","( dv 1 n1 )","( dv 1 0 )","( dv n1 0 )","( dv 0 1 )","( dv 1 1 )"]],[["( dv 0 0 )","( dv n1 n1 )","( dv 0 n1 )","( dv n1 1 )","( dv 1 n1 )","( dv 1 0 )","( dv n1 0 )","( dv 0 1 )","( dv 1 1 )"]],[["( dv 0 0 )","( dv n1 n1 )","( dv 0 n1 )","( dv n1 1 )","( dv 1 n1 )","( dv 1 0 )","( dv n1 0 )","( dv 0 1 )","( dv 1 1 )"]],[["( dv 0 0 )","( dv n1 n1 )","( dv 0 n1 )","( dv n1 1 )","( dv 1 n1 )","( dv 1 0 )","( dv n1 0 )","( dv 0 1 )","( dv 1 1 )"]],[["( dv 0 0 )","( dv n1 n1 )","( dv 0 n1 )","( dv n1 1 )","( dv 1 n1 )","( dv 1 0 )","( dv n1 0 )","( dv 0 1 )","( dv 1 1 )"]],[["( dv 0 0 )","( dv n1 n1 )","( dv 0 n1 )","( dv n1 1 )","( dv 1 n1 )","( dv 1 0 )","( dv n1 0 )","( dv 0 1 )","( dv 1 1 )"]],[["( dv 0 0 )","( dv n1 n1 )","( dv 0 n1 )","( dv n1 1 )","( dv 1 n1 )","( dv 1 0 )","( dv n1 0 )","( dv 0 1 )","( dv 1 1 )"]],[["( dv 0 0 )","( dv n1 n1 )","( dv 0 n1 )","( dv n1 1 )","( dv 1 n1 )","( dv 1 0 )","( dv n1 0 )","( dv 0 1 )","( dv 1 1 )"]],[["( dv 0 0 )","( dv n1 n1 )","( dv 0 n1 )","( dv n1 1 )","( dv 1 n1 )","( dv 1 0 )","( dv n1 0 )","( dv 0 1 )","( dv 1 1 )"]],[["( dv 0 0 )","( dv n1 n1 )","( dv 0 n1 )","( dv n1 1 )","( dv 1 n1 )","( dv 1 0 )","( dv n1 0 )","( dv 0 1 )","( dv 1 1 )"]],[["( dv 0 0 )","( dv n1 n1 )","( dv 0 n1 )","( dv n1 1 )","( dv 1 n1 )","( dv 1 0 )","( dv n1 0 )","( dv 0 1 )","( dv 1 1 )"]]],"randomToken":"Cy2rXhQcWAsH03uofu4mvaEsJEv69Qtm","roles":["robot"],"playerNamesFromHost":["Sancho"],"states":["( ( step 0 ) ( pos 0 0 ) ( vel 0 0 ) )","( ( pos n1 0 ) ( vel n1 0 ) ( step 1 ) )","( ( vel 0 0 ) ( pos n1 0 ) ( step 2 ) )","( ( step 3 ) )","( ( step 4 ) )","( ( step 5 ) )","( ( step 6 ) )","( ( step 7 ) )","( ( step 8 ) )","( ( step 9 ) )","( ( step 10 ) )","( ( step 11 ) )","( ( step 12 ) )","( ( step 13 ) )","( ( step 14 ) )","( ( step 15 ) )","( ( step 16 ) )","( ( step 17 ) )","( ( step 18 ) )","( ( step 19 ) )","( ( step 20 ) )","( ( step 21 ) )","( ( step 22 ) )","( ( step 23 ) )","( ( step 24 ) )","( ( step 25 ) )","( ( step 26 ) )","( ( step 27 ) )","( ( step 28 ) )","( ( step 29 ) )","( ( step 30 ) )","( ( step 31 ) )","( ( step 32 ) )","( ( step 33 ) )","( ( step 34 ) )","( ( step 35 ) )","( ( step 36 ) )","( ( step 37 ) )"],"playClock":15,"gameName":"Vector Racer Big","moves":[["( dv n1 0 )"],["( dv 1 0 )"],["( dv 0 n1 )"],["( dv 0 n1 )"],["( dv n1 n1 )"],["( dv 0 n1 )"],["( dv n1 n1 )"],["( dv 0 1 )"],["( dv 1 1 )"],["( dv 0 1 )"],["( dv n1 1 )"],["( dv n1 1 )"],["( dv 1 1 )"],["( dv 0 1 )"],["( dv 0 n1 )"],["( dv 1 0 )"],["( dv n1 1 )"],["( dv 0 n1 )"],["( dv 1 0 )"],["( dv 1 1 )"],["( dv 0 1 )"],["( dv n1 1 )"],["( dv 0 0 )"],["( dv 0 1 )"],["( dv 1 n1 )"],["( dv 1 1 )"],["( dv n1 1 )"],["( dv n1 n1 )"],["( dv n1 1 )"],["( dv n1 n1 )"],["( dv 1 0 )"],["( dv 1 n1 )"],["( dv n1 1 )"],["( dv 0 0 )"],["( dv 0 0 )"],["( dv 1 0 )"],["( dv 1 0 )"]],"startTime":1584339256039,"stateTimes":[1584339256108,1584339296094,1584339296115,1584339296128,1584339296132,1584339296134,1584339296136,1584339296138,1584339296142,1584339296145,1584339296148,1584339296156,1584339296157,1584339296159,1584339296161,1584339296164,1584339296168,1584339296169,1584339296170,1584339296173,1584339296177,1584339296180,1584339296181,1584339296183,1584339296185,1584339296188,1584339296189,1584339296191,1584339296192,1584339296194,1584339296195,1584339296196,1584339296197,1584339296199,1584339296200,1584339296209,1584339296211,1584339296212],"scrambled":false,"matchId":"optimaltraces.vectorracerbig.1584339255889","errors":[["TO"],["CE"],["CE"],["CE"],["CE"],["CE"],["CE"],["CE"],["CE"],["CE"],["CE"],["CE"],["CE"],["CE"],["CE"],["CE"],["CE"],["CE"],["CE"],["CE"],["CE"],["CE"],["CE"],["CE"],["CE"],["CE"],["CE"],["CE"],["CE"],["CE"],["CE"],["CE"],["CE"],["CE"],["CE"],["CE"],["CE"],["CE"]],"isCompleted":true,"isAborted":false,"previewClock":-1}