{"goalHistory":[[0,0,0,0,0,0],[0,0,0,0,0,0],[0,0,0,0,0,0],[0,0,0,0,0,0],[0,0,0,0,0,0],[0,0,0,0,0,0],[0,0,0,0,0,0],[0,0,0,0,0,0],[0,0,0,0,0,0],[0,0,0,0,0,0],[0,0,0,0,0,0],[0,0,0,0,0,0],[0,0,0,0,0,0],[0,0,0,0,0,0],[0,0,0,0,0,0],[0,0,0,0,0,0],[0,0,0,0,0,0],[0,0,0,0,0,0],[0,0,0,0,0,0],[0,0,0,0,0,0],[0,0,0,0,0,0],[0,0,0,0,0,0],[0,0,0,0,0,0],[0,0,0,0,0,0],[0,0,0,0,0,0],[0,0,0,0,0,0],[0,0,0,0,0,0],[0,0,0,0,0,0],[0,0,0,0,0,0],[0,0,0,0,25,0],[0,0,0,0,25,0],[0,0,0,0,25,0],[0,0,0,0,25,0],[0,0,0,0,25,0],[0,0,0,0,25,0],[0,0,0,0,25,0],[0,0,0,0,25,0],[0,0,0,0,25,0],[0,25,0,0,25,0],[0,25,0,0,25,0],[0,25,0,0,25,0],[0,25,0,0,25,0],[0,25,0,0,25,0],[0,25,0,0,25,0],[0,25,0,0,25,0],[0,25,0,0,25,0],[0,25,0,0,25,0],[0,25,0,0,25,0],[0,25,0,0,25,0],[0,25,0,0,25,0],[0,25,0,0,25,0],[0,25,0,0,25,0],[0,25,0,0,25,0],[0,25,0,0,25,0],[0,25,0,0,25,0],[25,25,0,0,25,0],[25,25,0,0,25,0],[25,25,0,0,25,0],[25,25,0,0,25,0],[25,25,0,0,25,0]],"startClock":30,"gameMetaURL":"http://games.ggp.org/stanford/games/chinesecheckers/v0/","goalValues":[25,25,0,0,25,0],"legalMoves":[[["( move a1 c3 )","( move a1 c5 )","( move b1 c4 )","( move b2 c4 )","( move b1 c3 )","noop","( move b2 c5 )"],["noop"],["noop"],["noop"],["noop"],["noop"]],[["noop"],["noop","( move c6 d5 )","( move c7 e5 )","( move c7 c3 )","( move d6 d5 )","( move c7 c5 )","( move c6 c5 )","( move d6 e5 )"],["noop"],["noop"],["noop"],["noop"]],[["noop"],["noop"],["( move g6 f5 )","( move g6 g5 )","( move f6 e5 )","( move g7 c5 )","( move g7 g5 )","( move g7 e5 )","( move f6 f5 )","noop"],["noop"],["noop"],["noop"]],[["noop"],["noop"],["noop"],["( move h2 f5 )","( move h1 g3 )","( move i1 g3 )","( move h2 g4 )","noop","( move h1 g4 )"],["noop"],["noop"]],[["noop"],["noop"],["noop"],["noop"],["( move g2 g4 )","( move g2 f2 )","( move g1 e1 )","( move f1 e1 )","noop","( move f1 f2 )"],["noop"]],[["noop"],["noop"],["noop"],["noop"],["noop"],["( move c2 c3 )","( move c1 e1 )","( move c1 c3 )","( move c1 c5 )","( move d1 d2 )","noop","( move c2 d2 )","( move d1 e1 )"]],[["( move b1 d4 )","( move a1 b2 )","( move b1 d2 )","( move c4 d4 )","noop","( move c4 d3 )"],["noop"],["noop"],["noop"],["noop"],["noop"]],[["noop"],["noop","( move c7 e5 )","( move d5 e4 )","( move c7 c6 )","( move d5 d3 )","( move d6 e5 )"],["noop"],["noop"],["noop"],["noop"]],[["noop"],["noop"],["( move g7 g6 )","( move g5 f4 )","( move g5 g4 )","( move f6 f5 )","noop"],["noop"],["noop"],["noop"]],[["noop"],["noop"],["noop"],["( move h2 f5 )","( move g3 f3 )","( move g3 e1 )","( move h2 g4 )","noop","( move h1 g4 )"],["noop"],["noop"]],[["noop"],["noop"],["noop"],["noop"],["( move g2 g4 )","( move g1 f1 )","( move g2 e2 )","noop","( move f2 f3 )","( move f2 e2 )"],["noop"]],[["noop"],["noop"],["noop"],["noop"],["noop"],["( move c2 e4 )","( move c2 c4 )","( move c3 c4 )","( move d1 d2 )","noop","( move c2 d2 )","( move d1 e1 )","( move c3 d3 )"]],[["( move d4 e4 )","( move b1 c4 )","( move a1 b2 )","noop","( move d4 e3 )"],["noop"],["noop"],["noop"],["noop"],["noop"]],[["noop"],["( move e5 e4 )","noop","( move c7 d6 )","( move d5 e4 )","( move c7 c6 )","( move d5 d3 )"],["noop"],["noop"],["noop"],["noop"]],[["noop"],["noop"],["( move g6 e4 )","( move g5 f4 )","( move f6 f4 )","noop","( move g6 c4 )"],["noop"],["noop"],["noop"]],[["noop"],["noop"],["noop"],["( move f5 e4 )","( move g3 f3 )","( move g3 e1 )","noop"],["noop"],["noop"]],[["noop"],["noop"],["noop"],["noop"],["( move g1 f1 )","( move g4 c6 )","( move g4 e4 )","noop","( move f2 f3 )","( move g1 g2 )","( move f2 e2 )"],["noop"]],[["noop"],["noop"],["noop"],["noop"],["noop"],["( move d2 d3 )","( move c2 e4 )","( move c2 c4 )","( move d2 e2 )","( move c2 e2 )","( move c3 c4 )","noop","( move c3 d3 )"]],[["( move d4 e4 )","( move b1 c4 )","( move a1 b2 )","( move b1 d2 )","noop","( move d4 e3 )"],["noop"],["noop"],["noop"],["noop"],["noop"]],[["noop"],["( move d6 d4 )","( move d6 d2 )","( move e5 e4 )","noop","( move d5 d4 )","( move d5 e4 )","( move d6 f3 )"],["noop"],["noop"],["noop"],["noop"]],[["noop"],["noop"],["( move g6 e4 )","( move g6 e2 )","( move f4 f3 )","noop","( move g6 c4 )"],["noop"],["noop"],["noop"]],[["noop"],["noop"],["noop"],["( move f5 e4 )","( move g3 e1 )","noop","( move h1 f4 )"],["noop"],["noop"]],[["noop"],["noop"],["noop"],["noop"],["( move g4 f4 )","( move f2 f4 )","( move f1 e1 )","noop","( move f2 e2 )"],["noop"]],[["noop"],["noop"],["noop"],["noop"],["noop"],["( move d3 f6 )","( move c2 e4 )","( move d3 f4 )","( move c2 c4 )","( move c3 c4 )","noop","( move c2 d2 )"]],[["( move b1 c4 )","( move a1 b2 )","( move b1 d2 )","noop","( move e3 f4 )"],["noop"],["noop"],["noop"],["noop"],["noop"]],[["noop"],["( move d4 d2 )","( move e5 e4 )","noop","( move d4 f1 )","( move d5 e4 )"],["noop"],["noop"],["noop"],["noop"]],[["noop"],["noop"],["( move g6 e4 )","( move g6 e2 )","( move g5 f4 )","noop","( move f3 e2 )"],["noop"],["noop"],["noop"]],[["noop"],["noop"],["noop"],["( move f5 e4 )","( move g3 f3 )","noop","( move h1 f4 )"],["noop"],["noop"]],[["noop"],["noop"],["noop"],["noop"],["( move e1 d2 )","( move g4 c6 )","( move g4 e4 )","noop","( move f2 f3 )"],["noop"]],[["noop"],["noop"],["noop"],["noop"],["noop"],["( move c3 c5 )","noop","( move c2 d2 )"]],[["( move a1 b2 )","noop","( move c4 g4 )","( move e3 f3 )","( move c4 e4 )","( move a1 b1 )"],["noop"],["noop"],["noop"],["noop"],["noop"]],[["noop"],["( move d4 d2 )","( move e5 e4 )","noop","( move d4 f1 )","( move d5 e4 )","( move d4 f3 )"],["noop"],["noop"],["noop"],["noop"]],[["noop"],["noop"],["( move g6 e4 )","( move g6 g4 )","( move g5 g4 )","noop"],["noop"],["noop"],["noop"]],[["noop"],["noop"],["noop"],["( move f5 d4 )","( move g3 f3 )","noop"],["noop"],["noop"]],[["noop"],["noop"],["noop"],["noop"],["( move c6 c7 )","noop","( move f2 f3 )"],["noop"]],[["noop"],["noop"],["noop"],["noop"],["noop"],["( move c3 c5 )","( move d3 d4 )","noop"]],[["( move b1 d4 )","( move b1 c3 )","( move c4 d4 )","noop","( move e3 f3 )","( move b1 f3 )"],["noop"],["noop"],["noop"],["noop"],["noop"]],[["noop"],["noop","( move d2 f1 )"],["noop"],["noop"],["noop"],["noop"]],[["noop"],["noop"],["( move e2 d2 )","( move e4 c4 )","( move g5 g4 )","noop"],["noop"],["noop"],["noop"]],[["noop"],["noop"],["noop"],["( move g3 f3 )","noop"],["noop"],["noop"]],[["noop"],["noop"],["noop"],["noop"],["( move e1 d2 )","noop","( move f2 f3 )"],["noop"]],[["noop"],["noop"],["noop"],["noop"],["noop"],["( move c2 c3 )","noop","( move c2 d2 )"]],[["( move b1 c4 )","( move b1 c3 )","noop"],["noop"],["noop"],["noop"],["noop"],["noop"]],[["noop"],["noop","( move f1 g1 )"],["noop"],["noop"],["noop"],["noop"]],[["noop"],["noop"],["( move g5 g4 )","( move e2 c2 )","noop"],["noop"],["noop"],["noop"]],[["noop"],["noop"],["noop"],["noop","( move g3 f2 )"],["noop"],["noop"]],[["noop"],["noop"],["noop"],["noop"],["( move e1 c3 )","noop"],["noop"]],[["noop"],["noop"],["noop"],["noop"],["noop"],["noop"]],[["( move e3 g5 )","noop","( move e3 g3 )"],["noop"],["noop"],["noop"],["noop"],["noop"]],[["noop"],["( move e5 e3 )","( move e5 g3 )","noop","( move f1 g1 )"],["noop"],["noop"],["noop"],["noop"]],[["noop"],["noop"],["( move e4 e3 )","( move g4 g3 )","( move e2 c2 )","noop"],["noop"],["noop"],["noop"]],[["noop"],["noop"],["noop"],["( move f5 e4 )","noop","( move f4 e4 )"],["noop"],["noop"]],[["noop"],["noop"],["noop"],["noop"],["( move f3 f4 )","( move e1 c3 )","noop"],["noop"]],[["noop"],["noop"],["noop"],["noop"],["noop"],["( move d3 f6 )","( move d3 f4 )","noop"]],[["( move g5 h2 )","noop"],["noop"],["noop"],["noop"],["noop"],["noop"]],[["noop"],["( move e5 g3 )","( move e5 g5 )","noop","( move f1 g1 )","( move d5 f4 )"],["noop"],["noop"],["noop"],["noop"]],[["noop"],["noop"],["( move g4 g3 )","( move e2 e1 )","( move e3 e1 )","( move e2 c2 )","noop"],["noop"],["noop"],["noop"]],[["noop"],["noop"],["noop"],["( move f5 e5 )","noop","( move f2 e1 )"],["noop"],["noop"]],[["noop"],["noop"],["noop"],["noop"],["( move f3 f4 )","noop"],["noop"]],[["noop"],["noop"],["noop"],["noop"],["noop"],["( move d3 f4 )","noop"]]],"randomToken":"W4Qa5ucBNAbEbCjDEpRukkucObqsZyg1","roles":["red","yellow","green","teal","blue","magenta"],"playerNamesFromHost":["RandomGamer","RandomGamer","RandomGamer","RandomGamer","RandomGamer","RandomGamer"],"states":["( ( cell g4 blank ) ( cell b2 red ) ( cell d6 yellow ) ( cell f4 blank ) ( cell e2 blank ) ( cell g2 blue ) ( cell g3 blank ) ( cell e4 blank ) ( cell e1 blank ) ( cell d5 blank ) ( cell g5 blank ) ( cell e3 blank ) ( cell c5 blank ) ( cell d1 magenta ) ( cell f5 blank ) ( cell i1 teal ) ( cell f6 green ) ( cell g1 blue ) ( cell d2 blank ) ( cell h2 teal ) ( cell c3 blank ) ( cell h1 teal ) ( control red ) ( cell a1 red ) ( cell c1 magenta ) ( cell c7 yellow ) ( cell c2 magenta ) ( cell g6 green ) ( cell c6 yellow ) ( cell f1 blue ) ( cell b1 red ) ( step 1 ) ( cell f3 blank ) ( cell f2 blank ) ( cell e5 blank ) ( cell d4 blank ) ( cell d3 blank ) ( cell c4 blank ) ( cell g7 green ) )","( ( cell g4 blank ) ( cell d6 yellow ) ( cell f4 blank ) ( cell e2 blank ) ( cell b2 blank ) ( cell g3 blank ) ( cell g2 blue ) ( control yellow ) ( cell e4 blank ) ( cell e1 blank ) ( cell d5 blank ) ( cell g5 blank ) ( cell e3 blank ) ( cell c5 blank ) ( cell d1 magenta ) ( cell f5 blank ) ( cell c4 red ) ( cell i1 teal ) ( step 2 ) ( cell f6 green ) ( cell g1 blue ) ( cell d2 blank ) ( cell h2 teal ) ( cell c3 blank ) ( cell h1 teal ) ( cell a1 red ) ( cell c1 magenta ) ( cell c7 yellow ) ( cell g6 green ) ( cell c6 yellow ) ( cell c2 magenta ) ( cell f1 blue ) ( cell b1 red ) ( cell f3 blank ) ( cell f2 blank ) ( cell e5 blank ) ( cell d4 blank ) ( cell d3 blank ) ( cell g7 green ) )","( ( cell g4 blank ) ( cell d6 yellow ) ( cell f4 blank ) ( cell e2 blank ) ( cell b2 blank ) ( cell g3 blank ) ( cell g2 blue ) ( cell e4 blank ) ( cell e1 blank ) ( cell g5 blank ) ( cell e3 blank ) ( cell c5 blank ) ( cell c6 blank ) ( cell d1 magenta ) ( cell f5 blank ) ( cell c4 red ) ( cell i1 teal ) ( cell f6 green ) ( cell g1 blue ) ( cell d2 blank ) ( cell h2 teal ) ( control green ) ( cell c3 blank ) ( step 3 ) ( cell h1 teal ) ( cell a1 red ) ( cell c1 magenta ) ( cell c7 yellow ) ( cell g6 green ) ( cell c2 magenta ) ( cell f1 blue ) ( cell b1 red ) ( cell d5 yellow ) ( cell f3 blank ) ( cell f2 blank ) ( cell e5 blank ) ( cell d4 blank ) ( cell d3 blank ) ( cell g7 green ) )","( ( cell g4 blank ) ( cell d6 yellow ) ( cell f4 blank ) ( cell e2 blank ) ( cell g5 green ) ( cell b2 blank ) ( cell g3 blank ) ( cell g2 blue ) ( cell e4 blank ) ( cell e1 blank ) ( cell e3 blank ) ( cell c5 blank ) ( cell c6 blank ) ( cell d1 magenta ) ( cell f5 blank ) ( cell c4 red ) ( cell i1 teal ) ( cell f6 green ) ( cell g1 blue ) ( cell d2 blank ) ( cell h2 teal ) ( cell c3 blank ) ( cell h1 teal ) ( step 4 ) ( cell a1 red ) ( cell c1 magenta ) ( cell c7 yellow ) ( cell c2 magenta ) ( cell f1 blue ) ( cell b1 red ) ( control teal ) ( cell d5 yellow ) ( cell g6 blank ) ( cell f3 blank ) ( cell f2 blank ) ( cell e5 blank ) ( cell d4 blank ) ( cell d3 blank ) ( cell g7 green ) )","( ( cell g4 blank ) ( cell d6 yellow ) ( cell f4 blank ) ( cell e2 blank ) ( cell g5 green ) ( cell b2 blank ) ( cell g2 blue ) ( cell e4 blank ) ( cell i1 blank ) ( cell e1 blank ) ( cell e3 blank ) ( cell c5 blank ) ( cell c6 blank ) ( cell d1 magenta ) ( cell f5 blank ) ( cell c4 red ) ( cell f6 green ) ( cell g1 blue ) ( cell d2 blank ) ( cell h2 teal ) ( cell c3 blank ) ( cell h1 teal ) ( cell a1 red ) ( cell c1 magenta ) ( cell c7 yellow ) ( cell c2 magenta ) ( cell g3 teal ) ( cell f1 blue ) ( cell b1 red ) ( cell d5 yellow ) ( step 5 ) ( cell g6 blank ) ( cell f3 blank ) ( control blue ) ( cell f2 blank ) ( cell e5 blank ) ( cell d4 blank ) ( cell d3 blank ) ( cell g7 green ) )","( ( cell g4 blank ) ( control magenta ) ( cell d6 yellow ) ( cell f4 blank ) ( step 6 ) ( cell e2 blank ) ( cell g5 green ) ( cell b2 blank ) ( cell f1 blank ) ( cell g2 blue ) ( cell e4 blank ) ( cell i1 blank ) ( cell e1 blank ) ( cell e3 blank ) ( cell c5 blank ) ( cell c6 blank ) ( cell d1 magenta ) ( cell f5 blank ) ( cell c4 red ) ( cell f6 green ) ( cell g1 blue ) ( cell d2 blank ) ( cell h2 teal ) ( cell c3 blank ) ( cell h1 teal ) ( cell f2 blue ) ( cell a1 red ) ( cell c1 magenta ) ( cell c7 yellow ) ( cell c2 magenta ) ( cell g3 teal ) ( cell b1 red ) ( cell d5 yellow ) ( cell g6 blank ) ( cell f3 blank ) ( cell e5 blank ) ( cell d4 blank ) ( cell d3 blank ) ( cell g7 green ) )","( ( cell g4 blank ) ( cell d6 yellow ) ( cell f4 blank ) ( cell e2 blank ) ( step 7 ) ( cell g5 green ) ( cell b2 blank ) ( cell f1 blank ) ( cell g2 blue ) ( cell e4 blank ) ( cell i1 blank ) ( cell e1 blank ) ( cell c1 blank ) ( cell e3 blank ) ( cell c5 blank ) ( cell c6 blank ) ( cell d1 magenta ) ( cell f5 blank ) ( cell c4 red ) ( cell f6 green ) ( cell g1 blue ) ( cell d2 blank ) ( cell h2 teal ) ( cell h1 teal ) ( cell f2 blue ) ( control red ) ( cell a1 red ) ( cell c7 yellow ) ( cell c2 magenta ) ( cell g3 teal ) ( cell c3 magenta ) ( cell b1 red ) ( cell d5 yellow ) ( cell g6 blank ) ( cell f3 blank ) ( cell e5 blank ) ( cell d4 blank ) ( cell d3 blank ) ( cell g7 green ) )","( ( cell g4 blank ) ( cell d6 yellow ) ( cell f4 blank ) ( cell e2 blank ) ( cell g5 green ) ( cell b2 blank ) ( cell f1 blank ) ( cell g2 blue ) ( control yellow ) ( cell e4 blank ) ( cell i1 blank ) ( cell e1 blank ) ( cell c1 blank ) ( cell e3 blank ) ( cell c5 blank ) ( cell c6 blank ) ( cell d1 magenta ) ( cell f5 blank ) ( cell f6 green ) ( cell g1 blue ) ( cell d2 blank ) ( cell h2 teal ) ( cell h1 teal ) ( cell f2 blue ) ( cell a1 red ) ( cell c7 yellow ) ( cell c2 magenta ) ( cell g3 teal ) ( cell c3 magenta ) ( cell b1 red ) ( cell d4 red ) ( cell d5 yellow ) ( cell g6 blank ) ( cell f3 blank ) ( step 8 ) ( cell e5 blank ) ( cell d3 blank ) ( cell c4 blank ) ( cell g7 green ) )","( ( cell g4 blank ) ( cell f4 blank ) ( cell e2 blank ) ( cell g5 green ) ( cell b2 blank ) ( cell f1 blank ) ( cell g2 blue ) ( cell e4 blank ) ( cell i1 blank ) ( cell e1 blank ) ( cell c1 blank ) ( cell e3 blank ) ( cell c5 blank ) ( cell c6 blank ) ( cell d1 magenta ) ( cell f5 blank ) ( cell f6 green ) ( cell g1 blue ) ( cell d2 blank ) ( cell h2 teal ) ( control green ) ( step 9 ) ( cell h1 teal ) ( cell f2 blue ) ( cell a1 red ) ( cell c7 yellow ) ( cell e5 yellow ) ( cell c2 magenta ) ( cell g3 teal ) ( cell c3 magenta ) ( cell b1 red ) ( cell d6 blank ) ( cell d4 red ) ( cell d5 yellow ) ( cell g6 blank ) ( cell f3 blank ) ( cell d3 blank ) ( cell c4 blank ) ( cell g7 green ) )","( ( cell g4 blank ) ( cell f4 blank ) ( cell e2 blank ) ( cell g5 green ) ( cell b2 blank ) ( cell f1 blank ) ( cell g2 blue ) ( cell e4 blank ) ( cell i1 blank ) ( cell e1 blank ) ( cell c1 blank ) ( cell e3 blank ) ( cell c5 blank ) ( cell c6 blank ) ( cell d1 magenta ) ( cell f5 blank ) ( cell f6 green ) ( cell g7 blank ) ( cell g1 blue ) ( cell d2 blank ) ( cell h2 teal ) ( cell h1 teal ) ( cell f2 blue ) ( step 10 ) ( cell a1 red ) ( cell c7 yellow ) ( cell g6 green ) ( cell e5 yellow ) ( cell c2 magenta ) ( cell g3 teal ) ( cell c3 magenta ) ( cell b1 red ) ( cell d6 blank ) ( cell d4 red ) ( control teal ) ( cell d5 yellow ) ( cell f3 blank ) ( cell d3 blank ) ( cell c4 blank ) )","( ( cell g4 blank ) ( cell f5 teal ) ( cell f4 blank ) ( cell e2 blank ) ( step 11 ) ( cell g5 green ) ( cell b2 blank ) ( cell f1 blank ) ( cell g2 blue ) ( cell e4 blank ) ( cell i1 blank ) ( cell e1 blank ) ( cell c1 blank ) ( cell e3 blank ) ( cell c5 blank ) ( cell c6 blank ) ( cell d1 magenta ) ( cell f6 green ) ( cell g7 blank ) ( cell g1 blue ) ( cell d2 blank ) ( cell h1 teal ) ( cell f2 blue ) ( cell h2 blank ) ( cell a1 red ) ( cell c7 yellow ) ( cell g6 green ) ( cell e5 yellow ) ( cell c2 magenta ) ( cell g3 teal ) ( cell c3 magenta ) ( cell b1 red ) ( cell d6 blank ) ( cell d4 red ) ( cell d5 yellow ) ( cell f3 blank ) ( control blue ) ( cell d3 blank ) ( cell c4 blank ) )","( ( cell f5 teal ) ( control magenta ) ( cell f4 blank ) ( cell e2 blank ) ( cell g5 green ) ( cell b2 blank ) ( cell f1 blank ) ( cell e4 blank ) ( cell i1 blank ) ( cell e1 blank ) ( cell c1 blank ) ( cell e3 blank ) ( cell c5 blank ) ( cell c6 blank ) ( cell d1 magenta ) ( cell f6 green ) ( cell g7 blank ) ( cell g1 blue ) ( cell d2 blank ) ( cell g4 blue ) ( cell g2 blank ) ( cell h1 teal ) ( cell f2 blue ) ( cell h2 blank ) ( cell a1 red ) ( cell c7 yellow ) ( cell g6 green ) ( cell e5 yellow ) ( cell c2 magenta ) ( cell g3 teal ) ( cell c3 magenta ) ( cell b1 red ) ( cell d6 blank ) ( cell d4 red ) ( step 12 ) ( cell d5 yellow ) ( cell f3 blank ) ( cell d3 blank ) ( cell c4 blank ) )","( ( cell f5 teal ) ( cell f4 blank ) ( cell d1 blank ) ( cell e2 blank ) ( cell g5 green ) ( cell b2 blank ) ( cell f1 blank ) ( cell e4 blank ) ( cell i1 blank ) ( cell e1 blank ) ( cell c1 blank ) ( cell e3 blank ) ( cell c5 blank ) ( cell c6 blank ) ( cell f6 green ) ( cell g7 blank ) ( cell g1 blue ) ( cell d2 magenta ) ( cell g4 blue ) ( cell g2 blank ) ( step 13 ) ( cell h1 teal ) ( cell f2 blue ) ( control red ) ( cell h2 blank ) ( cell a1 red ) ( cell c7 yellow ) ( cell g6 green ) ( cell e5 yellow ) ( cell c2 magenta ) ( cell g3 teal ) ( cell c3 magenta ) ( cell b1 red ) ( cell d6 blank ) ( cell d4 red ) ( cell d5 yellow ) ( cell f3 blank ) ( cell d3 blank ) ( cell c4 blank ) )","( ( cell f5 teal ) ( cell f4 blank ) ( cell d1 blank ) ( cell e2 blank ) ( cell g5 green ) ( step 14 ) ( cell b2 blank ) ( cell f1 blank ) ( control yellow ) ( cell e4 blank ) ( cell i1 blank ) ( cell e1 blank ) ( cell c1 blank ) ( cell e3 blank ) ( cell c5 blank ) ( cell c6 blank ) ( cell f6 green ) ( cell g7 blank ) ( cell g1 blue ) ( cell d2 magenta ) ( cell g4 blue ) ( cell g2 blank ) ( cell h1 teal ) ( cell f2 blue ) ( cell h2 blank ) ( cell a1 red ) ( cell c7 yellow ) ( cell g6 green ) ( cell e5 yellow ) ( cell c2 magenta ) ( cell g3 teal ) ( cell c3 magenta ) ( cell b1 red ) ( cell d6 blank ) ( cell d4 red ) ( cell d5 yellow ) ( cell f3 blank ) ( cell d3 blank ) ( cell c4 blank ) )","( ( cell f5 teal ) ( cell d6 yellow ) ( cell f4 blank ) ( cell d1 blank ) ( cell e2 blank ) ( cell g5 green ) ( cell b2 blank ) ( cell f1 blank ) ( cell e4 blank ) ( cell i1 blank ) ( cell e1 blank ) ( cell c1 blank ) ( cell e3 blank ) ( cell c5 blank ) ( cell c6 blank ) ( cell c7 blank ) ( cell f6 green ) ( cell g7 blank ) ( cell g1 blue ) ( cell d2 magenta ) ( cell g4 blue ) ( control green ) ( cell g2 blank ) ( cell h1 teal ) ( cell f2 blue ) ( cell h2 blank ) ( cell a1 red ) ( cell g6 green ) ( cell e5 yellow ) ( cell c2 magenta ) ( cell g3 teal ) ( cell c3 magenta ) ( cell b1 red ) ( cell d4 red ) ( cell d5 yellow ) ( step 15 ) ( cell f3 blank ) ( cell d3 blank ) ( cell c4 blank ) )","( ( cell f5 teal ) ( cell d6 yellow ) ( cell d1 blank ) ( cell e2 blank ) ( cell g5 green ) ( cell b2 blank ) ( cell f1 blank ) ( cell e4 blank ) ( cell i1 blank ) ( cell e1 blank ) ( cell f6 blank ) ( cell c1 blank ) ( cell e3 blank ) ( cell c5 blank ) ( cell c6 blank ) ( cell c7 blank ) ( cell g7 blank ) ( cell g1 blue ) ( cell d2 magenta ) ( cell g4 blue ) ( cell g2 blank ) ( cell h1 teal ) ( cell f4 green ) ( cell f2 blue ) ( cell h2 blank ) ( cell a1 red ) ( cell g6 green ) ( cell e5 yellow ) ( cell c2 magenta ) ( cell g3 teal ) ( cell c3 magenta ) ( cell b1 red ) ( cell d4 red ) ( control teal ) ( step 16 ) ( cell d5 yellow ) ( cell f3 blank ) ( cell d3 blank ) ( cell c4 blank ) )","( ( cell f5 teal ) ( cell d6 yellow ) ( cell d1 blank ) ( cell e2 blank ) ( cell g5 green ) ( cell b2 blank ) ( cell f1 blank ) ( step 17 ) ( cell e4 blank ) ( cell i1 blank ) ( cell e1 blank ) ( cell f6 blank ) ( cell c1 blank ) ( cell e3 blank ) ( cell c5 blank ) ( cell c6 blank ) ( cell c7 blank ) ( cell g7 blank ) ( cell g1 blue ) ( cell d2 magenta ) ( cell g4 blue ) ( cell g2 blank ) ( cell h1 teal ) ( cell f4 green ) ( cell f2 blue ) ( cell h2 blank ) ( cell a1 red ) ( cell g6 green ) ( cell e5 yellow ) ( cell c2 magenta ) ( cell g3 teal ) ( cell c3 magenta ) ( cell b1 red ) ( cell d4 red ) ( cell d5 yellow ) ( cell f3 blank ) ( control blue ) ( cell d3 blank ) ( cell c4 blank ) )","( ( cell f5 teal ) ( control magenta ) ( cell d6 yellow ) ( cell d1 blank ) ( cell e2 blank ) ( cell g5 green ) ( cell b2 blank ) ( cell e4 blank ) ( cell i1 blank ) ( cell e1 blank ) ( cell f6 blank ) ( cell c1 blank ) ( cell e3 blank ) ( cell c5 blank ) ( cell c6 blank ) ( cell c7 blank ) ( step 18 ) ( cell g7 blank ) ( cell d2 magenta ) ( cell g4 blue ) ( cell g2 blank ) ( cell h1 teal ) ( cell f4 green ) ( cell f2 blue ) ( cell h2 blank ) ( cell a1 red ) ( cell g6 green ) ( cell e5 yellow ) ( cell c2 magenta ) ( cell g3 teal ) ( cell f1 blue ) ( cell c3 magenta ) ( cell b1 red ) ( cell d4 red ) ( cell d5 yellow ) ( cell f3 blank ) ( cell d3 blank ) ( cell c4 blank ) ( cell g1 blank ) )","( ( cell d3 magenta ) ( cell f5 teal ) ( cell d6 yellow ) ( cell d1 blank ) ( cell e2 blank ) ( cell g5 green ) ( cell b2 blank ) ( cell e4 blank ) ( cell i1 blank ) ( cell e1 blank ) ( cell f6 blank ) ( cell c1 blank ) ( cell e3 blank ) ( cell c5 blank ) ( cell c6 blank ) ( cell c7 blank ) ( cell g7 blank ) ( cell d2 blank ) ( cell g4 blue ) ( cell g2 blank ) ( cell h1 teal ) ( cell f4 green ) ( cell f2 blue ) ( control red ) ( cell h2 blank ) ( cell a1 red ) ( cell g6 green ) ( cell e5 yellow ) ( cell c2 magenta ) ( cell g3 teal ) ( cell f1 blue ) ( cell c3 magenta ) ( cell b1 red ) ( cell d4 red ) ( cell d5 yellow ) ( cell f3 blank ) ( step 19 ) ( cell c4 blank ) ( cell g1 blank ) )","( ( cell d3 magenta ) ( cell f5 teal ) ( cell d6 yellow ) ( cell d1 blank ) ( cell e2 blank ) ( cell g5 green ) ( cell b2 blank ) ( control yellow ) ( cell e4 blank ) ( cell i1 blank ) ( cell e1 blank ) ( cell f6 blank ) ( cell c1 blank ) ( cell c5 blank ) ( cell c6 blank ) ( cell c7 blank ) ( cell g7 blank ) ( cell d2 blank ) ( cell g4 blue ) ( cell g2 blank ) ( cell e3 red ) ( cell h1 teal ) ( cell f4 green ) ( cell f2 blue ) ( cell h2 blank ) ( cell a1 red ) ( cell g6 green ) ( cell e5 yellow ) ( cell c2 magenta ) ( cell g3 teal ) ( cell f1 blue ) ( cell c3 magenta ) ( cell b1 red ) ( cell d5 yellow ) ( cell f3 blank ) ( step 20 ) ( cell d4 blank ) ( cell c4 blank ) ( cell g1 blank ) )","( ( cell d3 magenta ) ( cell f5 teal ) ( cell d1 blank ) ( cell e2 blank ) ( cell g5 green ) ( cell b2 blank ) ( cell e4 blank ) ( cell i1 blank ) ( cell e1 blank ) ( cell f6 blank ) ( cell c1 blank ) ( cell c5 blank ) ( cell c6 blank ) ( cell c7 blank ) ( cell g7 blank ) ( cell d2 blank ) ( cell g4 blue ) ( control green ) ( cell g2 blank ) ( cell e3 red ) ( cell h1 teal ) ( cell f4 green ) ( cell f2 blue ) ( cell h2 blank ) ( cell a1 red ) ( cell g6 green ) ( cell e5 yellow ) ( cell c2 magenta ) ( cell g3 teal ) ( cell f1 blue ) ( cell c3 magenta ) ( cell b1 red ) ( cell d6 blank ) ( step 21 ) ( cell d5 yellow ) ( cell f3 blank ) ( cell d4 yellow ) ( cell c4 blank ) ( cell g1 blank ) )","( ( cell d3 magenta ) ( cell f5 teal ) ( cell f4 blank ) ( cell d1 blank ) ( cell e2 blank ) ( cell g5 green ) ( cell b2 blank ) ( cell e4 blank ) ( cell i1 blank ) ( cell e1 blank ) ( step 22 ) ( cell f6 blank ) ( cell c1 blank ) ( cell c5 blank ) ( cell c6 blank ) ( cell c7 blank ) ( cell g7 blank ) ( cell d2 blank ) ( cell g4 blue ) ( cell g2 blank ) ( cell f3 green ) ( cell e3 red ) ( cell h1 teal ) ( cell f2 blue ) ( cell h2 blank ) ( cell a1 red ) ( cell g6 green ) ( cell e5 yellow ) ( cell c2 magenta ) ( cell g3 teal ) ( cell f1 blue ) ( cell c3 magenta ) ( cell b1 red ) ( cell d6 blank ) ( control teal ) ( cell d5 yellow ) ( cell d4 yellow ) ( cell c4 blank ) ( cell g1 blank ) )","( ( cell d3 magenta ) ( cell f5 teal ) ( cell f4 blank ) ( cell d1 blank ) ( cell e2 blank ) ( cell g5 green ) ( step 23 ) ( cell b2 blank ) ( cell e4 blank ) ( cell i1 blank ) ( cell e1 blank ) ( cell f6 blank ) ( cell c1 blank ) ( cell c5 blank ) ( cell c6 blank ) ( cell c7 blank ) ( cell g7 blank ) ( cell d2 blank ) ( cell g4 blue ) ( cell g2 blank ) ( cell f3 green ) ( cell e3 red ) ( cell h1 teal ) ( cell f2 blue ) ( cell h2 blank ) ( cell a1 red ) ( cell g6 green ) ( cell e5 yellow ) ( cell c2 magenta ) ( cell g3 teal ) ( cell f1 blue ) ( cell c3 magenta ) ( cell b1 red ) ( cell d6 blank ) ( cell d5 yellow ) ( control blue ) ( cell d4 yellow ) ( cell c4 blank ) ( cell g1 blank ) )","( ( cell d3 magenta ) ( cell f5 teal ) ( control magenta ) ( cell f4 blank ) ( cell d1 blank ) ( cell e2 blank ) ( step 24 ) ( cell g5 green ) ( cell b2 blank ) ( cell f1 blank ) ( cell e4 blank ) ( cell i1 blank ) ( cell f6 blank ) ( cell c1 blank ) ( cell c5 blank ) ( cell c6 blank ) ( cell c7 blank ) ( cell g7 blank ) ( cell d2 blank ) ( cell g4 blue ) ( cell g2 blank ) ( cell f3 green ) ( cell e3 red ) ( cell h1 teal ) ( cell f2 blue ) ( cell h2 blank ) ( cell a1 red ) ( cell g6 green ) ( cell e5 yellow ) ( cell c2 magenta ) ( cell g3 teal ) ( cell c3 magenta ) ( cell b1 red ) ( cell e1 blue ) ( cell d6 blank ) ( cell d5 yellow ) ( cell d4 yellow ) ( cell c4 blank ) ( cell g1 blank ) )","( ( cell d3 magenta ) ( cell f5 teal ) ( cell f4 blank ) ( cell d1 blank ) ( cell e2 blank ) ( cell g5 green ) ( cell b2 blank ) ( cell f1 blank ) ( cell e4 blank ) ( cell i1 blank ) ( cell f6 blank ) ( cell c1 blank ) ( cell c5 blank ) ( cell c6 blank ) ( cell c7 blank ) ( cell g7 blank ) ( cell d2 blank ) ( cell g4 blue ) ( cell g2 blank ) ( cell f3 green ) ( cell e3 red ) ( cell h1 teal ) ( cell f2 blue ) ( control red ) ( cell h2 blank ) ( cell a1 red ) ( cell g6 green ) ( cell e5 yellow ) ( cell c2 magenta ) ( cell g3 teal ) ( cell c3 magenta ) ( cell b1 red ) ( cell e1 blue ) ( cell d6 blank ) ( step 25 ) ( cell d5 yellow ) ( cell d4 yellow ) ( cell c4 blank ) ( cell g1 blank ) )","( ( cell d3 magenta ) ( cell f5 teal ) ( cell f4 blank ) ( cell d1 blank ) ( cell e2 blank ) ( cell g5 green ) ( cell b2 blank ) ( cell f1 blank ) ( control yellow ) ( cell b1 blank ) ( cell e4 blank ) ( cell i1 blank ) ( cell f6 blank ) ( cell c1 blank ) ( cell c5 blank ) ( cell c6 blank ) ( cell c4 red ) ( cell c7 blank ) ( cell g7 blank ) ( cell d2 blank ) ( cell g4 blue ) ( cell g2 blank ) ( step 26 ) ( cell f3 green ) ( cell e3 red ) ( cell h1 teal ) ( cell f2 blue ) ( cell h2 blank ) ( cell a1 red ) ( cell g6 green ) ( cell e5 yellow ) ( cell c2 magenta ) ( cell g3 teal ) ( cell c3 magenta ) ( cell e1 blue ) ( cell d6 blank ) ( cell d5 yellow ) ( cell d4 yellow ) ( cell g1 blank ) )","( ( cell d3 magenta ) ( cell f5 teal ) ( cell f4 blank ) ( cell d1 blank ) ( cell e2 blank ) ( cell g5 green ) ( cell b2 blank ) ( cell f1 blank ) ( cell b1 blank ) ( cell e4 blank ) ( cell i1 blank ) ( cell f6 blank ) ( cell c1 blank ) ( cell c5 blank ) ( cell c6 blank ) ( cell c4 red ) ( cell c7 blank ) ( cell g7 blank ) ( cell d2 blank ) ( cell g4 blue ) ( control green ) ( cell g2 blank ) ( cell f3 green ) ( cell e3 red ) ( cell h1 teal ) ( cell f2 blue ) ( cell h2 blank ) ( cell a1 red ) ( cell g6 green ) ( cell e5 yellow ) ( cell c2 magenta ) ( cell g3 teal ) ( cell c3 magenta ) ( cell e1 blue ) ( cell d6 blank ) ( cell d5 yellow ) ( cell d4 yellow ) ( step 27 ) ( cell g1 blank ) )","( ( cell d3 magenta ) ( cell f5 teal ) ( cell f4 blank ) ( cell d1 blank ) ( cell g5 green ) ( cell b2 blank ) ( cell f1 blank ) ( cell b1 blank ) ( cell e4 blank ) ( cell i1 blank ) ( cell f6 blank ) ( cell c1 blank ) ( cell c5 blank ) ( cell c6 blank ) ( cell c4 red ) ( cell c7 blank ) ( cell g7 blank ) ( cell d2 blank ) ( cell e2 green ) ( cell g4 blue ) ( cell g2 blank ) ( step 28 ) ( cell e3 red ) ( cell h1 teal ) ( cell f2 blue ) ( cell h2 blank ) ( cell a1 red ) ( cell g6 green ) ( cell e5 yellow ) ( cell c2 magenta ) ( cell g3 teal ) ( cell c3 magenta ) ( cell e1 blue ) ( cell d6 blank ) ( control teal ) ( cell d5 yellow ) ( cell f3 blank ) ( cell d4 yellow ) ( cell g1 blank ) )","( ( cell d3 magenta ) ( cell f5 teal ) ( cell d1 blank ) ( cell g5 green ) ( cell b2 blank ) ( cell f1 blank ) ( cell b1 blank ) ( cell e4 blank ) ( cell i1 blank ) ( cell f6 blank ) ( cell c1 blank ) ( cell c5 blank ) ( cell c6 blank ) ( cell c4 red ) ( step 29 ) ( cell c7 blank ) ( cell g7 blank ) ( cell f4 teal ) ( cell d2 blank ) ( cell e2 green ) ( cell g4 blue ) ( cell g2 blank ) ( cell e3 red ) ( cell f2 blue ) ( cell h2 blank ) ( cell a1 red ) ( cell g6 green ) ( cell e5 yellow ) ( cell c2 magenta ) ( cell g3 teal ) ( cell c3 magenta ) ( cell e1 blue ) ( cell d6 blank ) ( cell d5 yellow ) ( cell f3 blank ) ( control blue ) ( cell h1 blank ) ( cell d4 yellow ) ( cell g1 blank ) )","( ( cell d3 magenta ) ( cell g4 blank ) ( cell f5 teal ) ( control magenta ) ( cell d1 blank ) ( cell g5 green ) ( cell b2 blank ) ( cell f1 blank ) ( cell b1 blank ) ( cell e4 blank ) ( cell i1 blank ) ( cell f6 blank ) ( cell c1 blank ) ( cell c5 blank ) ( cell c4 red ) ( cell c7 blank ) ( cell g7 blank ) ( cell f4 teal ) ( cell d2 blank ) ( cell e2 green ) ( cell c6 blue ) ( cell g2 blank ) ( cell e3 red ) ( cell f2 blue ) ( cell h2 blank ) ( cell a1 red ) ( cell g6 green ) ( cell e5 yellow ) ( cell c2 magenta ) ( cell g3 teal ) ( cell c3 magenta ) ( cell e1 blue ) ( cell d6 blank ) ( step 30 ) ( cell d5 yellow ) ( cell f3 blank ) ( cell h1 blank ) ( cell d4 yellow ) ( cell g1 blank ) )","( ( cell d3 magenta ) ( cell g4 blank ) ( cell f5 teal ) ( cell d1 blank ) ( cell g5 green ) ( cell b2 blank ) ( cell f1 blank ) ( cell b1 blank ) ( cell e4 blank ) ( cell i1 blank ) ( cell f6 blank ) ( cell c1 blank ) ( cell c5 blank ) ( cell c4 red ) ( cell c7 blank ) ( cell g7 blank ) ( step 31 ) ( cell f4 teal ) ( cell d2 blank ) ( cell e2 green ) ( cell c6 blue ) ( cell g2 blank ) ( cell e3 red ) ( cell f2 blue ) ( control red ) ( cell h2 blank ) ( cell a1 red ) ( cell g6 green ) ( cell e5 yellow ) ( cell c2 magenta ) ( cell g3 teal ) ( cell c3 magenta ) ( cell e1 blue ) ( cell d6 blank ) ( cell d5 yellow ) ( cell f3 blank ) ( cell h1 blank ) ( cell d4 yellow ) ( cell g1 blank ) )","( ( cell d3 magenta ) ( cell g4 blank ) ( cell f5 teal ) ( cell d1 blank ) ( cell g5 green ) ( cell b2 blank ) ( cell f1 blank ) ( control yellow ) ( cell e4 blank ) ( cell i1 blank ) ( cell f6 blank ) ( cell c1 blank ) ( cell c5 blank ) ( cell c4 red ) ( cell c7 blank ) ( cell g7 blank ) ( cell f4 teal ) ( cell d2 blank ) ( cell e2 green ) ( cell c6 blue ) ( cell g2 blank ) ( cell e3 red ) ( cell f2 blue ) ( cell h2 blank ) ( step 32 ) ( cell g6 green ) ( cell e5 yellow ) ( cell c2 magenta ) ( cell g3 teal ) ( cell c3 magenta ) ( cell b1 red ) ( cell e1 blue ) ( cell d6 blank ) ( cell d5 yellow ) ( cell f3 blank ) ( cell h1 blank ) ( cell d4 yellow ) ( cell a1 blank ) ( cell g1 blank ) )","( ( cell d3 magenta ) ( cell g4 blank ) ( cell f5 teal ) ( cell d2 yellow ) ( cell d1 blank ) ( step 33 ) ( cell g5 green ) ( cell b2 blank ) ( cell f1 blank ) ( cell e4 blank ) ( cell i1 blank ) ( cell f6 blank ) ( cell c1 blank ) ( cell c5 blank ) ( cell c4 red ) ( cell c7 blank ) ( cell g7 blank ) ( cell f4 teal ) ( cell e2 green ) ( cell c6 blue ) ( control green ) ( cell g2 blank ) ( cell e3 red ) ( cell f2 blue ) ( cell h2 blank ) ( cell g6 green ) ( cell e5 yellow ) ( cell c2 magenta ) ( cell g3 teal ) ( cell c3 magenta ) ( cell b1 red ) ( cell e1 blue ) ( cell d6 blank ) ( cell d5 yellow ) ( cell f3 blank ) ( cell h1 blank ) ( cell d4 blank ) ( cell a1 blank ) ( cell g1 blank ) )","( ( cell d3 magenta ) ( cell g4 blank ) ( cell f5 teal ) ( cell d2 yellow ) ( cell d1 blank ) ( cell g5 green ) ( cell b2 blank ) ( cell f1 blank ) ( cell i1 blank ) ( cell f6 blank ) ( cell c1 blank ) ( cell c5 blank ) ( cell c4 red ) ( cell c7 blank ) ( cell g7 blank ) ( cell e4 green ) ( cell f4 teal ) ( cell e2 green ) ( cell c6 blue ) ( cell g2 blank ) ( step 34 ) ( cell e3 red ) ( cell f2 blue ) ( cell h2 blank ) ( cell e5 yellow ) ( cell c2 magenta ) ( cell g3 teal ) ( cell c3 magenta ) ( cell b1 red ) ( cell e1 blue ) ( cell d6 blank ) ( control teal ) ( cell d5 yellow ) ( cell g6 blank ) ( cell f3 blank ) ( cell h1 blank ) ( cell d4 blank ) ( cell a1 blank ) ( cell g1 blank ) )","( ( cell d3 magenta ) ( cell g4 blank ) ( cell f5 teal ) ( cell d2 yellow ) ( cell d1 blank ) ( cell g5 green ) ( cell b2 blank ) ( cell f1 blank ) ( cell i1 blank ) ( step 35 ) ( cell f6 blank ) ( cell c1 blank ) ( cell c5 blank ) ( cell c4 red ) ( cell c7 blank ) ( cell g7 blank ) ( cell e4 green ) ( cell f4 teal ) ( cell e2 green ) ( cell c6 blue ) ( cell g2 blank ) ( cell e3 red ) ( cell f2 blue ) ( cell h2 blank ) ( cell e5 yellow ) ( cell c2 magenta ) ( cell g3 teal ) ( cell c3 magenta ) ( cell b1 red ) ( cell e1 blue ) ( cell d6 blank ) ( cell d5 yellow ) ( cell g6 blank ) ( cell f3 blank ) ( control blue ) ( cell h1 blank ) ( cell d4 blank ) ( cell a1 blank ) ( cell g1 blank ) )","( ( cell d3 magenta ) ( cell g4 blank ) ( cell f5 teal ) ( control magenta ) ( cell d2 yellow ) ( cell d1 blank ) ( cell g5 green ) ( cell b2 blank ) ( cell f1 blank ) ( cell i1 blank ) ( cell f6 blank ) ( cell c1 blank ) ( cell c7 blue ) ( cell c5 blank ) ( cell c6 blank ) ( cell c4 red ) ( cell g7 blank ) ( cell e4 green ) ( cell f4 teal ) ( cell e2 green ) ( cell g2 blank ) ( cell e3 red ) ( cell f2 blue ) ( cell h2 blank ) ( cell e5 yellow ) ( cell c2 magenta ) ( cell g3 teal ) ( cell c3 magenta ) ( cell b1 red ) ( cell e1 blue ) ( cell d6 blank ) ( cell d5 yellow ) ( step 36 ) ( cell g6 blank ) ( cell f3 blank ) ( cell h1 blank ) ( cell d4 blank ) ( cell a1 blank ) ( cell g1 blank ) )","( ( cell d3 magenta ) ( cell g4 blank ) ( cell f5 teal ) ( cell c5 magenta ) ( cell d2 yellow ) ( cell d1 blank ) ( cell g5 green ) ( cell b2 blank ) ( cell f1 blank ) ( cell i1 blank ) ( cell f6 blank ) ( cell c1 blank ) ( cell c7 blue ) ( cell c6 blank ) ( cell c4 red ) ( cell g7 blank ) ( cell e4 green ) ( cell f4 teal ) ( cell e2 green ) ( cell g2 blank ) ( cell c3 blank ) ( cell e3 red ) ( step 37 ) ( cell f2 blue ) ( control red ) ( cell h2 blank ) ( cell e5 yellow ) ( cell c2 magenta ) ( cell g3 teal ) ( cell b1 red ) ( cell e1 blue ) ( cell d6 blank ) ( cell d5 yellow ) ( cell g6 blank ) ( cell f3 blank ) ( cell h1 blank ) ( cell d4 blank ) ( cell a1 blank ) ( cell g1 blank ) )","( ( cell d3 magenta ) ( cell g4 blank ) ( cell f5 teal ) ( cell c5 magenta ) ( cell d2 yellow ) ( cell d1 blank ) ( cell g5 green ) ( cell b2 blank ) ( cell f1 blank ) ( control yellow ) ( cell i1 blank ) ( cell f6 blank ) ( cell c1 blank ) ( cell c7 blue ) ( cell c6 blank ) ( cell g7 blank ) ( cell e4 green ) ( cell f4 teal ) ( cell e2 green ) ( step 38 ) ( cell g2 blank ) ( cell c3 blank ) ( cell e3 red ) ( cell f2 blue ) ( cell h2 blank ) ( cell e5 yellow ) ( cell c2 magenta ) ( cell g3 teal ) ( cell b1 red ) ( cell e1 blue ) ( cell d6 blank ) ( cell d4 red ) ( cell d5 yellow ) ( cell g6 blank ) ( cell f3 blank ) ( cell h1 blank ) ( cell a1 blank ) ( cell c4 blank ) ( cell g1 blank ) )","( ( cell d3 magenta ) ( cell g4 blank ) ( cell f5 teal ) ( cell c5 magenta ) ( cell d1 blank ) ( cell g5 green ) ( cell f1 yellow ) ( cell b2 blank ) ( cell i1 blank ) ( cell f6 blank ) ( cell c1 blank ) ( cell c7 blue ) ( cell c6 blank ) ( cell g7 blank ) ( cell e4 green ) ( cell f4 teal ) ( cell d2 blank ) ( cell e2 green ) ( control green ) ( cell g2 blank ) ( cell c3 blank ) ( cell e3 red ) ( cell f2 blue ) ( step 39 ) ( cell h2 blank ) ( cell e5 yellow ) ( cell c2 magenta ) ( cell g3 teal ) ( cell b1 red ) ( cell e1 blue ) ( cell d6 blank ) ( cell d4 red ) ( cell d5 yellow ) ( cell g6 blank ) ( cell f3 blank ) ( cell h1 blank ) ( cell a1 blank ) ( cell c4 blank ) ( cell g1 blank ) )","( ( cell d3 magenta ) ( cell g4 blank ) ( cell f5 teal ) ( cell c5 magenta ) ( cell d1 blank ) ( cell g5 green ) ( cell f1 yellow ) ( cell b2 blank ) ( cell i1 blank ) ( cell f6 blank ) ( cell c1 blank ) ( cell c7 blue ) ( cell c6 blank ) ( cell g7 blank ) ( cell e4 green ) ( cell f4 teal ) ( cell d2 blank ) ( cell e2 green ) ( cell g2 blank ) ( cell c3 blank ) ( cell e3 red ) ( cell f2 blue ) ( cell h2 blank ) ( cell e5 yellow ) ( cell c2 magenta ) ( cell g3 teal ) ( cell b1 red ) ( cell e1 blue ) ( cell d6 blank ) ( cell d4 red ) ( control teal ) ( cell d5 yellow ) ( cell g6 blank ) ( cell f3 blank ) ( cell h1 blank ) ( cell a1 blank ) ( step 40 ) ( cell c4 blank ) ( cell g1 blank ) )","( ( cell d3 magenta ) ( cell g4 blank ) ( cell f5 teal ) ( cell c5 magenta ) ( cell d1 blank ) ( cell g5 green ) ( cell f1 yellow ) ( cell b2 blank ) ( cell i1 blank ) ( cell f6 blank ) ( cell c1 blank ) ( cell c7 blue ) ( cell c6 blank ) ( cell g7 blank ) ( cell e4 green ) ( cell f4 teal ) ( cell d2 blank ) ( cell e2 green ) ( cell g2 blank ) ( cell c3 blank ) ( cell e3 red ) ( cell f2 blue ) ( cell h2 blank ) ( cell e5 yellow ) ( cell c2 magenta ) ( cell g3 teal ) ( cell b1 red ) ( cell e1 blue ) ( cell d6 blank ) ( cell d4 red ) ( cell d5 yellow ) ( cell g6 blank ) ( cell f3 blank ) ( control blue ) ( cell h1 blank ) ( step 41 ) ( cell a1 blank ) ( cell c4 blank ) ( cell g1 blank ) )","( ( cell d3 magenta ) ( cell g4 blank ) ( cell f5 teal ) ( control magenta ) ( cell c5 magenta ) ( step 42 ) ( cell d1 blank ) ( cell g5 green ) ( cell f1 yellow ) ( cell b2 blank ) ( cell i1 blank ) ( cell f3 blue ) ( cell f6 blank ) ( cell c1 blank ) ( cell c7 blue ) ( cell c6 blank ) ( cell g7 blank ) ( cell e4 green ) ( cell f4 teal ) ( cell d2 blank ) ( cell e2 green ) ( cell g2 blank ) ( cell c3 blank ) ( cell e3 red ) ( cell h2 blank ) ( cell e5 yellow ) ( cell c2 magenta ) ( cell g3 teal ) ( cell b1 red ) ( cell e1 blue ) ( cell d6 blank ) ( cell d4 red ) ( cell d5 yellow ) ( cell g6 blank ) ( cell h1 blank ) ( cell f2 blank ) ( cell a1 blank ) ( cell c4 blank ) ( cell g1 blank ) )","( ( cell d3 magenta ) ( cell g4 blank ) ( cell f5 teal ) ( cell c5 magenta ) ( cell d1 blank ) ( step 43 ) ( cell g5 green ) ( cell f1 yellow ) ( cell b2 blank ) ( cell i1 blank ) ( cell f3 blue ) ( cell f6 blank ) ( cell c1 blank ) ( cell c7 blue ) ( cell c6 blank ) ( cell g7 blank ) ( cell d2 magenta ) ( cell e4 green ) ( cell f4 teal ) ( cell e2 green ) ( cell c2 blank ) ( cell g2 blank ) ( cell c3 blank ) ( cell e3 red ) ( control red ) ( cell h2 blank ) ( cell e5 yellow ) ( cell g3 teal ) ( cell b1 red ) ( cell e1 blue ) ( cell d6 blank ) ( cell d4 red ) ( cell d5 yellow ) ( cell g6 blank ) ( cell h1 blank ) ( cell f2 blank ) ( cell a1 blank ) ( cell c4 blank ) ( cell g1 blank ) )","( ( cell d3 magenta ) ( cell g4 blank ) ( cell f5 teal ) ( cell c5 magenta ) ( cell d1 blank ) ( cell g5 green ) ( cell f1 yellow ) ( cell b2 blank ) ( control yellow ) ( cell b1 blank ) ( cell i1 blank ) ( cell f3 blue ) ( cell f6 blank ) ( cell c1 blank ) ( cell c7 blue ) ( cell c6 blank ) ( cell c4 red ) ( cell g7 blank ) ( cell d2 magenta ) ( cell e4 green ) ( cell f4 teal ) ( cell e2 green ) ( cell c2 blank ) ( cell g2 blank ) ( cell c3 blank ) ( cell e3 red ) ( cell h2 blank ) ( cell e5 yellow ) ( cell g3 teal ) ( cell e1 blue ) ( cell d6 blank ) ( cell d4 red ) ( cell d5 yellow ) ( cell g6 blank ) ( cell h1 blank ) ( cell f2 blank ) ( step 44 ) ( cell a1 blank ) ( cell g1 blank ) )","( ( cell d3 magenta ) ( cell g4 blank ) ( cell f5 teal ) ( cell c5 magenta ) ( cell d1 blank ) ( cell g5 green ) ( cell f1 yellow ) ( cell b2 blank ) ( cell b1 blank ) ( cell i1 blank ) ( cell f3 blue ) ( cell f6 blank ) ( cell c1 blank ) ( cell c7 blue ) ( cell c6 blank ) ( cell c4 red ) ( cell g7 blank ) ( cell d2 magenta ) ( cell e4 green ) ( cell f4 teal ) ( cell e2 green ) ( control green ) ( cell c2 blank ) ( step 45 ) ( cell g2 blank ) ( cell c3 blank ) ( cell e3 red ) ( cell h2 blank ) ( cell e5 yellow ) ( cell g3 teal ) ( cell e1 blue ) ( cell d6 blank ) ( cell d4 red ) ( cell d5 yellow ) ( cell g6 blank ) ( cell h1 blank ) ( cell f2 blank ) ( cell a1 blank ) ( cell g1 blank ) )","( ( cell d3 magenta ) ( cell f5 teal ) ( cell c5 magenta ) ( cell d1 blank ) ( cell f1 yellow ) ( cell b2 blank ) ( cell b1 blank ) ( cell i1 blank ) ( cell f3 blue ) ( cell f6 blank ) ( cell c1 blank ) ( cell g5 blank ) ( cell c7 blue ) ( cell c6 blank ) ( cell c4 red ) ( cell g7 blank ) ( cell d2 magenta ) ( cell e4 green ) ( cell f4 teal ) ( cell e2 green ) ( cell c2 blank ) ( cell g2 blank ) ( cell c3 blank ) ( cell e3 red ) ( cell h2 blank ) ( cell e5 yellow ) ( cell g3 teal ) ( cell e1 blue ) ( cell d6 blank ) ( cell d4 red ) ( control teal ) ( cell g4 green ) ( cell d5 yellow ) ( cell g6 blank ) ( cell h1 blank ) ( cell f2 blank ) ( step 46 ) ( cell a1 blank ) ( cell g1 blank ) )","( ( cell d3 magenta ) ( cell f5 teal ) ( cell c5 magenta ) ( cell d1 blank ) ( cell f1 yellow ) ( cell b2 blank ) ( cell g3 blank ) ( cell b1 blank ) ( cell i1 blank ) ( cell f3 blue ) ( cell f6 blank ) ( cell c1 blank ) ( cell g5 blank ) ( cell c7 blue ) ( cell c6 blank ) ( cell c4 red ) ( cell g7 blank ) ( cell d2 magenta ) ( cell e4 green ) ( cell f4 teal ) ( cell e2 green ) ( cell c2 blank ) ( cell g2 blank ) ( cell c3 blank ) ( cell e3 red ) ( cell f2 teal ) ( cell h2 blank ) ( step 47 ) ( cell e5 yellow ) ( cell e1 blue ) ( cell d6 blank ) ( cell d4 red ) ( cell g4 green ) ( cell d5 yellow ) ( cell g6 blank ) ( control blue ) ( cell h1 blank ) ( cell a1 blank ) ( cell g1 blank ) )","( ( cell d3 magenta ) ( cell f5 teal ) ( control magenta ) ( cell c5 magenta ) ( cell d1 blank ) ( cell f1 yellow ) ( cell b2 blank ) ( cell g3 blank ) ( step 48 ) ( cell b1 blank ) ( cell i1 blank ) ( cell f3 blue ) ( cell f6 blank ) ( cell c1 blank ) ( cell g5 blank ) ( cell c7 blue ) ( cell c6 blank ) ( cell c4 red ) ( cell g7 blank ) ( cell d2 magenta ) ( cell e4 green ) ( cell f4 teal ) ( cell e2 green ) ( cell c2 blank ) ( cell g2 blank ) ( cell c3 blank ) ( cell e3 red ) ( cell f2 teal ) ( cell h2 blank ) ( cell e5 yellow ) ( cell e1 blue ) ( cell d6 blank ) ( cell d4 red ) ( cell g4 green ) ( cell d5 yellow ) ( cell g6 blank ) ( cell h1 blank ) ( cell a1 blank ) ( cell g1 blank ) )","( ( cell d3 magenta ) ( cell f5 teal ) ( cell c5 magenta ) ( cell d1 blank ) ( cell f1 yellow ) ( cell b2 blank ) ( cell g3 blank ) ( cell b1 blank ) ( cell i1 blank ) ( cell f3 blue ) ( cell f6 blank ) ( step 49 ) ( cell c1 blank ) ( cell g5 blank ) ( cell c7 blue ) ( cell c6 blank ) ( cell c4 red ) ( cell g7 blank ) ( cell d2 magenta ) ( cell e4 green ) ( cell f4 teal ) ( cell e2 green ) ( cell c2 blank ) ( cell g2 blank ) ( cell c3 blank ) ( cell e3 red ) ( control red ) ( cell f2 teal ) ( cell h2 blank ) ( cell e5 yellow ) ( cell e1 blue ) ( cell d6 blank ) ( cell d4 red ) ( cell g4 green ) ( cell d5 yellow ) ( cell g6 blank ) ( cell h1 blank ) ( cell a1 blank ) ( cell g1 blank ) )","( ( cell d3 magenta ) ( cell f5 teal ) ( cell c5 magenta ) ( cell d1 blank ) ( cell f1 yellow ) ( cell b2 blank ) ( cell g3 blank ) ( control yellow ) ( cell b1 blank ) ( cell i1 blank ) ( cell f3 blue ) ( step 50 ) ( cell f6 blank ) ( cell c1 blank ) ( cell e3 blank ) ( cell c7 blue ) ( cell c6 blank ) ( cell c4 red ) ( cell g5 red ) ( cell g7 blank ) ( cell d2 magenta ) ( cell e4 green ) ( cell f4 teal ) ( cell e2 green ) ( cell c2 blank ) ( cell g2 blank ) ( cell c3 blank ) ( cell f2 teal ) ( cell h2 blank ) ( cell e5 yellow ) ( cell e1 blue ) ( cell d6 blank ) ( cell d4 red ) ( cell g4 green ) ( cell d5 yellow ) ( cell g6 blank ) ( cell h1 blank ) ( cell a1 blank ) ( cell g1 blank ) )","( ( cell d3 magenta ) ( cell f5 teal ) ( cell c5 magenta ) ( cell d1 blank ) ( cell f1 yellow ) ( cell b2 blank ) ( cell g3 blank ) ( cell b1 blank ) ( cell i1 blank ) ( step 51 ) ( cell f3 blue ) ( cell f6 blank ) ( cell c1 blank ) ( cell e3 blank ) ( cell c7 blue ) ( cell c6 blank ) ( cell c4 red ) ( cell g5 red ) ( cell g7 blank ) ( cell d2 magenta ) ( cell e4 green ) ( cell f4 teal ) ( cell e2 green ) ( control green ) ( cell c2 blank ) ( cell g2 blank ) ( cell c3 blank ) ( cell f2 teal ) ( cell h2 blank ) ( cell e5 yellow ) ( cell e1 blue ) ( cell d6 blank ) ( cell d4 red ) ( cell g4 green ) ( cell d5 yellow ) ( cell g6 blank ) ( cell h1 blank ) ( cell a1 blank ) ( cell g1 blank ) )","( ( cell d3 magenta ) ( cell f5 teal ) ( cell c5 magenta ) ( cell d1 blank ) ( cell f1 yellow ) ( cell b2 blank ) ( cell g3 blank ) ( cell b1 blank ) ( cell e4 blank ) ( cell i1 blank ) ( cell f3 blue ) ( cell f6 blank ) ( cell c1 blank ) ( cell c7 blue ) ( cell c6 blank ) ( cell c4 red ) ( cell g5 red ) ( cell g7 blank ) ( cell d2 magenta ) ( cell f4 teal ) ( cell e2 green ) ( cell c2 blank ) ( cell g2 blank ) ( cell c3 blank ) ( cell f2 teal ) ( cell h2 blank ) ( cell e3 green ) ( cell e5 yellow ) ( cell e1 blue ) ( cell d6 blank ) ( cell d4 red ) ( control teal ) ( cell g4 green ) ( cell d5 yellow ) ( cell g6 blank ) ( step 52 ) ( cell h1 blank ) ( cell a1 blank ) ( cell g1 blank ) )","( ( cell d3 magenta ) ( cell f5 teal ) ( cell c5 magenta ) ( cell f4 blank ) ( cell d1 blank ) ( cell f1 yellow ) ( cell b2 blank ) ( cell g3 blank ) ( cell b1 blank ) ( cell i1 blank ) ( cell f3 blue ) ( cell f6 blank ) ( cell c1 blank ) ( cell c7 blue ) ( cell c6 blank ) ( cell c4 red ) ( step 53 ) ( cell g5 red ) ( cell g7 blank ) ( cell d2 magenta ) ( cell e2 green ) ( cell c2 blank ) ( cell g2 blank ) ( cell c3 blank ) ( cell f2 teal ) ( cell h2 blank ) ( cell e3 green ) ( cell e5 yellow ) ( cell e1 blue ) ( cell d6 blank ) ( cell d4 red ) ( cell g4 green ) ( cell d5 yellow ) ( cell g6 blank ) ( control blue ) ( cell h1 blank ) ( cell e4 teal ) ( cell a1 blank ) ( cell g1 blank ) )","( ( cell d3 magenta ) ( cell f5 teal ) ( control magenta ) ( cell c5 magenta ) ( cell f4 blank ) ( cell d1 blank ) ( cell f1 yellow ) ( cell b2 blank ) ( cell g3 blank ) ( cell b1 blank ) ( cell i1 blank ) ( cell e1 blank ) ( cell f3 blue ) ( cell f6 blank ) ( cell c1 blank ) ( cell c7 blue ) ( cell c6 blank ) ( cell c4 red ) ( cell g5 red ) ( cell c3 blue ) ( cell g7 blank ) ( step 54 ) ( cell d2 magenta ) ( cell e2 green ) ( cell c2 blank ) ( cell g2 blank ) ( cell f2 teal ) ( cell h2 blank ) ( cell e3 green ) ( cell e5 yellow ) ( cell d6 blank ) ( cell d4 red ) ( cell g4 green ) ( cell d5 yellow ) ( cell g6 blank ) ( cell h1 blank ) ( cell e4 teal ) ( cell a1 blank ) ( cell g1 blank ) )","( ( cell d3 magenta ) ( cell f5 teal ) ( cell c5 magenta ) ( cell f4 blank ) ( cell d1 blank ) ( cell f1 yellow ) ( cell b2 blank ) ( cell g3 blank ) ( cell b1 blank ) ( cell i1 blank ) ( cell e1 blank ) ( cell f3 blue ) ( cell f6 blank ) ( cell c1 blank ) ( cell c7 blue ) ( cell c6 blank ) ( cell c4 red ) ( cell g5 red ) ( cell c3 blue ) ( cell g7 blank ) ( cell d2 magenta ) ( cell e2 green ) ( cell c2 blank ) ( cell g2 blank ) ( control red ) ( cell f2 teal ) ( cell h2 blank ) ( cell e3 green ) ( cell e5 yellow ) ( cell d6 blank ) ( cell d4 red ) ( cell g4 green ) ( cell d5 yellow ) ( step 55 ) ( cell g6 blank ) ( cell h1 blank ) ( cell e4 teal ) ( cell a1 blank ) ( cell g1 blank ) )","( ( cell d3 magenta ) ( cell f5 teal ) ( cell c5 magenta ) ( cell f4 blank ) ( cell d1 blank ) ( cell f1 yellow ) ( cell b2 blank ) ( cell g3 blank ) ( control yellow ) ( cell b1 blank ) ( cell i1 blank ) ( cell e1 blank ) ( cell f3 blue ) ( step 56 ) ( cell f6 blank ) ( cell c1 blank ) ( cell g5 blank ) ( cell c7 blue ) ( cell c6 blank ) ( cell c4 red ) ( cell c3 blue ) ( cell g7 blank ) ( cell d2 magenta ) ( cell e2 green ) ( cell c2 blank ) ( cell g2 blank ) ( cell f2 teal ) ( cell e3 green ) ( cell e5 yellow ) ( cell h2 red ) ( cell d6 blank ) ( cell d4 red ) ( cell g4 green ) ( cell d5 yellow ) ( cell g6 blank ) ( cell h1 blank ) ( cell e4 teal ) ( cell a1 blank ) ( cell g1 blank ) )","( ( cell d3 magenta ) ( cell f5 teal ) ( cell c5 magenta ) ( cell f4 blank ) ( cell d1 blank ) ( cell f1 yellow ) ( cell b2 blank ) ( cell g3 blank ) ( cell b1 blank ) ( cell i1 blank ) ( cell e1 blank ) ( cell f3 blue ) ( cell f6 blank ) ( cell c1 blank ) ( step 57 ) ( cell c7 blue ) ( cell c6 blank ) ( cell c4 red ) ( cell c3 blue ) ( cell g7 blank ) ( cell d2 magenta ) ( cell g5 yellow ) ( cell e2 green ) ( control green ) ( cell c2 blank ) ( cell g2 blank ) ( cell f2 teal ) ( cell e3 green ) ( cell h2 red ) ( cell d6 blank ) ( cell d4 red ) ( cell g4 green ) ( cell d5 yellow ) ( cell g6 blank ) ( cell h1 blank ) ( cell e5 blank ) ( cell e4 teal ) ( cell a1 blank ) ( cell g1 blank ) )","( ( cell d3 magenta ) ( cell g4 blank ) ( cell f5 teal ) ( cell c5 magenta ) ( cell f4 blank ) ( cell d1 blank ) ( cell f1 yellow ) ( cell b2 blank ) ( cell b1 blank ) ( cell i1 blank ) ( cell e1 blank ) ( cell f3 blue ) ( cell f6 blank ) ( cell c1 blank ) ( cell c7 blue ) ( cell c6 blank ) ( step 58 ) ( cell c4 red ) ( cell c3 blue ) ( cell g7 blank ) ( cell d2 magenta ) ( cell g5 yellow ) ( cell e2 green ) ( cell c2 blank ) ( cell g2 blank ) ( cell f2 teal ) ( cell e3 green ) ( cell h2 red ) ( cell d6 blank ) ( cell d4 red ) ( control teal ) ( cell d5 yellow ) ( cell g6 blank ) ( cell g3 green ) ( cell h1 blank ) ( cell e5 blank ) ( cell e4 teal ) ( cell a1 blank ) ( cell g1 blank ) )","( ( cell d3 magenta ) ( cell g4 blank ) ( cell c5 magenta ) ( cell f4 blank ) ( cell d1 blank ) ( cell f1 yellow ) ( cell b2 blank ) ( cell e5 teal ) ( cell b1 blank ) ( cell i1 blank ) ( cell e1 blank ) ( cell f3 blue ) ( cell f6 blank ) ( cell c1 blank ) ( step 59 ) ( cell c7 blue ) ( cell c6 blank ) ( cell f5 blank ) ( cell c4 red ) ( cell c3 blue ) ( cell g7 blank ) ( cell d2 magenta ) ( cell g5 yellow ) ( cell e2 green ) ( cell c2 blank ) ( cell g2 blank ) ( cell f2 teal ) ( cell e3 green ) ( cell h2 red ) ( cell d6 blank ) ( cell d4 red ) ( cell d5 yellow ) ( cell g6 blank ) ( cell g3 green ) ( control blue ) ( cell h1 blank ) ( cell e4 teal ) ( cell a1 blank ) ( cell g1 blank ) )","( ( cell d3 magenta ) ( cell g4 blank ) ( control magenta ) ( cell c5 magenta ) ( cell f4 blank ) ( cell d1 blank ) ( cell f1 yellow ) ( cell b2 blank ) ( cell e5 teal ) ( cell b1 blank ) ( cell i1 blank ) ( cell e1 blank ) ( cell f3 blue ) ( cell f6 blank ) ( cell c1 blank ) ( cell c7 blue ) ( cell c6 blank ) ( cell f5 blank ) ( cell c4 red ) ( cell c3 blue ) ( cell g7 blank ) ( cell d2 magenta ) ( cell g5 yellow ) ( cell e2 green ) ( cell c2 blank ) ( step 60 ) ( cell g2 blank ) ( cell f2 teal ) ( cell e3 green ) ( cell h2 red ) ( cell d6 blank ) ( cell d4 red ) ( cell d5 yellow ) ( cell g6 blank ) ( cell g3 green ) ( cell h1 blank ) ( cell e4 teal ) ( cell a1 blank ) ( cell g1 blank ) )"],"playClock":15,"gameName":"Chinese Checkers","moves":[["( move b2 c4 )","noop","noop","noop","noop","noop"],["noop","( move c6 d5 )","noop","noop","noop","noop"],["noop","noop","( move g6 g5 )","noop","noop","noop"],["noop","noop","noop","( move i1 g3 )","noop","noop"],["noop","noop","noop","noop","( move f1 f2 )","noop"],["noop","noop","noop","noop","noop","( move c1 c3 )"],["( move c4 d4 )","noop","noop","noop","noop","noop"],["noop","( move d6 e5 )","noop","noop","noop","noop"],["noop","noop","( move g7 g6 )","noop","noop","noop"],["noop","noop","noop","( move h2 f5 )","noop","noop"],["noop","noop","noop","noop","( move g2 g4 )","noop"],["noop","noop","noop","noop","noop","( move d1 d2 )"],["noop","noop","noop","noop","noop","noop"],["noop","( move c7 d6 )","noop","noop","noop","noop"],["noop","noop","( move f6 f4 )","noop","noop","noop"],["noop","noop","noop","noop","noop","noop"],["noop","noop","noop","noop","( move g1 f1 )","noop"],["noop","noop","noop","noop","noop","( move d2 d3 )"],["( move d4 e3 )","noop","noop","noop","noop","noop"],["noop","( move d6 d4 )","noop","noop","noop","noop"],["noop","noop","( move f4 f3 )","noop","noop","noop"],["noop","noop","noop","noop","noop","noop"],["noop","noop","noop","noop","( move f1 e1 )","noop"],["noop","noop","noop","noop","noop","noop"],["( move b1 c4 )","noop","noop","noop","noop","noop"],["noop","noop","noop","noop","noop","noop"],["noop","noop","( move f3 e2 )","noop","noop","noop"],["noop","noop","noop","( move h1 f4 )","noop","noop"],["noop","noop","noop","noop","( move g4 c6 )","noop"],["noop","noop","noop","noop","noop","noop"],["( move a1 b1 )","noop","noop","noop","noop","noop"],["noop","( move d4 d2 )","noop","noop","noop","noop"],["noop","noop","( move g6 e4 )","noop","noop","noop"],["noop","noop","noop","noop","noop","noop"],["noop","noop","noop","noop","( move c6 c7 )","noop"],["noop","noop","noop","noop","noop","( move c3 c5 )"],["( move c4 d4 )","noop","noop","noop","noop","noop"],["noop","( move d2 f1 )","noop","noop","noop","noop"],["noop","noop","noop","noop","noop","noop"],["noop","noop","noop","noop","noop","noop"],["noop","noop","noop","noop","( move f2 f3 )","noop"],["noop","noop","noop","noop","noop","( move c2 d2 )"],["( move b1 c4 )","noop","noop","noop","noop","noop"],["noop","noop","noop","noop","noop","noop"],["noop","noop","( move g5 g4 )","noop","noop","noop"],["noop","noop","noop","( move g3 f2 )","noop","noop"],["noop","noop","noop","noop","noop","noop"],["noop","noop","noop","noop","noop","noop"],["( move e3 g5 )","noop","noop","noop","noop","noop"],["noop","noop","noop","noop","noop","noop"],["noop","noop","( move e4 e3 )","noop","noop","noop"],["noop","noop","noop","( move f4 e4 )","noop","noop"],["noop","noop","noop","noop","( move e1 c3 )","noop"],["noop","noop","noop","noop","noop","noop"],["( move g5 h2 )","noop","noop","noop","noop","noop"],["noop","( move e5 g5 )","noop","noop","noop","noop"],["noop","noop","( move g4 g3 )","noop","noop","noop"],["noop","noop","noop","( move f5 e5 )","noop","noop"],["noop","noop","noop","noop","noop","noop"]],"startTime":1584044346237,"stateTimes":[1584044346316,1584044347970,1584044348164,1584044348405,1584044348574,1584044348720,1584044348846,1584044349022,1584044349150,1584044349265,1584044349380,1584044349533,1584044349631,1584044349730,1584044349823,1584044349901,1584044350029,1584044350138,1584044350247,1584044350337,1584044350444,1584044350538,1584044350624,1584044350723,1584044350810,1584044350906,1584044350995,1584044351088,1584044351208,1584044351307,1584044351386,1584044351487,1584044351572,1584044351691,1584044351786,1584044351880,1584044351972,1584044352120,1584044352241,1584044352375,1584044352478,1584044352558,1584044352662,1584044352781,1584044352876,1584044352950,1584044353016,1584044353110,1584044353218,1584044353330,1584044353403,1584044353483,1584044353595,1584044353690,1584044353815,1584044353901,1584044353986,1584044354094,1584044354178,1584044354272],"scrambled":false,"matchId":"randomtraces.chinesecheckers.1584044346098","errors":[["","","","","",""],["","","","","",""],["","","","","",""],["","","","","",""],["","","","","",""],["","","","","",""],["","","","","",""],["","","","","",""],["","","","","",""],["","","","","",""],["","","","","",""],["","","","","",""],["","","","","",""],["","","","","",""],["","","","","",""],["","","","","",""],["","","","","",""],["","","","","",""],["","","","","",""],["","","","","",""],["","","","","",""],["","","","","",""],["","","","","",""],["","","","","",""],["","","","","",""],["","","","","",""],["","","","","",""],["","","","","",""],["","","","","",""],["","","","","",""],["","","","","",""],["","","","","",""],["","","","","",""],["","","","","",""],["","","","","",""],["","","","","",""],["","","","","",""],["","","","","",""],["","","","","",""],["","","","","",""],["","","","","",""],["","","","","",""],["","","","","",""],["","","","","",""],["","","","","",""],["","","","","",""],["","","","","",""],["","","","","",""],["","","","","",""],["","","","","",""],["","","","","",""],["","","","","",""],["","","","","",""],["","","","","",""],["","","","","",""],["","","","","",""],["","","","","",""],["","","","","",""],["","","","","",""],["","","","","",""]],"isCompleted":true,"isAborted":false,"previewClock":-1}