{"goalHistory":[[0,0],[5,0]],"startClock":30,"gameMetaURL":"http://127.0.0.1:9140/games/gt_centipede/v0/","goalValues":[5,0],"legalMoves":[[["continue","finish"],["noop"]],[["continue","finish"],["noop"]],[["noop"],["continue","finish"]]],"randomToken":"oyF5kYc09nHG4seowc10jHQlz4rZqIV3","roles":["white","black"],"playerNamesFromHost":["RandomGamer","RandomGamer"],"states":["( ( whitePayoff 5 ) ( blackPayoff 0 ) ( control white ) )","( ( whitePayoff 5 ) ( gameOver ) ( blackPayoff 0 ) ( control black ) )"],"playClock":15,"gameName":"gt_centipede","moves":[["finish","noop"]],"startTime":1584965552405,"stateTimes":[1584965552448,1584965552650],"scrambled":false,"matchId":"randomtraces_iggp.gt_centipede.1584965552398","errors":[["",""],["",""]],"isCompleted":true,"isAborted":false,"previewClock":-1}