{"goalHistory":[[5,5],[10,10],[15,10],[20,15],[25,20],[25,25],[25,25],[25,25],[25,25],[25,25],[25,30],[30,35],[30,35],[30,40],[30,40],[30,40],[35,45],[40,50],[45,50],[50,55]],"startClock":30,"gameMetaURL":"http://games.ggp.org/stanford/games/dualhamilton/v0/","goalValues":[50,55],"legalMoves":[[["( move b )","( move h )","( move e )"],["( move h )","( move b )","( move e )"]],[["( move g )","( move i )","( move a )"],["( move g )","( move i )","( move a )"]],[["( move j )","( move h )","( move r )"],["( move h )","( move b )","( move e )"]],[["( move k )","( move i )","( move b )"],["( move f )","( move a )","( move d )"]],[["( move j )","( move c )","( move a )"],["( move c )","( move n )","( move e )"]],[["( move k )","( move i )","( move b )"],["( move b )","( move l )","( move d )"]],[["( move j )","( move c )","( move a )"],["( move c )","( move n )","( move e )"]],[["( move b )","( move h )","( move e )"],["( move f )","( move a )","( move d )"]],[["( move g )","( move i )","( move a )"],["( move h )","( move b )","( move e )"]],[["( move b )","( move h )","( move e )"],["( move g )","( move i )","( move a )"]],[["( move g )","( move i )","( move a )"],["( move h )","( move j )","( move r )"]],[["( move q )","( move h )","( move f )"],["( move b )","( move k )","( move i )"]],[["( move g )","( move i )","( move a )"],["( move h )","( move j )","( move r )"]],[["( move b )","( move h )","( move e )"],["( move i )","( move s )","( move q )"]],[["( move g )","( move i )","( move a )"],["( move h )","( move j )","( move r )"]],[["( move j )","( move h )","( move r )"],["( move g )","( move i )","( move a )"]],[["( move q )","( move s )","( move i )"],["( move h )","( move f )","( move q )"]],[["( move k )","( move r )","( move t )"],["( move g )","( move p )","( move r )"]],[["( move s )","( move m )","( move p )"],["( move h )","( move f )","( move q )"]],[["( move l )","( move n )","( move t )"],["( move g )","( move o )","( move e )"]]],"randomToken":"a66ddh80aQTCQWflREHmcFoI9rJNMaqH","roles":["left","right"],"playerNamesFromHost":["RandomGamer","RandomGamer"],"states":["( ( location left a ) ( score left 5 ) ( step 1 ) ( score right 5 ) ( visited right a ) ( location right a ) ( visited left a ) )","( ( location right h ) ( step 2 ) ( visited left h ) ( visited right h ) ( location left h ) ( score left 10 ) ( visited right a ) ( score right 10 ) ( visited left a ) )","( ( score left 15 ) ( visited left h ) ( visited right h ) ( step 3 ) ( location left i ) ( visited right a ) ( score right 10 ) ( visited left i ) ( visited left a ) ( location right a ) )","( ( score left 20 ) ( visited left j ) ( location right e ) ( visited left h ) ( visited right h ) ( location left j ) ( visited right a ) ( visited right e ) ( score right 15 ) ( step 4 ) ( visited left i ) ( visited left a ) )","( ( score right 20 ) ( visited left b ) ( visited right d ) ( visited right e ) ( visited left a ) ( visited left j ) ( location left b ) ( location right d ) ( step 5 ) ( visited left h ) ( visited right h ) ( score left 25 ) ( visited right a ) ( visited left i ) )","( ( visited right c ) ( visited left b ) ( location left j ) ( step 6 ) ( visited right d ) ( score right 25 ) ( visited right e ) ( visited left a ) ( visited left j ) ( visited left h ) ( visited right h ) ( score left 25 ) ( visited right a ) ( location right c ) ( visited left i ) )","( ( step 7 ) ( visited right c ) ( visited left b ) ( visited right d ) ( score right 25 ) ( visited right e ) ( visited left a ) ( visited left j ) ( location left b ) ( location right d ) ( visited left h ) ( visited right h ) ( score left 25 ) ( visited right a ) ( visited left i ) )","( ( visited right c ) ( location right e ) ( visited left b ) ( visited right d ) ( step 8 ) ( score right 25 ) ( visited right e ) ( visited left a ) ( location left a ) ( visited left j ) ( visited left h ) ( visited right h ) ( score left 25 ) ( visited right a ) ( visited left i ) )","( ( visited right c ) ( visited left b ) ( step 9 ) ( location left h ) ( visited right d ) ( score right 25 ) ( visited right e ) ( visited left a ) ( visited left j ) ( visited left h ) ( visited right h ) ( score left 25 ) ( visited right a ) ( visited left i ) ( location right a ) )","( ( step 10 ) ( visited right c ) ( location right h ) ( visited left b ) ( visited right d ) ( score right 25 ) ( visited right e ) ( visited left a ) ( location left a ) ( visited left j ) ( visited left h ) ( visited right h ) ( score left 25 ) ( visited right a ) ( visited left i ) )","( ( visited right c ) ( visited left b ) ( location left h ) ( location right i ) ( visited right d ) ( visited right i ) ( visited right e ) ( visited left a ) ( visited left j ) ( score right 30 ) ( visited left h ) ( visited right h ) ( step 11 ) ( score left 25 ) ( visited right a ) ( visited left i ) )","( ( location left g ) ( visited right c ) ( visited left g ) ( step 12 ) ( visited left b ) ( score right 35 ) ( visited right j ) ( visited right d ) ( location right j ) ( visited right i ) ( visited right e ) ( visited left a ) ( visited left j ) ( score left 30 ) ( visited left h ) ( visited right h ) ( visited right a ) ( visited left i ) )","( ( step 13 ) ( visited right c ) ( visited left g ) ( visited left b ) ( location left h ) ( score right 35 ) ( location right i ) ( visited right j ) ( visited right d ) ( visited right i ) ( visited right e ) ( visited left a ) ( visited left j ) ( score left 30 ) ( visited left h ) ( visited right h ) ( visited right a ) ( visited left i ) )","( ( visited right c ) ( visited left g ) ( visited left b ) ( visited right j ) ( visited right d ) ( visited right i ) ( visited right e ) ( location right r ) ( visited left a ) ( location left a ) ( score right 40 ) ( visited left j ) ( step 14 ) ( score left 30 ) ( visited left h ) ( visited right h ) ( visited right a ) ( visited left i ) ( visited right r ) )","( ( visited right c ) ( visited left g ) ( visited left b ) ( location left h ) ( location right i ) ( visited right j ) ( visited right d ) ( visited right i ) ( visited right e ) ( visited left a ) ( score right 40 ) ( visited left j ) ( score left 30 ) ( visited left h ) ( visited right h ) ( visited right a ) ( step 15 ) ( visited left i ) ( visited right r ) )","( ( visited right c ) ( location right h ) ( visited left g ) ( visited left b ) ( visited right j ) ( visited right d ) ( location left i ) ( visited right i ) ( visited right e ) ( visited left a ) ( score right 40 ) ( visited left j ) ( score left 30 ) ( step 16 ) ( visited left h ) ( visited right h ) ( visited right a ) ( visited left i ) ( visited right r ) )","( ( score left 35 ) ( location right g ) ( visited right c ) ( visited left g ) ( visited left b ) ( score right 45 ) ( visited right j ) ( visited right d ) ( visited right i ) ( visited right e ) ( visited left r ) ( visited left a ) ( visited left j ) ( location left r ) ( visited left h ) ( visited right h ) ( visited right g ) ( visited right a ) ( step 17 ) ( visited left i ) ( visited right r ) )","( ( visited right q ) ( visited right c ) ( score left 40 ) ( visited left g ) ( location right q ) ( visited left b ) ( visited right j ) ( visited right d ) ( visited right i ) ( visited right e ) ( visited left r ) ( visited left a ) ( visited left j ) ( score right 50 ) ( step 18 ) ( visited left s ) ( visited left h ) ( visited right h ) ( location left s ) ( visited right g ) ( visited right a ) ( visited left i ) ( visited right r ) )","( ( visited right q ) ( location right g ) ( visited right c ) ( visited left g ) ( visited left b ) ( visited left t ) ( visited right j ) ( visited right d ) ( visited right i ) ( visited right e ) ( step 19 ) ( visited left r ) ( visited left a ) ( visited left j ) ( score right 50 ) ( location left t ) ( visited left s ) ( visited left h ) ( visited right h ) ( visited right g ) ( visited right a ) ( visited left i ) ( score left 45 ) ( visited right r ) )","( ( visited right q ) ( visited right c ) ( score right 55 ) ( visited left g ) ( visited left t ) ( location left m ) ( visited right i ) ( visited right e ) ( visited left r ) ( visited right f ) ( visited left s ) ( visited left h ) ( visited right a ) ( visited left i ) ( visited left b ) ( visited right d ) ( visited right j ) ( location right f ) ( visited left a ) ( visited left j ) ( visited left m ) ( score left 50 ) ( visited right h ) ( visited right g ) ( step 20 ) ( visited right r ) )"],"playClock":15,"gameName":"Dual Hamilton","moves":[["( move h )","( move h )"],["( move i )","( move a )"],["( move j )","( move e )"],["( move b )","( move d )"],["( move j )","( move c )"],["( move b )","( move d )"],["( move a )","( move e )"],["( move h )","( move a )"],["( move a )","( move h )"],["( move h )","( move i )"],["( move g )","( move j )"],["( move h )","( move i )"],["( move a )","( move r )"],["( move h )","( move i )"],["( move i )","( move h )"],["( move r )","( move g )"],["( move s )","( move q )"],["( move t )","( move g )"],["( move m )","( move f )"]],"startTime":1584034266914,"stateTimes":[1584034266980,1584034267389,1584034267437,1584034267458,1584034267483,1584034267501,1584034267516,1584034267543,1584034267567,1584034267585,1584034267610,1584034267639,1584034267672,1584034267706,1584034267728,1584034267750,1584034267773,1584034267781,1584034267810,1584034267853],"scrambled":false,"matchId":"randomtraces.dualhamilton.1584034266812","errors":[["",""],["",""],["",""],["",""],["",""],["",""],["",""],["",""],["",""],["",""],["",""],["",""],["",""],["",""],["",""],["",""],["",""],["",""],["",""],["",""]],"isCompleted":true,"isAborted":false,"previewClock":-1}