{"goalHistory":[[0,0,0,0],[0,0,0,0],[0,0,0,0],[0,0,0,0],[0,0,0,0],[0,0,0,0],[0,0,0,0],[0,0,0,0],[0,0,0,0],[0,0,0,0],[0,0,0,0],[0,0,0,0],[0,0,0,0],[0,0,0,0],[0,0,0,0],[0,0,0,0],[0,0,0,0],[0,0,0,0],[0,25,0,0],[0,25,25,0],[0,25,25,25],[0,25,25,25],[0,25,25,25],[0,25,25,25],[0,25,25,25],[25,25,25,25],[25,25,25,25],[25,25,25,25],[25,25,25,25],[25,25,25,25],[25,25,25,25],[25,25,25,25],[25,25,25,25],[25,25,25,25],[25,25,25,25],[25,25,50,25],[25,25,50,25],[25,25,50,25],[25,50,50,25],[25,50,50,25],[25,50,50,25],[25,50,50,25],[25,50,50,25],[25,50,50,25],[25,50,50,50],[50,50,50,50],[50,50,50,50],[50,50,100,50]],"startClock":30,"gameMetaURL":"http://games.ggp.org/stanford/games/chinesecheckers4/v0/","goalValues":[50,50,100,50],"legalMoves":[[["( move c6 d5 )","( move c7 e5 )","noop","( move d6 d5 )","( move d6 e5 )","( move c6 c5 )","( move c7 c5 )"],["noop"],["noop"],["noop"]],[["noop"],["( move g6 f5 )","( move f6 f5 )","( move g7 g5 )","( move g7 e5 )","( move g6 g5 )","noop","( move f6 e5 )"],["noop"],["noop"]],[["noop"],["noop"],["noop","( move g1 e1 )","( move g2 g3 )","( move f1 f2 )","( move f1 e1 )","( move g1 g3 )","( move g2 f2 )"],["noop"]],[["noop"],["noop"],["noop"],["( move c2 c3 )","( move d1 e1 )","( move c1 c3 )","( move c2 d2 )","noop","( move d1 d2 )","( move c1 e1 )"]],[["( move d6 f5 )","( move c6 d5 )","noop","( move d6 d5 )","( move c5 c4 )","( move c6 c4 )","( move c5 d4 )"],["noop"],["noop"],["noop"]],[["noop"],["( move g6 f5 )","( move f6 f5 )","( move e5 e4 )","( move g6 g5 )","( move e5 d5 )","( move f6 d5 )","noop"],["noop"],["noop"]],[["noop"],["noop"],["noop","( move f1 f2 )","( move g3 g4 )","( move g3 f3 )","( move f1 d2 )","( move g2 g4 )","( move g2 f2 )"],["noop"]],[["noop"],["noop"],["noop"],["( move c2 c3 )","( move e1 f2 )","( move e1 e2 )","( move d1 f2 )","( move c2 d2 )","noop","( move d1 d2 )"]],[["noop","( move d6 d5 )","( move c5 c3 )","( move c5 d4 )","( move c4 d3 )","( move c4 c3 )"],["noop"],["noop"],["noop"]],[["noop"],["( move f5 e4 )","( move e5 e4 )","( move f5 f4 )","( move e5 d5 )","( move f6 d5 )","noop","( move f6 f4 )"],["noop"],["noop"]],[["noop"],["noop"],["( move g4 g5 )","noop","( move f1 f2 )","( move g4 f4 )","( move g3 g5 )","( move g3 f3 )"],["noop"]],[["noop"],["noop"],["noop"],["( move e1 e2 )","( move d2 d3 )","noop","( move d2 e2 )","( move c2 e2 )"]],[["noop","( move d6 d4 )","( move c4 d3 )"],["noop"],["noop"],["noop"]],[["noop"],["( move f5 e4 )","( move d5 d4 )","( move e5 e4 )","( move f5 f4 )","noop","( move e5 c5 )","( move d5 c5 )"],["noop"],["noop"]],[["noop"],["noop"],["( move g4 g5 )","noop","( move g4 f4 )","( move f2 f3 )","( move g3 g5 )","( move g3 f3 )","( move g3 e5 )"],["noop"]],[["noop"],["noop"],["noop"],["( move d2 f3 )","( move e1 g5 )","( move e1 g3 )","( move d2 d4 )","( move e2 f3 )","( move e2 e3 )","noop","( move e1 e3 )"]],[["( move c3 e1 )","noop","( move d6 d4 )"],["noop"],["noop"],["noop"]],[["noop"],["( move e4 c2 )","( move f5 f4 )","( move e4 c4 )","( move e4 e3 )","noop","( move d5 c5 )"],["noop"],["noop"]],[["noop"],["noop"],["noop","( move e5 d6 )","( move g4 f4 )","( move f2 f3 )"],["noop"]],[["noop"],["noop"],["noop"],["( move d2 f3 )","( move g5 g6 )","( move e2 f3 )","( move e2 e3 )","noop"]],[["( move c3 e1 )","noop","( move d4 e3 )"],["noop"],["noop"],["noop"]],[["noop"],["( move f5 e4 )","( move f5 f4 )","( move c2 c1 )","noop","( move d5 c5 )"],["noop"],["noop"]],[["noop"],["noop"],["( move g4 g5 )","noop","( move g4 f4 )","( move f2 f3 )","( move d6 c7 )"],["noop"]],[["noop"],["noop"],["noop"],["( move d2 f3 )","( move g6 g7 )","( move e2 f3 )","( move e2 e3 )","noop"]],[["noop","( move d4 e3 )","( move e1 f1 )"],["noop"],["noop"],["noop"]],[["noop"],["( move f5 e4 )","( move f5 f4 )","noop","( move d5 c5 )"],["noop"],["noop"]],[["noop"],["noop"],["noop","( move f2 f3 )","( move g5 f5 )","( move d6 c7 )"],["noop"]],[["noop"],["noop"],["noop"],["( move d2 f3 )","( move e2 f3 )","( move e2 e3 )","noop"]],[["( move d4 d2 )","( move f1 g1 )","noop","( move d3 d2 )","( move d4 e3 )"],["noop"],["noop"],["noop"]],[["noop"],["( move d5 d4 )","( move e4 d4 )","noop","( move d5 c5 )"],["noop"],["noop"]],[["noop"],["noop"],["noop","( move f2 f4 )","( move f5 e5 )","( move d6 c7 )"],["noop"]],[["noop"],["noop"],["noop"],["( move e2 g4 )","( move f3 g4 )","noop","( move e2 e4 )","( move f3 f4 )"]],[["( move f1 g1 )","noop","( move e3 g3 )","( move d3 d2 )","( move d3 e2 )","( move e3 e2 )"],["noop"],["noop"],["noop"]],[["noop"],["( move d4 d2 )","( move d4 c4 )","noop","( move d5 c5 )"],["noop"],["noop"]],[["noop"],["noop"],["noop","( move f2 e2 )","( move e5 c7 )","( move f2 f4 )","( move d6 c7 )"],["noop"]],[["noop"],["noop"],["noop"],["( move e4 f5 )","( move e4 e5 )","( move f3 g4 )","noop","( move f3 f4 )"]],[["( move f1 g1 )","noop","( move d3 e2 )","( move g3 g2 )"],["noop"],["noop"],["noop"]],[["noop"],["( move d5 d4 )","( move d2 d1 )","noop","( move d2 c2 )","( move d5 c5 )"],["noop"],["noop"]],[["noop"],["noop"],["noop","( move f2 e2 )","( move f2 f3 )"],["noop"]],[["noop"],["noop"],["noop"],["( move e4 f5 )","( move e4 e5 )","( move f4 f5 )","noop","( move f4 g5 )"]],[["noop","( move d3 d2 )","( move d3 e2 )","( move g3 g2 )"],["noop"],["noop"],["noop"]],[["noop"],["( move d5 d4 )","noop","( move d5 c5 )"],["noop"],["noop"]],[["noop"],["noop"],["noop","( move f2 f3 )","( move f2 d3 )","( move f2 d5 )"],["noop"]],[["noop"],["noop"],["noop"],["( move f5 f6 )","( move e4 e5 )","noop","( move e4 g6 )","( move f5 g6 )"]],[["noop","( move e2 f2 )","( move g3 g2 )","( move e2 e1 )"],["noop"],["noop"],["noop"]],[["noop"],["( move d4 c4 )","noop","( move d4 d3 )"],["noop"],["noop"]],[["noop"],["noop"],["noop","( move d5 c6 )"],["noop"]],[["noop"],["noop"],["noop"],["( move e4 f5 )","( move e4 e5 )","noop"]]],"randomToken":"4GovQACGxXMk8wrfKdu8Uvaao8uGifxr","roles":["yellow","green","blue","magenta"],"playerNamesFromHost":["Sancho","Sancho","Sancho","Sancho"],"states":["( ( cell f1 blue ) ( cell f6 green ) ( cell c4 blank ) ( cell e4 blank ) ( cell f5 blank ) ( cell c3 blank ) ( cell b2 red ) ( cell g4 blank ) ( cell f4 blank ) ( cell g3 blank ) ( cell g5 blank ) ( cell g6 green ) ( cell d5 blank ) ( cell f3 blank ) ( cell e2 blank ) ( cell d1 magenta ) ( cell c2 magenta ) ( cell c1 magenta ) ( cell h1 teal ) ( cell d4 blank ) ( cell d3 blank ) ( cell d2 blank ) ( cell g7 green ) ( cell g2 blue ) ( cell a1 red ) ( cell e3 blank ) ( cell c7 yellow ) ( cell c6 yellow ) ( cell c5 blank ) ( step 1 ) ( cell d6 yellow ) ( cell i1 teal ) ( control yellow ) ( cell f2 blank ) ( cell b1 red ) ( cell h2 teal ) ( cell e5 blank ) ( cell e1 blank ) ( cell g1 blue ) )","( ( cell f1 blue ) ( cell f6 green ) ( cell c4 blank ) ( cell f5 blank ) ( control green ) ( cell e4 blank ) ( cell c3 blank ) ( cell b2 red ) ( cell g4 blank ) ( cell f4 blank ) ( cell g3 blank ) ( cell c5 yellow ) ( cell g6 green ) ( cell g5 blank ) ( cell d5 blank ) ( cell e2 blank ) ( cell f3 blank ) ( cell d1 magenta ) ( cell c2 magenta ) ( cell c1 magenta ) ( cell h1 teal ) ( cell d4 blank ) ( cell d3 blank ) ( cell c7 blank ) ( cell d2 blank ) ( cell g7 green ) ( cell g2 blue ) ( cell a1 red ) ( cell e3 blank ) ( cell c6 yellow ) ( cell d6 yellow ) ( cell i1 teal ) ( cell f2 blank ) ( cell h2 teal ) ( cell b1 red ) ( cell e5 blank ) ( cell e1 blank ) ( cell g1 blue ) ( step 2 ) )","( ( cell f1 blue ) ( cell f6 green ) ( cell c4 blank ) ( cell f5 blank ) ( cell e4 blank ) ( cell c3 blank ) ( cell b2 red ) ( cell g4 blank ) ( cell f4 blank ) ( cell g3 blank ) ( cell c5 yellow ) ( cell g6 green ) ( cell g5 blank ) ( cell d5 blank ) ( cell e2 blank ) ( cell f3 blank ) ( cell d1 magenta ) ( cell c2 magenta ) ( cell c1 magenta ) ( cell h1 teal ) ( cell d4 blank ) ( cell d3 blank ) ( cell c7 blank ) ( cell d2 blank ) ( cell g2 blue ) ( cell a1 red ) ( cell e3 blank ) ( cell c6 yellow ) ( cell d6 yellow ) ( cell i1 teal ) ( cell f2 blank ) ( cell h2 teal ) ( cell g7 blank ) ( cell b1 red ) ( cell e1 blank ) ( step 3 ) ( cell g1 blue ) ( cell e5 green ) ( control blue ) )","( ( cell f1 blue ) ( cell f6 green ) ( cell g3 blue ) ( cell c4 blank ) ( cell f5 blank ) ( cell e4 blank ) ( cell c3 blank ) ( cell b2 red ) ( cell g4 blank ) ( cell f4 blank ) ( cell c5 yellow ) ( cell g6 green ) ( cell g5 blank ) ( cell d5 blank ) ( cell e2 blank ) ( cell f3 blank ) ( cell d1 magenta ) ( cell c2 magenta ) ( cell c1 magenta ) ( cell h1 teal ) ( cell d4 blank ) ( cell d3 blank ) ( cell c7 blank ) ( cell d2 blank ) ( control magenta ) ( cell g2 blue ) ( cell a1 red ) ( cell g1 blank ) ( cell e3 blank ) ( cell c6 yellow ) ( step 4 ) ( cell d6 yellow ) ( cell i1 teal ) ( cell f2 blank ) ( cell h2 teal ) ( cell g7 blank ) ( cell b1 red ) ( cell e1 blank ) ( cell e5 green ) )","( ( cell f1 blue ) ( cell f6 green ) ( cell g3 blue ) ( cell c4 blank ) ( cell f5 blank ) ( cell e4 blank ) ( cell c3 blank ) ( cell b2 red ) ( cell g4 blank ) ( cell f4 blank ) ( step 5 ) ( cell c5 yellow ) ( cell g6 green ) ( cell g5 blank ) ( cell d5 blank ) ( cell e2 blank ) ( cell f3 blank ) ( cell d1 magenta ) ( cell c2 magenta ) ( cell h1 teal ) ( cell d4 blank ) ( cell d3 blank ) ( cell c7 blank ) ( cell d2 blank ) ( cell c1 blank ) ( cell g2 blue ) ( cell a1 red ) ( cell g1 blank ) ( cell e3 blank ) ( cell c6 yellow ) ( cell e1 magenta ) ( cell d6 yellow ) ( cell i1 teal ) ( control yellow ) ( cell f2 blank ) ( cell h2 teal ) ( cell g7 blank ) ( cell b1 red ) ( cell e5 green ) )","( ( cell f1 blue ) ( cell f6 green ) ( cell g3 blue ) ( cell f5 blank ) ( control green ) ( cell e4 blank ) ( cell c3 blank ) ( cell b2 red ) ( cell g4 blank ) ( cell f4 blank ) ( cell c5 yellow ) ( cell c6 blank ) ( cell g6 green ) ( cell g5 blank ) ( cell d5 blank ) ( cell e2 blank ) ( cell f3 blank ) ( cell d1 magenta ) ( cell c2 magenta ) ( cell h1 teal ) ( cell d4 blank ) ( cell d3 blank ) ( cell c7 blank ) ( cell d2 blank ) ( step 6 ) ( cell c4 yellow ) ( cell c1 blank ) ( cell g2 blue ) ( cell a1 red ) ( cell g1 blank ) ( cell e3 blank ) ( cell e1 magenta ) ( cell d6 yellow ) ( cell i1 teal ) ( cell f2 blank ) ( cell h2 teal ) ( cell g7 blank ) ( cell b1 red ) ( cell e5 green ) )","( ( cell f1 blue ) ( cell f6 green ) ( cell g3 blue ) ( cell e4 blank ) ( cell c3 blank ) ( cell b2 red ) ( cell g4 blank ) ( cell f4 blank ) ( cell f5 green ) ( cell c5 yellow ) ( cell c6 blank ) ( cell g5 blank ) ( cell d5 blank ) ( cell e2 blank ) ( cell f3 blank ) ( cell d1 magenta ) ( cell c2 magenta ) ( cell h1 teal ) ( cell d4 blank ) ( cell d3 blank ) ( cell c7 blank ) ( cell d2 blank ) ( cell c4 yellow ) ( cell c1 blank ) ( cell g2 blue ) ( cell a1 red ) ( cell g1 blank ) ( cell e3 blank ) ( cell g6 blank ) ( cell e1 magenta ) ( cell d6 yellow ) ( cell i1 teal ) ( cell f2 blank ) ( cell h2 teal ) ( cell g7 blank ) ( cell b1 red ) ( step 7 ) ( cell e5 green ) ( control blue ) )","( ( cell f1 blue ) ( cell f6 green ) ( cell g3 blue ) ( cell e4 blank ) ( cell c3 blank ) ( cell b2 red ) ( cell f4 blank ) ( cell f5 green ) ( cell c5 yellow ) ( cell c6 blank ) ( cell g5 blank ) ( cell d5 blank ) ( cell e2 blank ) ( cell f3 blank ) ( step 8 ) ( cell d1 magenta ) ( cell c2 magenta ) ( cell h1 teal ) ( cell d4 blank ) ( cell d3 blank ) ( cell c7 blank ) ( cell d2 blank ) ( control magenta ) ( cell c4 yellow ) ( cell g2 blank ) ( cell c1 blank ) ( cell a1 red ) ( cell g1 blank ) ( cell e3 blank ) ( cell g4 blue ) ( cell g6 blank ) ( cell e1 magenta ) ( cell d6 yellow ) ( cell i1 teal ) ( cell f2 blank ) ( cell h2 teal ) ( cell g7 blank ) ( cell b1 red ) ( cell e5 green ) )","( ( cell f1 blue ) ( cell f6 green ) ( cell g3 blue ) ( cell e4 blank ) ( cell c3 blank ) ( cell b2 red ) ( cell f4 blank ) ( cell f5 green ) ( cell c5 yellow ) ( cell c6 blank ) ( cell g5 blank ) ( cell d5 blank ) ( cell e2 blank ) ( cell f3 blank ) ( cell c2 magenta ) ( cell h1 teal ) ( cell d4 blank ) ( cell d3 blank ) ( step 9 ) ( cell c7 blank ) ( cell c4 yellow ) ( cell g2 blank ) ( cell c1 blank ) ( cell a1 red ) ( cell g1 blank ) ( cell e3 blank ) ( cell d1 blank ) ( cell g4 blue ) ( cell g6 blank ) ( cell e1 magenta ) ( cell d6 yellow ) ( cell i1 teal ) ( cell d2 magenta ) ( control yellow ) ( cell f2 blank ) ( cell h2 teal ) ( cell g7 blank ) ( cell b1 red ) ( cell e5 green ) )","( ( cell f1 blue ) ( cell f6 green ) ( cell g3 blue ) ( control green ) ( cell e4 blank ) ( cell b2 red ) ( cell f4 blank ) ( cell c3 yellow ) ( cell f5 green ) ( step 10 ) ( cell c6 blank ) ( cell g5 blank ) ( cell d5 blank ) ( cell e2 blank ) ( cell f3 blank ) ( cell c2 magenta ) ( cell h1 teal ) ( cell d4 blank ) ( cell d3 blank ) ( cell c7 blank ) ( cell c4 yellow ) ( cell g2 blank ) ( cell c1 blank ) ( cell a1 red ) ( cell g1 blank ) ( cell e3 blank ) ( cell d1 blank ) ( cell g4 blue ) ( cell g6 blank ) ( cell c5 blank ) ( cell e1 magenta ) ( cell d6 yellow ) ( cell i1 teal ) ( cell d2 magenta ) ( cell f2 blank ) ( cell h2 teal ) ( cell g7 blank ) ( cell b1 red ) ( cell e5 green ) )","( ( cell f1 blue ) ( cell g3 blue ) ( cell e4 blank ) ( cell b2 red ) ( cell f4 blank ) ( cell c3 yellow ) ( cell f5 green ) ( cell c6 blank ) ( cell g5 blank ) ( cell e2 blank ) ( cell f3 blank ) ( cell c2 magenta ) ( cell h1 teal ) ( cell d4 blank ) ( cell d3 blank ) ( cell f6 blank ) ( cell c7 blank ) ( cell c4 yellow ) ( cell g2 blank ) ( cell c1 blank ) ( cell a1 red ) ( cell g1 blank ) ( cell e3 blank ) ( cell d1 blank ) ( cell g4 blue ) ( cell g6 blank ) ( cell c5 blank ) ( cell e1 magenta ) ( cell d6 yellow ) ( cell i1 teal ) ( cell d2 magenta ) ( cell d5 green ) ( cell f2 blank ) ( cell h2 teal ) ( cell g7 blank ) ( cell b1 red ) ( step 11 ) ( cell e5 green ) ( control blue ) )","( ( cell g3 blue ) ( cell e4 blank ) ( cell b2 red ) ( cell f4 blank ) ( cell c3 yellow ) ( cell f5 green ) ( cell c6 blank ) ( cell f2 blue ) ( cell g5 blank ) ( cell e2 blank ) ( cell f3 blank ) ( cell c2 magenta ) ( step 12 ) ( cell h1 teal ) ( cell d4 blank ) ( cell d3 blank ) ( cell f6 blank ) ( cell c7 blank ) ( control magenta ) ( cell c4 yellow ) ( cell g2 blank ) ( cell c1 blank ) ( cell a1 red ) ( cell g1 blank ) ( cell e3 blank ) ( cell d1 blank ) ( cell g4 blue ) ( cell g6 blank ) ( cell c5 blank ) ( cell e1 magenta ) ( cell d6 yellow ) ( cell i1 teal ) ( cell d2 magenta ) ( cell d5 green ) ( cell h2 teal ) ( cell g7 blank ) ( cell b1 red ) ( cell f1 blank ) ( cell e5 green ) )","( ( step 13 ) ( cell g3 blue ) ( cell e4 blank ) ( cell b2 red ) ( cell f4 blank ) ( cell c3 yellow ) ( cell f5 green ) ( cell c6 blank ) ( cell f2 blue ) ( cell c2 blank ) ( cell g5 blank ) ( cell f3 blank ) ( cell h1 teal ) ( cell d4 blank ) ( cell d3 blank ) ( cell f6 blank ) ( cell c7 blank ) ( cell c4 yellow ) ( cell g2 blank ) ( cell c1 blank ) ( cell a1 red ) ( cell g1 blank ) ( cell e3 blank ) ( cell d1 blank ) ( cell g4 blue ) ( cell g6 blank ) ( cell c5 blank ) ( cell e1 magenta ) ( cell d6 yellow ) ( cell i1 teal ) ( cell d2 magenta ) ( cell d5 green ) ( control yellow ) ( cell h2 teal ) ( cell g7 blank ) ( cell b1 red ) ( cell f1 blank ) ( cell e5 green ) ( cell e2 magenta ) )","( ( cell g3 blue ) ( cell d3 yellow ) ( cell c4 blank ) ( control green ) ( cell e4 blank ) ( cell b2 red ) ( cell f4 blank ) ( cell c3 yellow ) ( cell f5 green ) ( cell c6 blank ) ( cell f2 blue ) ( cell c2 blank ) ( cell g5 blank ) ( cell f3 blank ) ( cell h1 teal ) ( cell d4 blank ) ( cell f6 blank ) ( cell c7 blank ) ( cell g2 blank ) ( cell c1 blank ) ( cell a1 red ) ( cell g1 blank ) ( cell e3 blank ) ( cell d1 blank ) ( cell g4 blue ) ( cell g6 blank ) ( cell c5 blank ) ( cell e1 magenta ) ( cell d6 yellow ) ( cell i1 teal ) ( cell d2 magenta ) ( cell d5 green ) ( cell h2 teal ) ( cell g7 blank ) ( cell b1 red ) ( cell f1 blank ) ( step 14 ) ( cell e5 green ) ( cell e2 magenta ) )","( ( cell g3 blue ) ( cell d3 yellow ) ( cell c4 blank ) ( cell b2 red ) ( cell f4 blank ) ( cell c3 yellow ) ( cell f5 green ) ( cell c6 blank ) ( cell f2 blue ) ( cell c2 blank ) ( cell g5 blank ) ( cell f3 blank ) ( cell h1 teal ) ( cell d4 blank ) ( cell f6 blank ) ( cell c7 blank ) ( cell g2 blank ) ( cell c1 blank ) ( cell a1 red ) ( cell e4 green ) ( cell g1 blank ) ( cell e3 blank ) ( cell d1 blank ) ( cell g4 blue ) ( cell g6 blank ) ( cell c5 blank ) ( step 15 ) ( cell e1 magenta ) ( cell d6 yellow ) ( cell i1 teal ) ( cell d2 magenta ) ( cell d5 green ) ( cell h2 teal ) ( cell g7 blank ) ( cell b1 red ) ( cell e5 blank ) ( cell f1 blank ) ( control blue ) ( cell e2 magenta ) )","( ( cell d3 yellow ) ( cell c4 blank ) ( cell b2 red ) ( cell f4 blank ) ( cell c3 yellow ) ( cell g3 blank ) ( cell f5 green ) ( cell c6 blank ) ( cell f2 blue ) ( cell c2 blank ) ( cell g5 blank ) ( cell f3 blank ) ( cell e5 blue ) ( cell h1 teal ) ( cell d4 blank ) ( cell f6 blank ) ( step 16 ) ( cell c7 blank ) ( control magenta ) ( cell g2 blank ) ( cell c1 blank ) ( cell a1 red ) ( cell e4 green ) ( cell g1 blank ) ( cell e3 blank ) ( cell d1 blank ) ( cell g4 blue ) ( cell g6 blank ) ( cell c5 blank ) ( cell e1 magenta ) ( cell d6 yellow ) ( cell i1 teal ) ( cell d2 magenta ) ( cell d5 green ) ( cell h2 teal ) ( cell g7 blank ) ( cell b1 red ) ( cell f1 blank ) ( cell e2 magenta ) )","( ( cell d3 yellow ) ( cell c4 blank ) ( cell b2 red ) ( cell f4 blank ) ( cell c3 yellow ) ( cell g3 blank ) ( cell f5 green ) ( step 17 ) ( cell c6 blank ) ( cell f2 blue ) ( cell c2 blank ) ( cell f3 blank ) ( cell e5 blue ) ( cell h1 teal ) ( cell d4 blank ) ( cell f6 blank ) ( cell c7 blank ) ( cell g2 blank ) ( cell c1 blank ) ( cell a1 red ) ( cell e4 green ) ( cell g1 blank ) ( cell e3 blank ) ( cell d1 blank ) ( cell g4 blue ) ( cell g6 blank ) ( cell c5 blank ) ( cell d6 yellow ) ( cell i1 teal ) ( cell g5 magenta ) ( cell d2 magenta ) ( cell d5 green ) ( control yellow ) ( cell h2 teal ) ( cell g7 blank ) ( cell b1 red ) ( cell e1 blank ) ( cell f1 blank ) ( cell e2 magenta ) )","( ( cell d3 yellow ) ( cell c4 blank ) ( control green ) ( cell b2 red ) ( cell f4 blank ) ( cell c3 yellow ) ( cell g3 blank ) ( cell f5 green ) ( cell d6 blank ) ( cell c6 blank ) ( cell f2 blue ) ( cell d4 yellow ) ( cell c2 blank ) ( cell f3 blank ) ( cell e5 blue ) ( cell h1 teal ) ( cell f6 blank ) ( cell c7 blank ) ( cell g2 blank ) ( cell c1 blank ) ( cell a1 red ) ( step 18 ) ( cell e4 green ) ( cell g1 blank ) ( cell e3 blank ) ( cell d1 blank ) ( cell g4 blue ) ( cell g6 blank ) ( cell c5 blank ) ( cell i1 teal ) ( cell g5 magenta ) ( cell d2 magenta ) ( cell d5 green ) ( cell h2 teal ) ( cell g7 blank ) ( cell b1 red ) ( cell e1 blank ) ( cell f1 blank ) ( cell e2 magenta ) )","( ( cell d3 yellow ) ( cell c4 blank ) ( cell e4 blank ) ( cell b2 red ) ( cell f4 blank ) ( cell c3 yellow ) ( cell g3 blank ) ( cell f5 green ) ( cell c2 green ) ( cell d6 blank ) ( cell c6 blank ) ( cell f2 blue ) ( cell d4 yellow ) ( cell f3 blank ) ( cell e5 blue ) ( cell h1 teal ) ( cell f6 blank ) ( cell c7 blank ) ( cell g2 blank ) ( cell c1 blank ) ( cell a1 red ) ( cell g1 blank ) ( cell e3 blank ) ( cell d1 blank ) ( cell g4 blue ) ( cell g6 blank ) ( cell c5 blank ) ( cell i1 teal ) ( cell g5 magenta ) ( cell d2 magenta ) ( cell d5 green ) ( step 19 ) ( cell h2 teal ) ( cell g7 blank ) ( cell b1 red ) ( cell e1 blank ) ( cell f1 blank ) ( control blue ) ( cell e2 magenta ) )","( ( cell d3 yellow ) ( cell c4 blank ) ( cell e4 blank ) ( cell b2 red ) ( cell f4 blank ) ( cell c3 yellow ) ( cell g3 blank ) ( cell f5 green ) ( cell c2 green ) ( cell c6 blank ) ( cell f2 blue ) ( cell d4 yellow ) ( cell d6 blue ) ( cell f3 blank ) ( cell h1 teal ) ( cell f6 blank ) ( cell c7 blank ) ( step 20 ) ( control magenta ) ( cell g2 blank ) ( cell c1 blank ) ( cell a1 red ) ( cell g1 blank ) ( cell e3 blank ) ( cell d1 blank ) ( cell g4 blue ) ( cell g6 blank ) ( cell c5 blank ) ( cell i1 teal ) ( cell g5 magenta ) ( cell d2 magenta ) ( cell d5 green ) ( cell h2 teal ) ( cell g7 blank ) ( cell b1 red ) ( cell e5 blank ) ( cell e1 blank ) ( cell f1 blank ) ( cell e2 magenta ) )","( ( cell d3 yellow ) ( cell c4 blank ) ( cell e4 blank ) ( cell b2 red ) ( cell f4 blank ) ( cell c3 yellow ) ( cell g3 blank ) ( cell f5 green ) ( cell c2 green ) ( cell c6 blank ) ( cell f2 blue ) ( cell d4 yellow ) ( cell g5 blank ) ( cell d6 blue ) ( cell f3 blank ) ( cell h1 teal ) ( cell f6 blank ) ( cell c7 blank ) ( cell g2 blank ) ( cell c1 blank ) ( cell a1 red ) ( cell g1 blank ) ( cell e3 blank ) ( cell d1 blank ) ( cell g6 magenta ) ( cell g4 blue ) ( cell c5 blank ) ( cell i1 teal ) ( cell d2 magenta ) ( cell d5 green ) ( control yellow ) ( cell h2 teal ) ( cell g7 blank ) ( cell b1 red ) ( cell e5 blank ) ( cell e1 blank ) ( step 21 ) ( cell f1 blank ) ( cell e2 magenta ) )","( ( cell d3 yellow ) ( cell c4 blank ) ( control green ) ( cell e4 blank ) ( cell c3 blank ) ( cell b2 red ) ( cell f4 blank ) ( cell g3 blank ) ( cell f5 green ) ( cell c2 green ) ( cell c6 blank ) ( cell f2 blue ) ( cell d4 yellow ) ( cell g5 blank ) ( cell d6 blue ) ( cell f3 blank ) ( cell h1 teal ) ( cell f6 blank ) ( cell c7 blank ) ( cell g2 blank ) ( cell c1 blank ) ( cell a1 red ) ( cell g1 blank ) ( cell e3 blank ) ( cell d1 blank ) ( cell g6 magenta ) ( cell g4 blue ) ( cell c5 blank ) ( cell i1 teal ) ( cell d2 magenta ) ( cell d5 green ) ( cell h2 teal ) ( cell g7 blank ) ( cell b1 red ) ( cell e5 blank ) ( step 22 ) ( cell e1 yellow ) ( cell f1 blank ) ( cell e2 magenta ) )","( ( cell d3 yellow ) ( cell c4 blank ) ( cell e4 blank ) ( cell c3 blank ) ( cell b2 red ) ( cell f4 blank ) ( cell g3 blank ) ( cell f5 green ) ( cell c6 blank ) ( cell f2 blue ) ( cell d4 yellow ) ( cell c2 blank ) ( cell g5 blank ) ( cell d6 blue ) ( cell f3 blank ) ( cell h1 teal ) ( cell f6 blank ) ( cell c7 blank ) ( cell g2 blank ) ( cell a1 red ) ( cell g1 blank ) ( cell e3 blank ) ( cell d1 blank ) ( cell g6 magenta ) ( cell g4 blue ) ( cell c5 blank ) ( cell c1 green ) ( cell i1 teal ) ( cell d2 magenta ) ( cell d5 green ) ( step 23 ) ( cell h2 teal ) ( cell g7 blank ) ( cell b1 red ) ( cell e5 blank ) ( cell e1 yellow ) ( cell f1 blank ) ( control blue ) ( cell e2 magenta ) )","( ( cell d3 yellow ) ( cell c4 blank ) ( cell e4 blank ) ( cell c3 blank ) ( cell b2 red ) ( cell g4 blank ) ( cell f4 blank ) ( cell g3 blank ) ( step 24 ) ( cell f5 green ) ( cell c6 blank ) ( cell f2 blue ) ( cell d4 yellow ) ( cell c2 blank ) ( cell d6 blue ) ( cell f3 blank ) ( cell h1 teal ) ( cell f6 blank ) ( cell c7 blank ) ( control magenta ) ( cell g5 blue ) ( cell g2 blank ) ( cell a1 red ) ( cell g1 blank ) ( cell e3 blank ) ( cell d1 blank ) ( cell g6 magenta ) ( cell c5 blank ) ( cell c1 green ) ( cell i1 teal ) ( cell d2 magenta ) ( cell d5 green ) ( cell h2 teal ) ( cell g7 blank ) ( cell b1 red ) ( cell e5 blank ) ( cell e1 yellow ) ( cell f1 blank ) ( cell e2 magenta ) )","( ( cell d3 yellow ) ( cell c4 blank ) ( cell e4 blank ) ( cell c3 blank ) ( cell b2 red ) ( cell g4 blank ) ( cell f4 blank ) ( cell g3 blank ) ( cell f5 green ) ( cell c6 blank ) ( cell f2 blue ) ( cell d4 yellow ) ( cell c2 blank ) ( cell d6 blue ) ( cell f3 blank ) ( cell h1 teal ) ( cell f6 blank ) ( cell c7 blank ) ( cell g5 blue ) ( cell g2 blank ) ( cell a1 red ) ( cell g1 blank ) ( cell e3 blank ) ( cell d1 blank ) ( cell g6 blank ) ( cell c5 blank ) ( cell c1 green ) ( cell i1 teal ) ( cell d2 magenta ) ( cell d5 green ) ( control yellow ) ( cell h2 teal ) ( cell b1 red ) ( cell e5 blank ) ( cell e1 yellow ) ( cell f1 blank ) ( step 25 ) ( cell e2 magenta ) ( cell g7 magenta ) )","( ( step 26 ) ( cell d3 yellow ) ( cell c4 blank ) ( control green ) ( cell e4 blank ) ( cell c3 blank ) ( cell b2 red ) ( cell g4 blank ) ( cell f4 blank ) ( cell g3 blank ) ( cell f5 green ) ( cell c6 blank ) ( cell f2 blue ) ( cell d4 yellow ) ( cell c2 blank ) ( cell d6 blue ) ( cell f3 blank ) ( cell h1 teal ) ( cell f6 blank ) ( cell c7 blank ) ( cell f1 yellow ) ( cell g5 blue ) ( cell g2 blank ) ( cell a1 red ) ( cell g1 blank ) ( cell e3 blank ) ( cell d1 blank ) ( cell g6 blank ) ( cell c5 blank ) ( cell c1 green ) ( cell i1 teal ) ( cell d2 magenta ) ( cell d5 green ) ( cell h2 teal ) ( cell b1 red ) ( cell e5 blank ) ( cell e1 blank ) ( cell e2 magenta ) ( cell g7 magenta ) )","( ( cell d3 yellow ) ( cell c4 blank ) ( cell f5 blank ) ( cell c3 blank ) ( cell b2 red ) ( cell g4 blank ) ( cell f4 blank ) ( cell g3 blank ) ( cell c6 blank ) ( cell f2 blue ) ( cell d4 yellow ) ( cell c2 blank ) ( cell d6 blue ) ( cell f3 blank ) ( cell h1 teal ) ( cell f6 blank ) ( cell c7 blank ) ( cell f1 yellow ) ( cell g5 blue ) ( cell g2 blank ) ( cell a1 red ) ( cell e4 green ) ( cell g1 blank ) ( cell e3 blank ) ( cell d1 blank ) ( cell g6 blank ) ( cell c5 blank ) ( cell c1 green ) ( cell i1 teal ) ( cell d2 magenta ) ( cell d5 green ) ( step 27 ) ( cell h2 teal ) ( cell b1 red ) ( cell e5 blank ) ( cell e1 blank ) ( control blue ) ( cell e2 magenta ) ( cell g7 magenta ) )","( ( cell d3 yellow ) ( cell c4 blank ) ( cell c3 blank ) ( cell b2 red ) ( cell g4 blank ) ( cell f4 blank ) ( cell g3 blank ) ( step 28 ) ( cell c6 blank ) ( cell f2 blue ) ( cell d4 yellow ) ( cell c2 blank ) ( cell g5 blank ) ( cell d6 blue ) ( cell f3 blank ) ( cell h1 teal ) ( cell f5 blue ) ( cell f6 blank ) ( cell c7 blank ) ( cell f1 yellow ) ( control magenta ) ( cell g2 blank ) ( cell a1 red ) ( cell e4 green ) ( cell g1 blank ) ( cell e3 blank ) ( cell d1 blank ) ( cell g6 blank ) ( cell c5 blank ) ( cell c1 green ) ( cell i1 teal ) ( cell d2 magenta ) ( cell d5 green ) ( cell h2 teal ) ( cell b1 red ) ( cell e5 blank ) ( cell e1 blank ) ( cell e2 magenta ) ( cell g7 magenta ) )","( ( step 29 ) ( cell f3 magenta ) ( cell d3 yellow ) ( cell c4 blank ) ( cell c3 blank ) ( cell b2 red ) ( cell g4 blank ) ( cell f4 blank ) ( cell g3 blank ) ( cell c6 blank ) ( cell f2 blue ) ( cell d4 yellow ) ( cell c2 blank ) ( cell g5 blank ) ( cell d6 blue ) ( cell h1 teal ) ( cell f5 blue ) ( cell f6 blank ) ( cell c7 blank ) ( cell f1 yellow ) ( cell d2 blank ) ( cell g2 blank ) ( cell a1 red ) ( cell e4 green ) ( cell g1 blank ) ( cell e3 blank ) ( cell d1 blank ) ( cell g6 blank ) ( cell c5 blank ) ( cell c1 green ) ( cell i1 teal ) ( cell d5 green ) ( control yellow ) ( cell h2 teal ) ( cell b1 red ) ( cell e5 blank ) ( cell e1 blank ) ( cell e2 magenta ) ( cell g7 magenta ) )","( ( cell f3 magenta ) ( cell d3 yellow ) ( cell c4 blank ) ( control green ) ( cell c3 blank ) ( cell e3 yellow ) ( cell b2 red ) ( cell g4 blank ) ( cell f4 blank ) ( cell g3 blank ) ( cell c6 blank ) ( cell f2 blue ) ( cell c2 blank ) ( cell g5 blank ) ( cell d6 blue ) ( cell h1 teal ) ( cell d4 blank ) ( cell f5 blue ) ( cell f6 blank ) ( step 30 ) ( cell c7 blank ) ( cell f1 yellow ) ( cell d2 blank ) ( cell g2 blank ) ( cell a1 red ) ( cell e4 green ) ( cell g1 blank ) ( cell d1 blank ) ( cell g6 blank ) ( cell c5 blank ) ( cell c1 green ) ( cell i1 teal ) ( cell d5 green ) ( cell h2 teal ) ( cell b1 red ) ( cell e5 blank ) ( cell e1 blank ) ( cell e2 magenta ) ( cell g7 magenta ) )","( ( cell f3 magenta ) ( cell d3 yellow ) ( cell c4 blank ) ( cell e4 blank ) ( cell c3 blank ) ( cell e3 yellow ) ( cell b2 red ) ( cell g4 blank ) ( cell f4 blank ) ( cell g3 blank ) ( cell c6 blank ) ( cell f2 blue ) ( cell c2 blank ) ( cell g5 blank ) ( cell d6 blue ) ( cell h1 teal ) ( cell f5 blue ) ( cell f6 blank ) ( cell c7 blank ) ( cell f1 yellow ) ( cell d2 blank ) ( cell d4 green ) ( cell g2 blank ) ( cell a1 red ) ( step 31 ) ( cell g1 blank ) ( cell d1 blank ) ( cell g6 blank ) ( cell c5 blank ) ( cell c1 green ) ( cell i1 teal ) ( cell d5 green ) ( cell h2 teal ) ( cell b1 red ) ( cell e5 blank ) ( cell e1 blank ) ( control blue ) ( cell e2 magenta ) ( cell g7 magenta ) )","( ( cell f3 magenta ) ( cell d3 yellow ) ( cell c4 blank ) ( cell f5 blank ) ( cell e4 blank ) ( cell c3 blank ) ( cell e3 yellow ) ( cell b2 red ) ( cell g4 blank ) ( cell f4 blank ) ( cell g3 blank ) ( cell c6 blank ) ( cell f2 blue ) ( cell c2 blank ) ( cell g5 blank ) ( cell d6 blue ) ( cell e5 blue ) ( cell h1 teal ) ( cell f6 blank ) ( cell c7 blank ) ( cell f1 yellow ) ( cell d2 blank ) ( control magenta ) ( cell d4 green ) ( cell g2 blank ) ( cell a1 red ) ( cell g1 blank ) ( cell d1 blank ) ( cell g6 blank ) ( cell c5 blank ) ( cell c1 green ) ( cell i1 teal ) ( cell d5 green ) ( step 32 ) ( cell h2 teal ) ( cell b1 red ) ( cell e1 blank ) ( cell e2 magenta ) ( cell g7 magenta ) )","( ( cell f3 magenta ) ( cell d3 yellow ) ( cell c4 blank ) ( cell f5 blank ) ( step 33 ) ( cell c3 blank ) ( cell e3 yellow ) ( cell b2 red ) ( cell g4 blank ) ( cell f4 blank ) ( cell g3 blank ) ( cell c6 blank ) ( cell f2 blue ) ( cell c2 blank ) ( cell g5 blank ) ( cell d6 blue ) ( cell e2 blank ) ( cell e5 blue ) ( cell h1 teal ) ( cell e4 magenta ) ( cell f6 blank ) ( cell c7 blank ) ( cell f1 yellow ) ( cell d2 blank ) ( cell d4 green ) ( cell g2 blank ) ( cell a1 red ) ( cell g1 blank ) ( cell d1 blank ) ( cell g6 blank ) ( cell c5 blank ) ( cell c1 green ) ( cell i1 teal ) ( cell d5 green ) ( control yellow ) ( cell h2 teal ) ( cell b1 red ) ( cell e1 blank ) ( cell g7 magenta ) )","( ( cell f3 magenta ) ( cell d3 yellow ) ( cell c4 blank ) ( cell f5 blank ) ( control green ) ( cell c3 blank ) ( cell b2 red ) ( cell g4 blank ) ( cell f4 blank ) ( cell g3 yellow ) ( cell c6 blank ) ( cell f2 blue ) ( cell c2 blank ) ( cell g5 blank ) ( cell d6 blue ) ( cell e2 blank ) ( step 34 ) ( cell e5 blue ) ( cell h1 teal ) ( cell e4 magenta ) ( cell f6 blank ) ( cell c7 blank ) ( cell f1 yellow ) ( cell d2 blank ) ( cell d4 green ) ( cell g2 blank ) ( cell a1 red ) ( cell g1 blank ) ( cell e3 blank ) ( cell d1 blank ) ( cell g6 blank ) ( cell c5 blank ) ( cell c1 green ) ( cell i1 teal ) ( cell d5 green ) ( cell h2 teal ) ( cell b1 red ) ( cell e1 blank ) ( cell g7 magenta ) )","( ( cell d2 green ) ( cell f3 magenta ) ( cell d3 yellow ) ( cell c4 blank ) ( cell f5 blank ) ( cell c3 blank ) ( cell b2 red ) ( cell g4 blank ) ( cell f4 blank ) ( cell g3 yellow ) ( cell c6 blank ) ( cell f2 blue ) ( cell c2 blank ) ( cell g5 blank ) ( cell d6 blue ) ( cell e2 blank ) ( cell e5 blue ) ( cell h1 teal ) ( cell d4 blank ) ( cell e4 magenta ) ( cell f6 blank ) ( cell c7 blank ) ( cell f1 yellow ) ( step 35 ) ( cell g2 blank ) ( cell a1 red ) ( cell g1 blank ) ( cell e3 blank ) ( cell d1 blank ) ( cell g6 blank ) ( cell c5 blank ) ( cell c1 green ) ( cell i1 teal ) ( cell d5 green ) ( cell h2 teal ) ( cell b1 red ) ( cell e1 blank ) ( control blue ) ( cell g7 magenta ) )","( ( cell d2 green ) ( cell f3 magenta ) ( cell d3 yellow ) ( cell c4 blank ) ( cell f5 blank ) ( cell c3 blank ) ( cell b2 red ) ( cell g4 blank ) ( cell f4 blank ) ( cell g3 yellow ) ( cell c7 blue ) ( cell c6 blank ) ( cell f2 blue ) ( cell c2 blank ) ( cell g5 blank ) ( cell d6 blue ) ( cell e2 blank ) ( step 36 ) ( cell h1 teal ) ( cell d4 blank ) ( cell e4 magenta ) ( cell f6 blank ) ( cell f1 yellow ) ( control magenta ) ( cell g2 blank ) ( cell a1 red ) ( cell g1 blank ) ( cell e3 blank ) ( cell d1 blank ) ( cell g6 blank ) ( cell c5 blank ) ( cell c1 green ) ( cell i1 teal ) ( cell d5 green ) ( cell h2 teal ) ( cell b1 red ) ( cell e5 blank ) ( cell e1 blank ) ( cell g7 magenta ) )","( ( cell d2 green ) ( cell d3 yellow ) ( cell c4 blank ) ( cell f5 blank ) ( cell c3 blank ) ( cell b2 red ) ( cell g4 blank ) ( cell g3 yellow ) ( cell c7 blue ) ( cell c6 blank ) ( cell f2 blue ) ( cell c2 blank ) ( cell g5 blank ) ( cell d6 blue ) ( cell e2 blank ) ( cell f3 blank ) ( cell h1 teal ) ( cell d4 blank ) ( cell e4 magenta ) ( cell f6 blank ) ( cell f4 magenta ) ( cell f1 yellow ) ( cell g2 blank ) ( cell a1 red ) ( cell g1 blank ) ( cell e3 blank ) ( cell d1 blank ) ( cell g6 blank ) ( cell c5 blank ) ( cell c1 green ) ( cell i1 teal ) ( cell d5 green ) ( control yellow ) ( step 37 ) ( cell h2 teal ) ( cell b1 red ) ( cell e5 blank ) ( cell e1 blank ) ( cell g7 magenta ) )","( ( cell d2 green ) ( cell d3 yellow ) ( cell c4 blank ) ( cell f5 blank ) ( control green ) ( cell c3 blank ) ( cell b2 red ) ( cell g4 blank ) ( cell g3 yellow ) ( cell c7 blue ) ( cell c6 blank ) ( cell f2 blue ) ( cell c2 blank ) ( cell g5 blank ) ( cell d6 blue ) ( cell e2 blank ) ( cell f3 blank ) ( cell h1 teal ) ( cell g1 yellow ) ( cell d4 blank ) ( cell e4 magenta ) ( cell f6 blank ) ( cell f4 magenta ) ( cell g2 blank ) ( cell a1 red ) ( cell e3 blank ) ( cell d1 blank ) ( cell g6 blank ) ( cell c5 blank ) ( step 38 ) ( cell c1 green ) ( cell i1 teal ) ( cell d5 green ) ( cell h2 teal ) ( cell b1 red ) ( cell e5 blank ) ( cell e1 blank ) ( cell f1 blank ) ( cell g7 magenta ) )","( ( cell d1 green ) ( cell d3 yellow ) ( cell c4 blank ) ( cell f5 blank ) ( cell c3 blank ) ( cell b2 red ) ( cell g4 blank ) ( cell g3 yellow ) ( cell c7 blue ) ( cell c6 blank ) ( cell f2 blue ) ( cell c2 blank ) ( cell g5 blank ) ( cell d6 blue ) ( cell e2 blank ) ( cell f3 blank ) ( step 39 ) ( cell h1 teal ) ( cell g1 yellow ) ( cell d4 blank ) ( cell e4 magenta ) ( cell f6 blank ) ( cell f4 magenta ) ( cell d2 blank ) ( cell g2 blank ) ( cell a1 red ) ( cell e3 blank ) ( cell g6 blank ) ( cell c5 blank ) ( cell c1 green ) ( cell i1 teal ) ( cell d5 green ) ( cell h2 teal ) ( cell b1 red ) ( cell e5 blank ) ( cell e1 blank ) ( cell f1 blank ) ( control blue ) ( cell g7 magenta ) )","( ( cell d1 green ) ( cell d3 yellow ) ( cell c4 blank ) ( cell f5 blank ) ( cell c3 blank ) ( cell b2 red ) ( cell g4 blank ) ( cell g3 yellow ) ( cell c7 blue ) ( cell c6 blank ) ( cell f2 blue ) ( cell c2 blank ) ( cell g5 blank ) ( cell d6 blue ) ( cell e2 blank ) ( cell f3 blank ) ( cell h1 teal ) ( cell g1 yellow ) ( cell d4 blank ) ( cell e4 magenta ) ( cell f6 blank ) ( cell f4 magenta ) ( cell d2 blank ) ( control magenta ) ( cell g2 blank ) ( cell a1 red ) ( cell e3 blank ) ( cell g6 blank ) ( cell c5 blank ) ( cell c1 green ) ( cell i1 teal ) ( cell d5 green ) ( step 40 ) ( cell h2 teal ) ( cell b1 red ) ( cell e5 blank ) ( cell e1 blank ) ( cell f1 blank ) ( cell g7 magenta ) )","( ( cell d1 green ) ( cell d3 yellow ) ( cell c4 blank ) ( cell c3 blank ) ( cell b2 red ) ( cell g4 blank ) ( cell f4 blank ) ( cell g3 yellow ) ( cell c7 blue ) ( cell c6 blank ) ( cell f2 blue ) ( cell c2 blank ) ( cell g5 blank ) ( cell d6 blue ) ( cell e2 blank ) ( cell f3 blank ) ( cell h1 teal ) ( cell g1 yellow ) ( cell d4 blank ) ( cell e4 magenta ) ( cell f6 blank ) ( cell d2 blank ) ( cell g2 blank ) ( cell f5 magenta ) ( cell a1 red ) ( cell e3 blank ) ( cell g6 blank ) ( cell c5 blank ) ( cell c1 green ) ( cell i1 teal ) ( cell d5 green ) ( step 41 ) ( control yellow ) ( cell h2 teal ) ( cell b1 red ) ( cell e5 blank ) ( cell e1 blank ) ( cell f1 blank ) ( cell g7 magenta ) )","( ( cell d1 green ) ( cell c4 blank ) ( control green ) ( cell c3 blank ) ( cell b2 red ) ( cell g4 blank ) ( cell f4 blank ) ( cell g3 yellow ) ( cell c7 blue ) ( cell c6 blank ) ( cell f2 blue ) ( cell c2 blank ) ( cell g5 blank ) ( cell d6 blue ) ( cell f3 blank ) ( step 42 ) ( cell h1 teal ) ( cell g1 yellow ) ( cell d4 blank ) ( cell d3 blank ) ( cell e4 magenta ) ( cell f6 blank ) ( cell d2 blank ) ( cell g2 blank ) ( cell f5 magenta ) ( cell a1 red ) ( cell e3 blank ) ( cell g6 blank ) ( cell c5 blank ) ( cell c1 green ) ( cell i1 teal ) ( cell d5 green ) ( cell e2 yellow ) ( cell h2 teal ) ( cell b1 red ) ( cell e5 blank ) ( cell e1 blank ) ( cell f1 blank ) ( cell g7 magenta ) )","( ( cell d1 green ) ( cell c4 blank ) ( cell c3 blank ) ( cell b2 red ) ( cell g4 blank ) ( cell f4 blank ) ( cell g3 yellow ) ( cell c7 blue ) ( cell c6 blank ) ( cell f2 blue ) ( cell c2 blank ) ( cell g5 blank ) ( cell d5 blank ) ( cell d6 blue ) ( cell f3 blank ) ( cell h1 teal ) ( cell g1 yellow ) ( cell d3 blank ) ( cell e4 magenta ) ( cell f6 blank ) ( cell d2 blank ) ( cell d4 green ) ( cell g2 blank ) ( cell f5 magenta ) ( cell a1 red ) ( cell e3 blank ) ( cell g6 blank ) ( cell c5 blank ) ( cell c1 green ) ( cell i1 teal ) ( step 43 ) ( cell e2 yellow ) ( cell h2 teal ) ( cell b1 red ) ( cell e5 blank ) ( cell e1 blank ) ( cell f1 blank ) ( control blue ) ( cell g7 magenta ) )","( ( cell d1 green ) ( cell c4 blank ) ( cell c3 blank ) ( cell b2 red ) ( cell g4 blank ) ( cell f4 blank ) ( step 44 ) ( cell g3 yellow ) ( cell c7 blue ) ( cell d5 blue ) ( cell c6 blank ) ( cell c2 blank ) ( cell g5 blank ) ( cell d6 blue ) ( cell f3 blank ) ( cell h1 teal ) ( cell g1 yellow ) ( cell d3 blank ) ( cell e4 magenta ) ( cell f6 blank ) ( cell d2 blank ) ( control magenta ) ( cell d4 green ) ( cell g2 blank ) ( cell f5 magenta ) ( cell a1 red ) ( cell e3 blank ) ( cell g6 blank ) ( cell c5 blank ) ( cell c1 green ) ( cell i1 teal ) ( cell e2 yellow ) ( cell f2 blank ) ( cell h2 teal ) ( cell b1 red ) ( cell e5 blank ) ( cell e1 blank ) ( cell f1 blank ) ( cell g7 magenta ) )","( ( cell d1 green ) ( cell c4 blank ) ( step 45 ) ( cell f5 blank ) ( cell c3 blank ) ( cell b2 red ) ( cell g4 blank ) ( cell f4 blank ) ( cell g3 yellow ) ( cell c7 blue ) ( cell d5 blue ) ( cell c6 blank ) ( cell c2 blank ) ( cell g5 blank ) ( cell d6 blue ) ( cell f3 blank ) ( cell h1 teal ) ( cell g1 yellow ) ( cell d3 blank ) ( cell e4 magenta ) ( cell d2 blank ) ( cell d4 green ) ( cell g2 blank ) ( cell a1 red ) ( cell e3 blank ) ( cell g6 blank ) ( cell c5 blank ) ( cell c1 green ) ( cell i1 teal ) ( cell f6 magenta ) ( control yellow ) ( cell e2 yellow ) ( cell f2 blank ) ( cell h2 teal ) ( cell b1 red ) ( cell e5 blank ) ( cell e1 blank ) ( cell f1 blank ) ( cell g7 magenta ) )","( ( cell d1 green ) ( cell c4 blank ) ( cell f5 blank ) ( control green ) ( cell c3 blank ) ( cell b2 red ) ( cell g4 blank ) ( cell f4 blank ) ( cell g3 blank ) ( cell c7 blue ) ( cell d5 blue ) ( cell c6 blank ) ( cell c2 blank ) ( cell g5 blank ) ( cell d6 blue ) ( cell f3 blank ) ( cell h1 teal ) ( cell g1 yellow ) ( cell d3 blank ) ( cell e4 magenta ) ( cell d2 blank ) ( cell d4 green ) ( cell a1 red ) ( cell e3 blank ) ( cell g6 blank ) ( cell c5 blank ) ( cell c1 green ) ( cell i1 teal ) ( cell f6 magenta ) ( step 46 ) ( cell e2 yellow ) ( cell g2 yellow ) ( cell f2 blank ) ( cell h2 teal ) ( cell b1 red ) ( cell e5 blank ) ( cell e1 blank ) ( cell f1 blank ) ( cell g7 magenta ) )","( ( cell d1 green ) ( cell c4 blank ) ( cell f5 blank ) ( cell c3 blank ) ( cell b2 red ) ( cell g4 blank ) ( cell f4 blank ) ( cell g3 blank ) ( cell c7 blue ) ( cell d5 blue ) ( cell c6 blank ) ( cell c2 blank ) ( cell g5 blank ) ( cell d6 blue ) ( cell f3 blank ) ( cell h1 teal ) ( cell g1 yellow ) ( cell d4 blank ) ( cell e4 magenta ) ( cell d2 blank ) ( cell a1 red ) ( step 47 ) ( cell e3 blank ) ( cell g6 blank ) ( cell c5 blank ) ( cell c1 green ) ( cell i1 teal ) ( cell f6 magenta ) ( cell e2 yellow ) ( cell g2 yellow ) ( cell f2 blank ) ( cell h2 teal ) ( cell b1 red ) ( cell e5 blank ) ( cell e1 blank ) ( cell f1 blank ) ( cell d3 green ) ( control blue ) ( cell g7 magenta ) )","( ( cell d1 green ) ( cell c4 blank ) ( cell f5 blank ) ( cell c3 blank ) ( cell b2 red ) ( cell g4 blank ) ( cell f4 blank ) ( cell g3 blank ) ( cell c7 blue ) ( cell c2 blank ) ( cell g5 blank ) ( cell d5 blank ) ( cell d6 blue ) ( cell f3 blank ) ( cell h1 teal ) ( cell g1 yellow ) ( cell d4 blank ) ( cell e4 magenta ) ( cell d2 blank ) ( step 48 ) ( control magenta ) ( cell a1 red ) ( cell e3 blank ) ( cell g6 blank ) ( cell c5 blank ) ( cell c1 green ) ( cell c6 blue ) ( cell i1 teal ) ( cell f6 magenta ) ( cell e2 yellow ) ( cell g2 yellow ) ( cell f2 blank ) ( cell h2 teal ) ( cell b1 red ) ( cell e5 blank ) ( cell e1 blank ) ( cell f1 blank ) ( cell d3 green ) ( cell g7 magenta ) )"],"playClock":15,"gameName":"Chinese Checkers 4","moves":[["( move c7 c5 )","noop","noop","noop"],["noop","( move g7 e5 )","noop","noop"],["noop","noop","( move g1 g3 )","noop"],["noop","noop","noop","( move c1 e1 )"],["( move c6 c4 )","noop","noop","noop"],["noop","( move g6 f5 )","noop","noop"],["noop","noop","( move g2 g4 )","noop"],["noop","noop","noop","( move d1 d2 )"],["( move c5 c3 )","noop","noop","noop"],["noop","( move f6 d5 )","noop","noop"],["noop","noop","( move f1 f2 )","noop"],["noop","noop","noop","( move c2 e2 )"],["( move c4 d3 )","noop","noop","noop"],["noop","( move e5 e4 )","noop","noop"],["noop","noop","( move g3 e5 )","noop"],["noop","noop","noop","( move e1 g5 )"],["( move d6 d4 )","noop","noop","noop"],["noop","( move e4 c2 )","noop","noop"],["noop","noop","( move e5 d6 )","noop"],["noop","noop","noop","( move g5 g6 )"],["( move c3 e1 )","noop","noop","noop"],["noop","( move c2 c1 )","noop","noop"],["noop","noop","( move g4 g5 )","noop"],["noop","noop","noop","( move g6 g7 )"],["( move e1 f1 )","noop","noop","noop"],["noop","( move f5 e4 )","noop","noop"],["noop","noop","( move g5 f5 )","noop"],["noop","noop","noop","( move d2 f3 )"],["( move d4 e3 )","noop","noop","noop"],["noop","( move e4 d4 )","noop","noop"],["noop","noop","( move f5 e5 )","noop"],["noop","noop","noop","( move e2 e4 )"],["( move e3 g3 )","noop","noop","noop"],["noop","( move d4 d2 )","noop","noop"],["noop","noop","( move e5 c7 )","noop"],["noop","noop","noop","( move f3 f4 )"],["( move f1 g1 )","noop","noop","noop"],["noop","( move d2 d1 )","noop","noop"],["noop","noop","noop","noop"],["noop","noop","noop","( move f4 f5 )"],["( move d3 e2 )","noop","noop","noop"],["noop","( move d5 d4 )","noop","noop"],["noop","noop","( move f2 d5 )","noop"],["noop","noop","noop","( move f5 f6 )"],["( move g3 g2 )","noop","noop","noop"],["noop","( move d4 d3 )","noop","noop"],["noop","noop","( move d5 c6 )","noop"]],"startTime":1584540161645,"stateTimes":[1584540161743,1584540208011,1584540220666,1584540233267,1584540245886,1584540258489,1584540271078,1584540283682,1584540296272,1584540308823,1584540321439,1584540334031,1584540346596,1584540359181,1584540371771,1584540384342,1584540396919,1584540409490,1584540422046,1584540434618,1584540447193,1584540459766,1584540472330,1584540484882,1584540497440,1584540509984,1584540522552,1584540535102,1584540547660,1584540560209,1584540572773,1584540585335,1584540598137,1584540610691,1584540623258,1584540635827,1584540648399,1584540660961,1584540673534,1584540686080,1584540698637,1584540698843,1584540698891,1584540698933,1584540698958,1584540698980,1584540699029,1584540699058],"scrambled":false,"matchId":"optimaltraces.chinesecheckers4.1584540161470","errors":[["TO","TO","TO","TO"],["","","TO",""],["","","",""],["","","",""],["","","",""],["","","",""],["","","",""],["","","",""],["","","",""],["","","",""],["","","",""],["","","",""],["","","",""],["","","",""],["","","",""],["","","",""],["","","",""],["","","",""],["","","",""],["","","",""],["","","",""],["","","",""],["","","",""],["","","",""],["","","",""],["","","",""],["","","",""],["","","",""],["","","",""],["","","",""],["","","",""],["","","",""],["","","",""],["","","",""],["","","",""],["","","",""],["","","",""],["","","",""],["","","",""],["","","",""],["","","",""],["","","",""],["","","",""],["","","",""],["","","",""],["","","",""],["","","",""],["","","",""]],"isCompleted":true,"isAborted":false,"previewClock":-1}