{"goalHistory":[[0],[0],[0],[0],[0],[0],[0],[0],[0],[100]],"startClock":30,"gameMetaURL":"http://games.ggp.org/stanford/games/untwistycomplex/v0/","goalValues":[100],"legalMoves":[[["4","2","7","5","10","3","6","8","1","9"]],[["4","2","7","5","10","3","6","8","1","9"]],[["4","2","7","5","10","3","6","8","1","9"]],[["4","2","7","5","10","3","6","8","1","9"]],[["4","2","7","5","10","3","6","8","1","9"]],[["4","2","7","5","10","3","6","8","1","9"]],[["4","2","7","5","10","3","6","8","1","9"]],[["4","2","7","5","10","3","6","8","1","9"]],[["4","2","7","5","10","3","6","8","1","9"]],[["4","2","7","5","10","3","6","8","1","9"]]],"randomToken":"bHYxwoGeV9mNTWcjNGhXMSb5SOW7YoBl","roles":["robot"],"playerNamesFromHost":["Sancho"],"states":["( q1 ( step 1 ) )","( ( step 2 ) q2 q1 )","( q3 ( step 3 ) q1 )","( q4 ( step 4 ) q1 )","( q5 ( step 5 ) q1 )","( ( step 6 ) q6 q1 )","( ( step 7 ) q7 q1 )","( ( step 8 ) q8 q1 )","( ( step 9 ) q9 q1 )","( q2 ( step 10 ) q10 q1 )"],"playClock":15,"gameName":"Untwisty 10x10","moves":[["9"],["8"],["1"],["1"],["10"],["10"],["10"],["10"],["9"]],"startTime":1584332135108,"stateTimes":[1584332135173,1584332155767,1584332155782,1584332155810,1584332155824,1584332155842,1584332155854,1584332155862,1584332155870,1584332155885],"scrambled":false,"matchId":"optimaltraces.untwistycomplex.1584332134988","errors":[[""],[""],[""],[""],[""],[""],[""],[""],[""],[""]],"isCompleted":true,"isAborted":false,"previewClock":-1}