{"goalHistory":[[100,0],[100,0],[100,0],[100,0],[100,0],[100,0],[100,0],[100,0],[100,0],[100,0],[100,0],[100,0],[100,0],[100,0],[100,0],[100,0],[100,0],[100,0],[100,0],[100,0],[100,0],[100,0],[100,0],[100,0],[100,0],[100,0],[100,0],[100,0],[100,0],[100,0],[100,0],[100,0],[100,0],[100,0],[100,0],[100,0],[100,0],[100,0],[100,0],[100,0],[100,0],[100,0],[100,0],[100,0],[100,0],[100,0],[100,0],[100,0],[100,0],[100,0],[100,0],[100,0]],"startClock":30,"gameMetaURL":"http://127.0.0.1:9140/games/sheep_and_wolf/v0/","goalValues":[100,0],"legalMoves":[[["( move c4 c8 c3 c7 )","( move c4 c8 c5 c7 )"],["noop"]],[["( move c4 c8 c3 c7 )","( move c4 c8 c5 c7 )"],["noop"]],[["noop"],["( move c1 c1 c2 c2 )","( move c5 c1 c4 c2 )","( move c3 c1 c4 c2 )","( move c5 c1 c6 c2 )","( move c3 c1 c2 c2 )","( move c7 c1 c6 c2 )","( move c7 c1 c8 c2 )"]],[["( move c5 c7 c4 c8 )","( move c5 c7 c6 c6 )","( move c5 c7 c4 c6 )","( move c5 c7 c6 c8 )"],["noop"]],[["noop"],["( move c1 c1 c2 c2 )","( move c5 c1 c4 c2 )","( move c3 c1 c4 c2 )","( move c5 c1 c6 c2 )","( move c3 c1 c2 c2 )","( move c8 c2 c7 c3 )"]],[["( move c6 c6 c5 c5 )","( move c6 c6 c7 c5 )","( move c6 c6 c7 c7 )","( move c6 c6 c5 c7 )"],["noop"]],[["noop"],["( move c5 c1 c4 c2 )","( move c3 c1 c4 c2 )","( move c5 c1 c6 c2 )","( move c2 c2 c1 c3 )","( move c2 c2 c3 c3 )","( move c8 c2 c7 c3 )"]],[["( move c7 c7 c6 c6 )","( move c7 c7 c8 c6 )","( move c7 c7 c6 c8 )","( move c7 c7 c8 c8 )"],["noop"]],[["noop"],["( move c4 c2 c5 c3 )","( move c2 c2 c1 c3 )","( move c4 c2 c3 c3 )","( move c2 c2 c3 c3 )","( move c8 c2 c7 c3 )"]],[["( move c8 c8 c7 c7 )"],["noop"]],[["noop"],["( move c4 c2 c5 c3 )","( move c2 c2 c1 c3 )","( move c4 c2 c3 c3 )","( move c2 c2 c3 c3 )","( move c7 c3 c8 c4 )","( move c7 c3 c6 c4 )"]],[["( move c7 c7 c6 c6 )","( move c7 c7 c8 c6 )","( move c7 c7 c6 c8 )","( move c7 c7 c8 c8 )"],["noop"]],[["noop"],["( move c4 c2 c5 c3 )","( move c2 c2 c1 c3 )","( move c4 c2 c3 c3 )","( move c2 c2 c3 c3 )","( move c8 c4 c7 c5 )"]],[["( move c6 c8 c7 c7 )","( move c6 c8 c5 c7 )"],["noop"]],[["noop"],["( move c3 c1 c4 c2 )","( move c2 c2 c1 c3 )","( move c2 c2 c3 c3 )","( move c5 c3 c4 c4 )","( move c8 c4 c7 c5 )","( move c5 c3 c6 c4 )"]],[["( move c7 c7 c6 c6 )","( move c7 c7 c8 c6 )","( move c7 c7 c6 c8 )","( move c7 c7 c8 c8 )"],["noop"]],[["noop"],["( move c3 c1 c4 c2 )","( move c3 c1 c2 c2 )","( move c5 c3 c4 c4 )","( move c3 c3 c2 c4 )","( move c8 c4 c7 c5 )","( move c3 c3 c4 c4 )","( move c5 c3 c6 c4 )"]],[["( move c8 c6 c7 c7 )","( move c8 c6 c7 c5 )"],["noop"]],[["noop"],["( move c2 c2 c1 c3 )","( move c5 c3 c4 c4 )","( move c3 c3 c2 c4 )","( move c8 c4 c7 c5 )","( move c3 c3 c4 c4 )","( move c5 c3 c6 c4 )"]],[["( move c7 c7 c6 c6 )","( move c7 c7 c8 c6 )","( move c7 c7 c6 c8 )","( move c7 c7 c8 c8 )"],["noop"]],[["noop"],["( move c5 c3 c4 c4 )","( move c3 c3 c2 c4 )","( move c8 c4 c7 c5 )","( move c3 c3 c4 c4 )","( move c1 c3 c2 c4 )","( move c5 c3 c6 c4 )"]],[["( move c6 c8 c7 c7 )","( move c6 c8 c5 c7 )"],["noop"]],[["noop"],["( move c5 c3 c4 c4 )","( move c8 c4 c7 c5 )","( move c2 c4 c1 c5 )","( move c2 c4 c3 c5 )","( move c5 c3 c6 c4 )"]],[["( move c7 c7 c6 c6 )","( move c7 c7 c8 c6 )","( move c7 c7 c6 c8 )","( move c7 c7 c8 c8 )"],["noop"]],[["noop"],["( move c5 c3 c4 c4 )","( move c3 c5 c2 c6 )","( move c8 c4 c7 c5 )","( move c3 c5 c4 c6 )","( move c1 c3 c2 c4 )","( move c5 c3 c6 c4 )"]],[["( move c8 c8 c7 c7 )"],["noop"]],[["noop"],["( move c5 c3 c4 c4 )","( move c3 c5 c2 c6 )","( move c8 c4 c7 c5 )","( move c3 c5 c4 c6 )","( move c2 c4 c1 c5 )","( move c5 c3 c6 c4 )"]],[["( move c7 c7 c6 c6 )","( move c7 c7 c8 c6 )","( move c7 c7 c6 c8 )","( move c7 c7 c8 c8 )"],["noop"]],[["noop"],["( move c3 c5 c2 c6 )","( move c8 c4 c7 c5 )","( move c3 c5 c4 c6 )","( move c6 c4 c7 c5 )","( move c2 c4 c1 c5 )","( move c6 c4 c5 c5 )"]],[["( move c8 c6 c7 c7 )","( move c8 c6 c7 c5 )"],["noop"]],[["noop"],["( move c2 c6 c1 c7 )","( move c2 c6 c3 c7 )","( move c2 c4 c1 c5 )","( move c2 c4 c3 c5 )","( move c6 c4 c5 c5 )"]],[["( move c7 c5 c6 c6 )","( move c7 c5 c8 c6 )"],["noop"]],[["noop"],["( move c8 c4 c7 c5 )","( move c3 c7 c4 c8 )","( move c3 c7 c2 c8 )","( move c6 c4 c7 c5 )","( move c2 c4 c1 c5 )","( move c2 c4 c3 c5 )","( move c6 c4 c5 c5 )"]],[["( move c8 c6 c7 c7 )","( move c8 c6 c7 c5 )"],["noop"]],[["noop"],["( move c3 c5 c2 c6 )","( move c8 c4 c7 c5 )","( move c3 c7 c4 c8 )","( move c3 c5 c4 c6 )","( move c3 c7 c2 c8 )","( move c6 c4 c7 c5 )","( move c6 c4 c5 c5 )"]],[["( move c7 c7 c6 c6 )","( move c7 c7 c8 c6 )","( move c7 c7 c6 c8 )","( move c7 c7 c8 c8 )"],["noop"]],[["noop"],["( move c3 c5 c2 c6 )","( move c8 c4 c7 c5 )","( move c3 c5 c4 c6 )","( move c6 c4 c7 c5 )","( move c6 c4 c5 c5 )"]],[["( move c6 c8 c7 c7 )","( move c6 c8 c5 c7 )"],["noop"]],[["noop"],["( move c2 c6 c1 c7 )","( move c8 c4 c7 c5 )","( move c2 c6 c3 c7 )","( move c6 c4 c7 c5 )","( move c6 c4 c5 c5 )"]],[["( move c7 c7 c6 c6 )","( move c7 c7 c8 c6 )","( move c7 c7 c6 c8 )","( move c7 c7 c8 c8 )"],["noop"]],[["noop"],["( move c2 c6 c1 c7 )","( move c7 c5 c8 c6 )","( move c7 c5 c6 c6 )","( move c2 c6 c3 c7 )","( move c6 c4 c5 c5 )"]],[["( move c6 c8 c7 c7 )","( move c6 c8 c5 c7 )"],["noop"]],[["noop"],["( move c7 c5 c8 c6 )","( move c7 c5 c6 c6 )","( move c6 c4 c5 c5 )","( move c1 c7 c2 c8 )"]],[["( move c7 c7 c6 c6 )","( move c7 c7 c6 c8 )","( move c7 c7 c8 c8 )"],["noop"]],[["noop"],["( move c8 c6 c7 c7 )","( move c6 c4 c7 c5 )","( move c6 c4 c5 c5 )","( move c1 c7 c2 c8 )"]],[["( move c6 c8 c7 c7 )","( move c6 c8 c5 c7 )"],["noop"]],[["noop"],["( move c7 c5 c6 c6 )","( move c1 c7 c2 c8 )"]],[["( move c7 c7 c6 c8 )","( move c7 c7 c8 c8 )"],["noop"]],[["noop"],["( move c8 c6 c7 c7 )","( move c6 c6 c5 c7 )","( move c6 c6 c7 c7 )","( move c1 c7 c2 c8 )"]],[["( move c6 c8 c5 c7 )"],["noop"]],[["noop"],["( move c7 c7 c6 c8 )","( move c7 c7 c8 c8 )","( move c1 c7 c2 c8 )"]],[["( move c5 c7 c4 c6 )"],["noop"]],[["noop"],["( move c6 c6 c5 c7 )","( move c6 c6 c7 c7 )","( move c1 c7 c2 c8 )"]]],"randomToken":"FdgzR2H6ssrtue25y4LjMeoX3vjShWok","roles":["wolf","sheep"],"playerNamesFromHost":["RandomGamer","RandomGamer"],"states":["( ( cell c6 c7 b ) ( cell c1 c1 s ) ( cell c1 c4 b ) ( cell c4 c4 b ) ( cell c7 c2 b ) ( cell c5 c5 b ) ( cell c7 c8 b ) ( cell c5 c6 b ) ( cell c3 c6 b ) ( cell c4 c2 b ) ( cell c1 c3 b ) ( cell c3 c7 b ) ( cell c7 c3 b ) ( cell c5 c7 b ) ( cell c6 c5 b ) ( cell c4 c7 b ) ( cell c8 c1 b ) ( cell c8 c4 b ) ( cell c4 c3 b ) ( cell c2 c5 b ) ( cell c2 c3 b ) ( cell c6 c1 b ) ( cell c8 c3 b ) ( cell c3 c5 b ) ( cell c6 c2 b ) ( cell c2 c8 b ) ( cell c2 c2 b ) ( cell c4 c6 b ) ( cell c2 c6 b ) ( cell c8 c8 b ) ( cell c8 c5 b ) ( cell c7 c4 b ) ( cell c4 c5 b ) ( cell c1 c5 b ) ( cell c6 c3 b ) ( cell c5 c3 b ) ( cell c7 c1 s ) ( cell c4 c1 b ) ( cell c3 c8 b ) ( cell c3 c3 b ) ( cell c1 c8 b ) ( cell c7 c5 b ) ( control wolf ) ( cell c3 c2 b ) ( cell c2 c4 b ) ( cell c7 c7 b ) ( cell c6 c8 b ) ( cell c8 c6 b ) ( cell c5 c4 b ) ( cell c1 c6 b ) ( cell c1 c7 b ) ( cell c8 c7 b ) ( cell c5 c2 b ) ( cell c5 c8 b ) ( cell c2 c7 b ) ( cell c3 c1 s ) ( cell c5 c1 s ) ( cell c8 c2 b ) ( cell c2 c1 b ) ( cell c6 c4 b ) ( cell c7 c6 b ) ( cell c3 c4 b ) ( cell c4 c8 w ) ( cell c6 c6 b ) ( cell c1 c2 b ) )","( ( cell c6 c7 b ) ( cell c1 c1 s ) ( cell c1 c4 b ) ( cell c4 c4 b ) ( cell c5 c5 b ) ( cell c7 c2 b ) ( cell c7 c8 b ) ( cell c5 c6 b ) ( cell c3 c6 b ) ( cell c4 c2 b ) ( cell c1 c3 b ) ( cell c3 c7 b ) ( cell c7 c3 b ) ( cell c6 c5 b ) ( cell c4 c7 b ) ( cell c4 c8 b ) ( cell c8 c1 b ) ( cell c8 c4 b ) ( cell c4 c3 b ) ( cell c2 c5 b ) ( cell c2 c3 b ) ( cell c6 c1 b ) ( cell c8 c3 b ) ( cell c3 c5 b ) ( cell c2 c6 b ) ( cell c4 c6 b ) ( cell c6 c2 b ) ( cell c2 c8 b ) ( cell c2 c2 b ) ( cell c8 c8 b ) ( cell c7 c4 b ) ( cell c8 c5 b ) ( cell c4 c5 b ) ( cell c1 c5 b ) ( cell c6 c3 b ) ( cell c5 c3 b ) ( cell c7 c1 s ) ( cell c4 c1 b ) ( cell c3 c8 b ) ( cell c3 c3 b ) ( cell c1 c8 b ) ( cell c7 c5 b ) ( control sheep ) ( cell c3 c2 b ) ( cell c2 c4 b ) ( cell c7 c7 b ) ( cell c6 c8 b ) ( cell c1 c6 b ) ( cell c8 c6 b ) ( cell c5 c4 b ) ( cell c1 c7 b ) ( cell c8 c7 b ) ( cell c5 c2 b ) ( cell c5 c8 b ) ( cell c2 c7 b ) ( cell c3 c1 s ) ( cell c5 c1 s ) ( cell c8 c2 b ) ( cell c2 c1 b ) ( cell c6 c4 b ) ( cell c5 c7 w ) ( cell c7 c6 b ) ( cell c3 c4 b ) ( cell c6 c6 b ) ( cell c1 c2 b ) )","( ( cell c6 c7 b ) ( cell c1 c1 s ) ( cell c1 c4 b ) ( cell c4 c4 b ) ( cell c5 c5 b ) ( cell c7 c2 b ) ( cell c8 c2 s ) ( cell c7 c8 b ) ( cell c5 c6 b ) ( cell c3 c6 b ) ( cell c4 c2 b ) ( cell c1 c3 b ) ( cell c3 c7 b ) ( cell c7 c3 b ) ( cell c6 c5 b ) ( cell c4 c7 b ) ( cell c4 c8 b ) ( cell c8 c1 b ) ( cell c8 c4 b ) ( cell c4 c3 b ) ( cell c2 c5 b ) ( cell c2 c3 b ) ( cell c6 c1 b ) ( cell c8 c3 b ) ( cell c3 c5 b ) ( cell c7 c1 b ) ( cell c2 c6 b ) ( cell c4 c6 b ) ( cell c6 c2 b ) ( cell c2 c8 b ) ( cell c2 c2 b ) ( cell c8 c8 b ) ( cell c7 c4 b ) ( cell c8 c5 b ) ( cell c4 c5 b ) ( cell c1 c5 b ) ( cell c6 c3 b ) ( cell c5 c3 b ) ( cell c4 c1 b ) ( cell c3 c8 b ) ( cell c3 c3 b ) ( cell c1 c8 b ) ( cell c7 c5 b ) ( control wolf ) ( cell c3 c2 b ) ( cell c2 c4 b ) ( cell c7 c7 b ) ( cell c6 c8 b ) ( cell c1 c6 b ) ( cell c8 c6 b ) ( cell c5 c4 b ) ( cell c1 c7 b ) ( cell c8 c7 b ) ( cell c5 c2 b ) ( cell c5 c8 b ) ( cell c2 c7 b ) ( cell c3 c1 s ) ( cell c5 c1 s ) ( cell c2 c1 b ) ( cell c6 c4 b ) ( cell c5 c7 w ) ( cell c7 c6 b ) ( cell c3 c4 b ) ( cell c6 c6 b ) ( cell c1 c2 b ) )","( ( cell c6 c7 b ) ( cell c1 c1 s ) ( cell c1 c4 b ) ( cell c4 c4 b ) ( cell c5 c5 b ) ( cell c7 c2 b ) ( cell c8 c2 s ) ( cell c7 c8 b ) ( cell c5 c6 b ) ( cell c3 c6 b ) ( cell c4 c2 b ) ( cell c1 c3 b ) ( cell c3 c7 b ) ( cell c7 c3 b ) ( cell c5 c7 b ) ( cell c6 c5 b ) ( cell c4 c7 b ) ( cell c4 c8 b ) ( cell c8 c1 b ) ( cell c8 c4 b ) ( cell c4 c3 b ) ( cell c2 c5 b ) ( cell c2 c3 b ) ( cell c6 c1 b ) ( cell c8 c3 b ) ( cell c3 c5 b ) ( cell c7 c1 b ) ( cell c2 c6 b ) ( cell c4 c6 b ) ( cell c6 c2 b ) ( cell c2 c8 b ) ( cell c2 c2 b ) ( cell c8 c8 b ) ( cell c7 c4 b ) ( cell c8 c5 b ) ( cell c4 c5 b ) ( cell c1 c5 b ) ( cell c6 c3 b ) ( cell c6 c6 w ) ( cell c5 c3 b ) ( cell c4 c1 b ) ( cell c3 c8 b ) ( cell c3 c3 b ) ( cell c1 c8 b ) ( cell c7 c5 b ) ( control sheep ) ( cell c3 c2 b ) ( cell c2 c4 b ) ( cell c7 c7 b ) ( cell c6 c8 b ) ( cell c1 c6 b ) ( cell c8 c6 b ) ( cell c5 c4 b ) ( cell c1 c7 b ) ( cell c8 c7 b ) ( cell c5 c2 b ) ( cell c5 c8 b ) ( cell c2 c7 b ) ( cell c3 c1 s ) ( cell c5 c1 s ) ( cell c2 c1 b ) ( cell c6 c4 b ) ( cell c7 c6 b ) ( cell c3 c4 b ) ( cell c1 c2 b ) )","( ( cell c6 c7 b ) ( cell c1 c4 b ) ( cell c4 c4 b ) ( cell c5 c5 b ) ( cell c7 c2 b ) ( cell c8 c2 s ) ( cell c7 c8 b ) ( cell c5 c6 b ) ( cell c3 c6 b ) ( cell c4 c2 b ) ( cell c1 c3 b ) ( cell c3 c7 b ) ( cell c7 c3 b ) ( cell c5 c7 b ) ( cell c6 c5 b ) ( cell c4 c7 b ) ( cell c4 c8 b ) ( cell c8 c1 b ) ( cell c8 c4 b ) ( cell c4 c3 b ) ( cell c2 c5 b ) ( cell c2 c3 b ) ( cell c6 c1 b ) ( cell c1 c1 b ) ( cell c8 c3 b ) ( cell c3 c5 b ) ( cell c7 c1 b ) ( cell c2 c6 b ) ( cell c4 c6 b ) ( cell c6 c2 b ) ( cell c2 c8 b ) ( cell c8 c8 b ) ( cell c7 c4 b ) ( cell c8 c5 b ) ( cell c4 c5 b ) ( cell c1 c5 b ) ( cell c6 c3 b ) ( cell c6 c6 w ) ( cell c5 c3 b ) ( cell c4 c1 b ) ( cell c3 c8 b ) ( cell c2 c2 s ) ( cell c3 c3 b ) ( cell c1 c8 b ) ( cell c7 c5 b ) ( control wolf ) ( cell c3 c2 b ) ( cell c2 c4 b ) ( cell c7 c7 b ) ( cell c6 c8 b ) ( cell c1 c6 b ) ( cell c8 c6 b ) ( cell c5 c4 b ) ( cell c1 c7 b ) ( cell c8 c7 b ) ( cell c5 c2 b ) ( cell c5 c8 b ) ( cell c2 c7 b ) ( cell c3 c1 s ) ( cell c5 c1 s ) ( cell c2 c1 b ) ( cell c6 c4 b ) ( cell c7 c6 b ) ( cell c3 c4 b ) ( cell c1 c2 b ) )","( ( cell c6 c7 b ) ( cell c1 c4 b ) ( cell c4 c4 b ) ( cell c5 c5 b ) ( cell c7 c2 b ) ( cell c8 c2 s ) ( cell c7 c8 b ) ( cell c5 c6 b ) ( cell c3 c6 b ) ( cell c4 c2 b ) ( cell c1 c3 b ) ( cell c3 c7 b ) ( cell c7 c3 b ) ( cell c5 c7 b ) ( cell c6 c5 b ) ( cell c4 c7 b ) ( cell c4 c8 b ) ( cell c8 c1 b ) ( cell c8 c4 b ) ( cell c4 c3 b ) ( cell c2 c5 b ) ( cell c2 c3 b ) ( cell c7 c7 w ) ( cell c6 c1 b ) ( cell c1 c1 b ) ( cell c8 c3 b ) ( cell c3 c5 b ) ( cell c7 c1 b ) ( cell c2 c6 b ) ( cell c4 c6 b ) ( cell c6 c2 b ) ( cell c2 c8 b ) ( cell c8 c8 b ) ( cell c7 c4 b ) ( cell c8 c5 b ) ( cell c4 c5 b ) ( cell c1 c5 b ) ( cell c6 c3 b ) ( cell c5 c3 b ) ( cell c4 c1 b ) ( cell c3 c8 b ) ( cell c2 c2 s ) ( cell c3 c3 b ) ( cell c1 c8 b ) ( cell c7 c5 b ) ( control sheep ) ( cell c3 c2 b ) ( cell c2 c4 b ) ( cell c6 c8 b ) ( cell c1 c6 b ) ( cell c8 c6 b ) ( cell c5 c4 b ) ( cell c1 c7 b ) ( cell c8 c7 b ) ( cell c5 c2 b ) ( cell c5 c8 b ) ( cell c2 c7 b ) ( cell c3 c1 s ) ( cell c5 c1 s ) ( cell c2 c1 b ) ( cell c6 c4 b ) ( cell c7 c6 b ) ( cell c3 c4 b ) ( cell c6 c6 b ) ( cell c1 c2 b ) )","( ( cell c6 c7 b ) ( cell c1 c4 b ) ( cell c4 c4 b ) ( cell c5 c5 b ) ( cell c7 c2 b ) ( cell c8 c2 s ) ( cell c7 c8 b ) ( cell c5 c6 b ) ( cell c3 c6 b ) ( cell c1 c3 b ) ( cell c3 c7 b ) ( cell c7 c3 b ) ( cell c5 c7 b ) ( cell c6 c5 b ) ( cell c4 c7 b ) ( cell c4 c8 b ) ( cell c8 c1 b ) ( cell c8 c4 b ) ( cell c4 c3 b ) ( cell c2 c5 b ) ( cell c4 c2 s ) ( cell c2 c3 b ) ( cell c7 c7 w ) ( cell c6 c1 b ) ( cell c1 c1 b ) ( cell c8 c3 b ) ( cell c3 c5 b ) ( cell c7 c1 b ) ( cell c2 c6 b ) ( cell c4 c6 b ) ( cell c6 c2 b ) ( cell c2 c8 b ) ( cell c8 c8 b ) ( cell c7 c4 b ) ( cell c8 c5 b ) ( cell c4 c5 b ) ( cell c1 c5 b ) ( cell c6 c3 b ) ( cell c5 c3 b ) ( cell c4 c1 b ) ( cell c3 c8 b ) ( cell c2 c2 s ) ( cell c5 c1 b ) ( cell c3 c3 b ) ( cell c1 c8 b ) ( cell c7 c5 b ) ( control wolf ) ( cell c3 c2 b ) ( cell c2 c4 b ) ( cell c6 c8 b ) ( cell c1 c6 b ) ( cell c8 c6 b ) ( cell c5 c4 b ) ( cell c1 c7 b ) ( cell c8 c7 b ) ( cell c5 c2 b ) ( cell c5 c8 b ) ( cell c2 c7 b ) ( cell c3 c1 s ) ( cell c2 c1 b ) ( cell c6 c4 b ) ( cell c7 c6 b ) ( cell c3 c4 b ) ( cell c6 c6 b ) ( cell c1 c2 b ) )","( ( cell c6 c7 b ) ( cell c1 c4 b ) ( cell c4 c4 b ) ( cell c5 c5 b ) ( cell c7 c2 b ) ( cell c8 c2 s ) ( cell c7 c8 b ) ( cell c5 c6 b ) ( cell c3 c6 b ) ( cell c1 c3 b ) ( cell c3 c7 b ) ( cell c7 c3 b ) ( cell c5 c7 b ) ( cell c6 c5 b ) ( cell c4 c7 b ) ( cell c4 c8 b ) ( cell c8 c1 b ) ( cell c8 c4 b ) ( cell c4 c3 b ) ( cell c2 c5 b ) ( cell c4 c2 s ) ( cell c2 c3 b ) ( cell c6 c1 b ) ( cell c1 c1 b ) ( cell c8 c3 b ) ( cell c3 c5 b ) ( cell c7 c1 b ) ( cell c2 c6 b ) ( cell c4 c6 b ) ( cell c6 c2 b ) ( cell c2 c8 b ) ( cell c7 c4 b ) ( cell c8 c5 b ) ( cell c4 c5 b ) ( cell c1 c5 b ) ( cell c6 c3 b ) ( cell c5 c3 b ) ( cell c4 c1 b ) ( cell c3 c8 b ) ( cell c2 c2 s ) ( cell c5 c1 b ) ( cell c3 c3 b ) ( cell c1 c8 b ) ( cell c7 c5 b ) ( control sheep ) ( cell c3 c2 b ) ( cell c2 c4 b ) ( cell c7 c7 b ) ( cell c6 c8 b ) ( cell c1 c6 b ) ( cell c8 c6 b ) ( cell c5 c4 b ) ( cell c1 c7 b ) ( cell c8 c7 b ) ( cell c5 c2 b ) ( cell c8 c8 w ) ( cell c5 c8 b ) ( cell c2 c7 b ) ( cell c3 c1 s ) ( cell c2 c1 b ) ( cell c6 c4 b ) ( cell c7 c6 b ) ( cell c3 c4 b ) ( cell c6 c6 b ) ( cell c1 c2 b ) )","( ( cell c6 c7 b ) ( cell c1 c4 b ) ( cell c4 c4 b ) ( cell c5 c5 b ) ( cell c7 c2 b ) ( cell c7 c3 s ) ( cell c7 c8 b ) ( cell c5 c6 b ) ( cell c3 c6 b ) ( cell c1 c3 b ) ( cell c3 c7 b ) ( cell c5 c7 b ) ( cell c6 c5 b ) ( cell c4 c7 b ) ( cell c4 c8 b ) ( cell c8 c1 b ) ( cell c8 c4 b ) ( cell c4 c3 b ) ( cell c2 c5 b ) ( cell c4 c2 s ) ( cell c2 c3 b ) ( cell c6 c1 b ) ( cell c1 c1 b ) ( cell c8 c3 b ) ( cell c3 c5 b ) ( cell c7 c1 b ) ( cell c2 c6 b ) ( cell c4 c6 b ) ( cell c6 c2 b ) ( cell c2 c8 b ) ( cell c7 c4 b ) ( cell c8 c5 b ) ( cell c4 c5 b ) ( cell c1 c5 b ) ( cell c6 c3 b ) ( cell c5 c3 b ) ( cell c4 c1 b ) ( cell c3 c8 b ) ( cell c2 c2 s ) ( cell c5 c1 b ) ( cell c3 c3 b ) ( cell c1 c8 b ) ( cell c7 c5 b ) ( control wolf ) ( cell c3 c2 b ) ( cell c2 c4 b ) ( cell c7 c7 b ) ( cell c6 c8 b ) ( cell c1 c6 b ) ( cell c8 c6 b ) ( cell c5 c4 b ) ( cell c1 c7 b ) ( cell c8 c7 b ) ( cell c5 c2 b ) ( cell c8 c8 w ) ( cell c5 c8 b ) ( cell c2 c7 b ) ( cell c3 c1 s ) ( cell c8 c2 b ) ( cell c2 c1 b ) ( cell c6 c4 b ) ( cell c7 c6 b ) ( cell c3 c4 b ) ( cell c6 c6 b ) ( cell c1 c2 b ) )","( ( cell c6 c7 b ) ( cell c1 c4 b ) ( cell c4 c4 b ) ( cell c5 c5 b ) ( cell c7 c2 b ) ( cell c7 c3 s ) ( cell c7 c8 b ) ( cell c5 c6 b ) ( cell c3 c6 b ) ( cell c1 c3 b ) ( cell c3 c7 b ) ( cell c5 c7 b ) ( cell c6 c5 b ) ( cell c4 c7 b ) ( cell c4 c8 b ) ( cell c8 c1 b ) ( cell c8 c4 b ) ( cell c4 c3 b ) ( cell c2 c5 b ) ( cell c4 c2 s ) ( cell c2 c3 b ) ( cell c7 c7 w ) ( cell c6 c1 b ) ( cell c1 c1 b ) ( cell c8 c3 b ) ( cell c3 c5 b ) ( cell c7 c1 b ) ( cell c2 c6 b ) ( cell c4 c6 b ) ( cell c6 c2 b ) ( cell c2 c8 b ) ( cell c8 c8 b ) ( cell c7 c4 b ) ( cell c8 c5 b ) ( cell c4 c5 b ) ( cell c1 c5 b ) ( cell c6 c3 b ) ( cell c5 c3 b ) ( cell c4 c1 b ) ( cell c3 c8 b ) ( cell c2 c2 s ) ( cell c5 c1 b ) ( cell c3 c3 b ) ( cell c1 c8 b ) ( cell c7 c5 b ) ( control sheep ) ( cell c3 c2 b ) ( cell c2 c4 b ) ( cell c6 c8 b ) ( cell c1 c6 b ) ( cell c8 c6 b ) ( cell c5 c4 b ) ( cell c1 c7 b ) ( cell c8 c7 b ) ( cell c5 c2 b ) ( cell c5 c8 b ) ( cell c2 c7 b ) ( cell c3 c1 s ) ( cell c8 c2 b ) ( cell c2 c1 b ) ( cell c6 c4 b ) ( cell c7 c6 b ) ( cell c3 c4 b ) ( cell c6 c6 b ) ( cell c1 c2 b ) )","( ( cell c6 c7 b ) ( cell c1 c4 b ) ( cell c4 c4 b ) ( cell c5 c5 b ) ( cell c7 c2 b ) ( cell c7 c8 b ) ( cell c5 c6 b ) ( cell c3 c6 b ) ( cell c1 c3 b ) ( cell c3 c7 b ) ( cell c7 c3 b ) ( cell c5 c7 b ) ( cell c6 c5 b ) ( cell c4 c7 b ) ( cell c4 c8 b ) ( cell c8 c1 b ) ( cell c4 c3 b ) ( cell c2 c5 b ) ( cell c4 c2 s ) ( cell c2 c3 b ) ( cell c7 c7 w ) ( cell c6 c1 b ) ( cell c1 c1 b ) ( cell c8 c3 b ) ( cell c3 c5 b ) ( cell c7 c1 b ) ( cell c2 c6 b ) ( cell c4 c6 b ) ( cell c6 c2 b ) ( cell c2 c8 b ) ( cell c8 c8 b ) ( cell c7 c4 b ) ( cell c8 c5 b ) ( cell c4 c5 b ) ( cell c1 c5 b ) ( cell c6 c3 b ) ( cell c5 c3 b ) ( cell c4 c1 b ) ( cell c3 c8 b ) ( cell c2 c2 s ) ( cell c5 c1 b ) ( cell c3 c3 b ) ( cell c1 c8 b ) ( cell c7 c5 b ) ( control wolf ) ( cell c3 c2 b ) ( cell c2 c4 b ) ( cell c6 c8 b ) ( cell c1 c6 b ) ( cell c8 c6 b ) ( cell c5 c4 b ) ( cell c8 c4 s ) ( cell c1 c7 b ) ( cell c8 c7 b ) ( cell c5 c2 b ) ( cell c5 c8 b ) ( cell c2 c7 b ) ( cell c3 c1 s ) ( cell c8 c2 b ) ( cell c2 c1 b ) ( cell c6 c4 b ) ( cell c7 c6 b ) ( cell c3 c4 b ) ( cell c6 c6 b ) ( cell c1 c2 b ) )","( ( cell c6 c7 b ) ( cell c1 c4 b ) ( cell c4 c4 b ) ( cell c5 c5 b ) ( cell c7 c2 b ) ( cell c7 c8 b ) ( cell c5 c6 b ) ( cell c3 c6 b ) ( cell c1 c3 b ) ( cell c3 c7 b ) ( cell c7 c3 b ) ( cell c5 c7 b ) ( cell c6 c5 b ) ( cell c4 c7 b ) ( cell c4 c8 b ) ( cell c8 c1 b ) ( cell c4 c3 b ) ( cell c2 c5 b ) ( cell c4 c2 s ) ( cell c2 c3 b ) ( cell c6 c1 b ) ( cell c6 c8 w ) ( cell c1 c1 b ) ( cell c8 c3 b ) ( cell c3 c5 b ) ( cell c7 c1 b ) ( cell c2 c6 b ) ( cell c4 c6 b ) ( cell c6 c2 b ) ( cell c2 c8 b ) ( cell c8 c8 b ) ( cell c7 c4 b ) ( cell c8 c5 b ) ( cell c4 c5 b ) ( cell c1 c5 b ) ( cell c6 c3 b ) ( cell c5 c3 b ) ( cell c4 c1 b ) ( cell c3 c8 b ) ( cell c2 c2 s ) ( cell c5 c1 b ) ( cell c3 c3 b ) ( cell c1 c8 b ) ( cell c7 c5 b ) ( control sheep ) ( cell c3 c2 b ) ( cell c2 c4 b ) ( cell c7 c7 b ) ( cell c1 c6 b ) ( cell c8 c6 b ) ( cell c5 c4 b ) ( cell c8 c4 s ) ( cell c1 c7 b ) ( cell c8 c7 b ) ( cell c5 c2 b ) ( cell c5 c8 b ) ( cell c2 c7 b ) ( cell c3 c1 s ) ( cell c8 c2 b ) ( cell c2 c1 b ) ( cell c6 c4 b ) ( cell c7 c6 b ) ( cell c3 c4 b ) ( cell c6 c6 b ) ( cell c1 c2 b ) )","( ( cell c6 c7 b ) ( cell c1 c4 b ) ( cell c4 c4 b ) ( cell c5 c5 b ) ( cell c7 c2 b ) ( cell c7 c8 b ) ( cell c5 c3 s ) ( cell c5 c6 b ) ( cell c3 c6 b ) ( cell c4 c2 b ) ( cell c1 c3 b ) ( cell c3 c7 b ) ( cell c7 c3 b ) ( cell c5 c7 b ) ( cell c6 c5 b ) ( cell c4 c7 b ) ( cell c4 c8 b ) ( cell c8 c1 b ) ( cell c4 c3 b ) ( cell c2 c5 b ) ( cell c2 c3 b ) ( cell c6 c1 b ) ( cell c6 c8 w ) ( cell c1 c1 b ) ( cell c8 c3 b ) ( cell c3 c5 b ) ( cell c7 c1 b ) ( cell c2 c6 b ) ( cell c4 c6 b ) ( cell c6 c2 b ) ( cell c2 c8 b ) ( cell c8 c8 b ) ( cell c7 c4 b ) ( cell c8 c5 b ) ( cell c4 c5 b ) ( cell c1 c5 b ) ( cell c6 c3 b ) ( cell c4 c1 b ) ( cell c3 c8 b ) ( cell c2 c2 s ) ( cell c5 c1 b ) ( cell c3 c3 b ) ( cell c1 c8 b ) ( cell c7 c5 b ) ( control wolf ) ( cell c3 c2 b ) ( cell c2 c4 b ) ( cell c7 c7 b ) ( cell c1 c6 b ) ( cell c8 c6 b ) ( cell c5 c4 b ) ( cell c8 c4 s ) ( cell c1 c7 b ) ( cell c8 c7 b ) ( cell c5 c2 b ) ( cell c5 c8 b ) ( cell c2 c7 b ) ( cell c3 c1 s ) ( cell c8 c2 b ) ( cell c2 c1 b ) ( cell c6 c4 b ) ( cell c7 c6 b ) ( cell c3 c4 b ) ( cell c6 c6 b ) ( cell c1 c2 b ) )","( ( cell c6 c7 b ) ( cell c1 c4 b ) ( cell c4 c4 b ) ( cell c5 c5 b ) ( cell c7 c2 b ) ( cell c7 c8 b ) ( cell c5 c3 s ) ( cell c5 c6 b ) ( cell c3 c6 b ) ( cell c4 c2 b ) ( cell c1 c3 b ) ( cell c3 c7 b ) ( cell c7 c3 b ) ( cell c5 c7 b ) ( cell c6 c5 b ) ( cell c4 c7 b ) ( cell c4 c8 b ) ( cell c8 c1 b ) ( cell c4 c3 b ) ( cell c2 c5 b ) ( cell c2 c3 b ) ( cell c7 c7 w ) ( cell c6 c1 b ) ( cell c1 c1 b ) ( cell c8 c3 b ) ( cell c3 c5 b ) ( cell c7 c1 b ) ( cell c2 c6 b ) ( cell c4 c6 b ) ( cell c6 c2 b ) ( cell c2 c8 b ) ( cell c8 c8 b ) ( cell c7 c4 b ) ( cell c8 c5 b ) ( cell c4 c5 b ) ( cell c1 c5 b ) ( cell c6 c3 b ) ( cell c4 c1 b ) ( cell c3 c8 b ) ( cell c2 c2 s ) ( cell c5 c1 b ) ( cell c3 c3 b ) ( cell c1 c8 b ) ( cell c7 c5 b ) ( control sheep ) ( cell c3 c2 b ) ( cell c2 c4 b ) ( cell c6 c8 b ) ( cell c1 c6 b ) ( cell c8 c6 b ) ( cell c5 c4 b ) ( cell c8 c4 s ) ( cell c1 c7 b ) ( cell c8 c7 b ) ( cell c5 c2 b ) ( cell c5 c8 b ) ( cell c2 c7 b ) ( cell c3 c1 s ) ( cell c8 c2 b ) ( cell c2 c1 b ) ( cell c6 c4 b ) ( cell c7 c6 b ) ( cell c3 c4 b ) ( cell c6 c6 b ) ( cell c1 c2 b ) )","( ( cell c6 c7 b ) ( cell c1 c4 b ) ( cell c4 c4 b ) ( cell c5 c5 b ) ( cell c7 c2 b ) ( cell c7 c8 b ) ( cell c5 c3 s ) ( cell c5 c6 b ) ( cell c3 c3 s ) ( cell c3 c6 b ) ( cell c4 c2 b ) ( cell c1 c3 b ) ( cell c3 c7 b ) ( cell c7 c3 b ) ( cell c5 c7 b ) ( cell c6 c5 b ) ( cell c4 c7 b ) ( cell c4 c8 b ) ( cell c8 c1 b ) ( cell c4 c3 b ) ( cell c2 c5 b ) ( cell c2 c3 b ) ( cell c7 c7 w ) ( cell c6 c1 b ) ( cell c1 c1 b ) ( cell c8 c3 b ) ( cell c3 c5 b ) ( cell c7 c1 b ) ( cell c2 c6 b ) ( cell c4 c6 b ) ( cell c6 c2 b ) ( cell c2 c8 b ) ( cell c2 c2 b ) ( cell c8 c8 b ) ( cell c7 c4 b ) ( cell c8 c5 b ) ( cell c4 c5 b ) ( cell c1 c5 b ) ( cell c6 c3 b ) ( cell c4 c1 b ) ( cell c3 c8 b ) ( cell c5 c1 b ) ( cell c1 c8 b ) ( cell c7 c5 b ) ( control wolf ) ( cell c3 c2 b ) ( cell c2 c4 b ) ( cell c6 c8 b ) ( cell c1 c6 b ) ( cell c8 c6 b ) ( cell c5 c4 b ) ( cell c8 c4 s ) ( cell c1 c7 b ) ( cell c8 c7 b ) ( cell c5 c2 b ) ( cell c5 c8 b ) ( cell c2 c7 b ) ( cell c3 c1 s ) ( cell c8 c2 b ) ( cell c2 c1 b ) ( cell c6 c4 b ) ( cell c7 c6 b ) ( cell c3 c4 b ) ( cell c6 c6 b ) ( cell c1 c2 b ) )","( ( cell c6 c7 b ) ( cell c1 c4 b ) ( cell c4 c4 b ) ( cell c5 c5 b ) ( cell c7 c2 b ) ( cell c7 c8 b ) ( cell c5 c3 s ) ( cell c5 c6 b ) ( cell c3 c3 s ) ( cell c3 c6 b ) ( cell c4 c2 b ) ( cell c1 c3 b ) ( cell c3 c7 b ) ( cell c7 c3 b ) ( cell c5 c7 b ) ( cell c6 c5 b ) ( cell c4 c7 b ) ( cell c4 c8 b ) ( cell c8 c1 b ) ( cell c4 c3 b ) ( cell c2 c5 b ) ( cell c2 c3 b ) ( cell c6 c1 b ) ( cell c1 c1 b ) ( cell c8 c3 b ) ( cell c3 c5 b ) ( cell c7 c1 b ) ( cell c2 c6 b ) ( cell c4 c6 b ) ( cell c6 c2 b ) ( cell c2 c8 b ) ( cell c2 c2 b ) ( cell c8 c8 b ) ( cell c7 c4 b ) ( cell c8 c5 b ) ( cell c4 c5 b ) ( cell c1 c5 b ) ( cell c6 c3 b ) ( cell c4 c1 b ) ( cell c3 c8 b ) ( cell c5 c1 b ) ( cell c1 c8 b ) ( cell c7 c5 b ) ( control sheep ) ( cell c3 c2 b ) ( cell c8 c6 w ) ( cell c2 c4 b ) ( cell c7 c7 b ) ( cell c6 c8 b ) ( cell c1 c6 b ) ( cell c5 c4 b ) ( cell c8 c4 s ) ( cell c1 c7 b ) ( cell c8 c7 b ) ( cell c5 c2 b ) ( cell c5 c8 b ) ( cell c2 c7 b ) ( cell c3 c1 s ) ( cell c8 c2 b ) ( cell c2 c1 b ) ( cell c6 c4 b ) ( cell c7 c6 b ) ( cell c3 c4 b ) ( cell c6 c6 b ) ( cell c1 c2 b ) )","( ( cell c3 c1 b ) ( cell c6 c7 b ) ( cell c1 c4 b ) ( cell c4 c4 b ) ( cell c5 c5 b ) ( cell c7 c2 b ) ( cell c7 c8 b ) ( cell c5 c3 s ) ( cell c5 c6 b ) ( cell c3 c3 s ) ( cell c3 c6 b ) ( cell c4 c2 b ) ( cell c1 c3 b ) ( cell c3 c7 b ) ( cell c7 c3 b ) ( cell c5 c7 b ) ( cell c6 c5 b ) ( cell c4 c7 b ) ( cell c4 c8 b ) ( cell c8 c1 b ) ( cell c4 c3 b ) ( cell c2 c5 b ) ( cell c2 c3 b ) ( cell c6 c1 b ) ( cell c1 c1 b ) ( cell c8 c3 b ) ( cell c3 c5 b ) ( cell c7 c1 b ) ( cell c2 c6 b ) ( cell c4 c6 b ) ( cell c6 c2 b ) ( cell c2 c8 b ) ( cell c8 c8 b ) ( cell c7 c4 b ) ( cell c8 c5 b ) ( cell c4 c5 b ) ( cell c1 c5 b ) ( cell c6 c3 b ) ( cell c4 c1 b ) ( cell c3 c8 b ) ( cell c2 c2 s ) ( cell c5 c1 b ) ( cell c1 c8 b ) ( cell c7 c5 b ) ( control wolf ) ( cell c3 c2 b ) ( cell c8 c6 w ) ( cell c2 c4 b ) ( cell c7 c7 b ) ( cell c6 c8 b ) ( cell c1 c6 b ) ( cell c5 c4 b ) ( cell c8 c4 s ) ( cell c1 c7 b ) ( cell c8 c7 b ) ( cell c5 c2 b ) ( cell c5 c8 b ) ( cell c2 c7 b ) ( cell c8 c2 b ) ( cell c2 c1 b ) ( cell c6 c4 b ) ( cell c7 c6 b ) ( cell c3 c4 b ) ( cell c6 c6 b ) ( cell c1 c2 b ) )","( ( cell c3 c1 b ) ( cell c6 c7 b ) ( cell c1 c4 b ) ( cell c4 c4 b ) ( cell c5 c5 b ) ( cell c7 c2 b ) ( cell c7 c8 b ) ( cell c5 c3 s ) ( cell c5 c6 b ) ( cell c3 c3 s ) ( cell c3 c6 b ) ( cell c4 c2 b ) ( cell c1 c3 b ) ( cell c3 c7 b ) ( cell c7 c3 b ) ( cell c5 c7 b ) ( cell c6 c5 b ) ( cell c4 c7 b ) ( cell c4 c8 b ) ( cell c8 c1 b ) ( cell c4 c3 b ) ( cell c2 c5 b ) ( cell c2 c3 b ) ( cell c7 c7 w ) ( cell c6 c1 b ) ( cell c1 c1 b ) ( cell c8 c3 b ) ( cell c3 c5 b ) ( cell c7 c1 b ) ( cell c2 c6 b ) ( cell c4 c6 b ) ( cell c6 c2 b ) ( cell c2 c8 b ) ( cell c8 c8 b ) ( cell c7 c4 b ) ( cell c8 c5 b ) ( cell c4 c5 b ) ( cell c1 c5 b ) ( cell c6 c3 b ) ( cell c4 c1 b ) ( cell c3 c8 b ) ( cell c2 c2 s ) ( cell c5 c1 b ) ( cell c1 c8 b ) ( cell c7 c5 b ) ( control sheep ) ( cell c3 c2 b ) ( cell c2 c4 b ) ( cell c6 c8 b ) ( cell c1 c6 b ) ( cell c8 c6 b ) ( cell c5 c4 b ) ( cell c8 c4 s ) ( cell c1 c7 b ) ( cell c8 c7 b ) ( cell c5 c2 b ) ( cell c5 c8 b ) ( cell c2 c7 b ) ( cell c8 c2 b ) ( cell c2 c1 b ) ( cell c6 c4 b ) ( cell c7 c6 b ) ( cell c3 c4 b ) ( cell c6 c6 b ) ( cell c1 c2 b ) )","( ( cell c3 c1 b ) ( cell c6 c7 b ) ( cell c1 c4 b ) ( cell c4 c4 b ) ( cell c5 c5 b ) ( cell c7 c2 b ) ( cell c7 c8 b ) ( cell c5 c3 s ) ( cell c5 c6 b ) ( cell c3 c3 s ) ( cell c3 c6 b ) ( cell c4 c2 b ) ( cell c3 c7 b ) ( cell c7 c3 b ) ( cell c5 c7 b ) ( cell c6 c5 b ) ( cell c4 c7 b ) ( cell c4 c8 b ) ( cell c8 c1 b ) ( cell c4 c3 b ) ( cell c2 c5 b ) ( cell c2 c3 b ) ( cell c7 c7 w ) ( cell c6 c1 b ) ( cell c1 c3 s ) ( cell c1 c1 b ) ( cell c8 c3 b ) ( cell c3 c5 b ) ( cell c7 c1 b ) ( cell c2 c6 b ) ( cell c4 c6 b ) ( cell c6 c2 b ) ( cell c2 c8 b ) ( cell c2 c2 b ) ( cell c8 c8 b ) ( cell c7 c4 b ) ( cell c8 c5 b ) ( cell c4 c5 b ) ( cell c1 c5 b ) ( cell c6 c3 b ) ( cell c4 c1 b ) ( cell c3 c8 b ) ( cell c5 c1 b ) ( cell c1 c8 b ) ( cell c7 c5 b ) ( control wolf ) ( cell c3 c2 b ) ( cell c2 c4 b ) ( cell c6 c8 b ) ( cell c1 c6 b ) ( cell c8 c6 b ) ( cell c5 c4 b ) ( cell c8 c4 s ) ( cell c1 c7 b ) ( cell c8 c7 b ) ( cell c5 c2 b ) ( cell c5 c8 b ) ( cell c2 c7 b ) ( cell c8 c2 b ) ( cell c2 c1 b ) ( cell c6 c4 b ) ( cell c7 c6 b ) ( cell c3 c4 b ) ( cell c6 c6 b ) ( cell c1 c2 b ) )","( ( cell c3 c1 b ) ( cell c6 c7 b ) ( cell c1 c4 b ) ( cell c4 c4 b ) ( cell c5 c5 b ) ( cell c7 c2 b ) ( cell c7 c8 b ) ( cell c5 c3 s ) ( cell c5 c6 b ) ( cell c3 c3 s ) ( cell c3 c6 b ) ( cell c4 c2 b ) ( cell c3 c7 b ) ( cell c7 c3 b ) ( cell c5 c7 b ) ( cell c6 c5 b ) ( cell c4 c7 b ) ( cell c4 c8 b ) ( cell c8 c1 b ) ( cell c4 c3 b ) ( cell c2 c5 b ) ( cell c2 c3 b ) ( cell c6 c1 b ) ( cell c1 c3 s ) ( cell c6 c8 w ) ( cell c1 c1 b ) ( cell c8 c3 b ) ( cell c3 c5 b ) ( cell c7 c1 b ) ( cell c2 c6 b ) ( cell c4 c6 b ) ( cell c6 c2 b ) ( cell c2 c8 b ) ( cell c2 c2 b ) ( cell c8 c8 b ) ( cell c7 c4 b ) ( cell c8 c5 b ) ( cell c4 c5 b ) ( cell c1 c5 b ) ( cell c6 c3 b ) ( cell c4 c1 b ) ( cell c3 c8 b ) ( cell c5 c1 b ) ( cell c1 c8 b ) ( cell c7 c5 b ) ( control sheep ) ( cell c3 c2 b ) ( cell c2 c4 b ) ( cell c7 c7 b ) ( cell c1 c6 b ) ( cell c8 c6 b ) ( cell c5 c4 b ) ( cell c8 c4 s ) ( cell c1 c7 b ) ( cell c8 c7 b ) ( cell c5 c2 b ) ( cell c5 c8 b ) ( cell c2 c7 b ) ( cell c8 c2 b ) ( cell c2 c1 b ) ( cell c6 c4 b ) ( cell c7 c6 b ) ( cell c3 c4 b ) ( cell c6 c6 b ) ( cell c1 c2 b ) )","( ( cell c3 c1 b ) ( cell c6 c7 b ) ( cell c1 c4 b ) ( cell c4 c4 b ) ( cell c5 c5 b ) ( cell c7 c2 b ) ( cell c7 c8 b ) ( cell c5 c3 s ) ( cell c5 c6 b ) ( cell c3 c6 b ) ( cell c4 c2 b ) ( cell c3 c7 b ) ( cell c7 c3 b ) ( cell c5 c7 b ) ( cell c6 c5 b ) ( cell c4 c7 b ) ( cell c4 c8 b ) ( cell c8 c1 b ) ( cell c4 c3 b ) ( cell c2 c5 b ) ( cell c2 c3 b ) ( cell c6 c1 b ) ( cell c1 c3 s ) ( cell c2 c4 s ) ( cell c6 c8 w ) ( cell c1 c1 b ) ( cell c8 c3 b ) ( cell c3 c5 b ) ( cell c7 c1 b ) ( cell c2 c6 b ) ( cell c4 c6 b ) ( cell c6 c2 b ) ( cell c2 c8 b ) ( cell c2 c2 b ) ( cell c8 c8 b ) ( cell c7 c4 b ) ( cell c8 c5 b ) ( cell c4 c5 b ) ( cell c1 c5 b ) ( cell c6 c3 b ) ( cell c4 c1 b ) ( cell c3 c8 b ) ( cell c5 c1 b ) ( cell c3 c3 b ) ( cell c1 c8 b ) ( cell c7 c5 b ) ( control wolf ) ( cell c3 c2 b ) ( cell c7 c7 b ) ( cell c1 c6 b ) ( cell c8 c6 b ) ( cell c5 c4 b ) ( cell c8 c4 s ) ( cell c1 c7 b ) ( cell c8 c7 b ) ( cell c5 c2 b ) ( cell c5 c8 b ) ( cell c2 c7 b ) ( cell c8 c2 b ) ( cell c2 c1 b ) ( cell c6 c4 b ) ( cell c7 c6 b ) ( cell c3 c4 b ) ( cell c6 c6 b ) ( cell c1 c2 b ) )","( ( cell c3 c1 b ) ( cell c6 c7 b ) ( cell c1 c4 b ) ( cell c4 c4 b ) ( cell c5 c5 b ) ( cell c7 c2 b ) ( cell c7 c8 b ) ( cell c5 c3 s ) ( cell c5 c6 b ) ( cell c3 c6 b ) ( cell c4 c2 b ) ( cell c3 c7 b ) ( cell c7 c3 b ) ( cell c5 c7 b ) ( cell c6 c5 b ) ( cell c4 c7 b ) ( cell c4 c8 b ) ( cell c8 c1 b ) ( cell c4 c3 b ) ( cell c2 c5 b ) ( cell c2 c3 b ) ( cell c7 c7 w ) ( cell c6 c1 b ) ( cell c1 c3 s ) ( cell c2 c4 s ) ( cell c1 c1 b ) ( cell c8 c3 b ) ( cell c3 c5 b ) ( cell c7 c1 b ) ( cell c2 c6 b ) ( cell c4 c6 b ) ( cell c6 c2 b ) ( cell c2 c8 b ) ( cell c2 c2 b ) ( cell c8 c8 b ) ( cell c7 c4 b ) ( cell c8 c5 b ) ( cell c4 c5 b ) ( cell c1 c5 b ) ( cell c6 c3 b ) ( cell c4 c1 b ) ( cell c3 c8 b ) ( cell c5 c1 b ) ( cell c3 c3 b ) ( cell c1 c8 b ) ( cell c7 c5 b ) ( control sheep ) ( cell c3 c2 b ) ( cell c6 c8 b ) ( cell c1 c6 b ) ( cell c8 c6 b ) ( cell c5 c4 b ) ( cell c8 c4 s ) ( cell c1 c7 b ) ( cell c8 c7 b ) ( cell c5 c2 b ) ( cell c5 c8 b ) ( cell c2 c7 b ) ( cell c8 c2 b ) ( cell c2 c1 b ) ( cell c6 c4 b ) ( cell c7 c6 b ) ( cell c3 c4 b ) ( cell c6 c6 b ) ( cell c1 c2 b ) )","( ( cell c3 c1 b ) ( cell c6 c7 b ) ( cell c1 c4 b ) ( cell c4 c4 b ) ( cell c5 c5 b ) ( cell c7 c2 b ) ( cell c7 c8 b ) ( cell c5 c3 s ) ( cell c5 c6 b ) ( cell c3 c6 b ) ( cell c4 c2 b ) ( cell c3 c7 b ) ( cell c7 c3 b ) ( cell c5 c7 b ) ( cell c6 c5 b ) ( cell c4 c7 b ) ( cell c4 c8 b ) ( cell c8 c1 b ) ( cell c4 c3 b ) ( cell c2 c5 b ) ( cell c2 c3 b ) ( cell c7 c7 w ) ( cell c6 c1 b ) ( cell c1 c3 s ) ( cell c1 c1 b ) ( cell c8 c3 b ) ( cell c7 c1 b ) ( cell c2 c6 b ) ( cell c4 c6 b ) ( cell c6 c2 b ) ( cell c2 c8 b ) ( cell c2 c2 b ) ( cell c8 c8 b ) ( cell c7 c4 b ) ( cell c8 c5 b ) ( cell c4 c5 b ) ( cell c1 c5 b ) ( cell c6 c3 b ) ( cell c4 c1 b ) ( cell c3 c8 b ) ( cell c5 c1 b ) ( cell c3 c3 b ) ( cell c1 c8 b ) ( cell c7 c5 b ) ( control wolf ) ( cell c3 c2 b ) ( cell c2 c4 b ) ( cell c6 c8 b ) ( cell c1 c6 b ) ( cell c8 c6 b ) ( cell c5 c4 b ) ( cell c3 c5 s ) ( cell c8 c4 s ) ( cell c1 c7 b ) ( cell c8 c7 b ) ( cell c5 c2 b ) ( cell c5 c8 b ) ( cell c2 c7 b ) ( cell c8 c2 b ) ( cell c2 c1 b ) ( cell c6 c4 b ) ( cell c7 c6 b ) ( cell c3 c4 b ) ( cell c6 c6 b ) ( cell c1 c2 b ) )","( ( cell c3 c1 b ) ( cell c6 c7 b ) ( cell c1 c4 b ) ( cell c4 c4 b ) ( cell c5 c5 b ) ( cell c7 c2 b ) ( cell c7 c8 b ) ( cell c5 c3 s ) ( cell c5 c6 b ) ( cell c3 c6 b ) ( cell c4 c2 b ) ( cell c3 c7 b ) ( cell c7 c3 b ) ( cell c5 c7 b ) ( cell c6 c5 b ) ( cell c4 c7 b ) ( cell c4 c8 b ) ( cell c8 c1 b ) ( cell c4 c3 b ) ( cell c2 c5 b ) ( cell c2 c3 b ) ( cell c6 c1 b ) ( cell c1 c3 s ) ( cell c1 c1 b ) ( cell c8 c3 b ) ( cell c7 c1 b ) ( cell c2 c6 b ) ( cell c4 c6 b ) ( cell c6 c2 b ) ( cell c2 c8 b ) ( cell c2 c2 b ) ( cell c7 c4 b ) ( cell c8 c5 b ) ( cell c4 c5 b ) ( cell c1 c5 b ) ( cell c6 c3 b ) ( cell c4 c1 b ) ( cell c3 c8 b ) ( cell c5 c1 b ) ( cell c3 c3 b ) ( cell c1 c8 b ) ( cell c7 c5 b ) ( control sheep ) ( cell c3 c2 b ) ( cell c2 c4 b ) ( cell c7 c7 b ) ( cell c6 c8 b ) ( cell c1 c6 b ) ( cell c8 c6 b ) ( cell c5 c4 b ) ( cell c3 c5 s ) ( cell c8 c4 s ) ( cell c1 c7 b ) ( cell c8 c7 b ) ( cell c5 c2 b ) ( cell c8 c8 w ) ( cell c5 c8 b ) ( cell c2 c7 b ) ( cell c8 c2 b ) ( cell c2 c1 b ) ( cell c6 c4 b ) ( cell c7 c6 b ) ( cell c3 c4 b ) ( cell c6 c6 b ) ( cell c1 c2 b ) )","( ( cell c3 c1 b ) ( cell c6 c7 b ) ( cell c1 c4 b ) ( cell c4 c4 b ) ( cell c5 c5 b ) ( cell c7 c2 b ) ( cell c7 c8 b ) ( cell c5 c3 s ) ( cell c5 c6 b ) ( cell c3 c6 b ) ( cell c4 c2 b ) ( cell c1 c3 b ) ( cell c3 c7 b ) ( cell c7 c3 b ) ( cell c5 c7 b ) ( cell c6 c5 b ) ( cell c4 c7 b ) ( cell c4 c8 b ) ( cell c8 c1 b ) ( cell c4 c3 b ) ( cell c2 c5 b ) ( cell c2 c3 b ) ( cell c6 c1 b ) ( cell c2 c4 s ) ( cell c1 c1 b ) ( cell c8 c3 b ) ( cell c7 c1 b ) ( cell c2 c6 b ) ( cell c4 c6 b ) ( cell c6 c2 b ) ( cell c2 c8 b ) ( cell c2 c2 b ) ( cell c7 c4 b ) ( cell c8 c5 b ) ( cell c4 c5 b ) ( cell c1 c5 b ) ( cell c6 c3 b ) ( cell c4 c1 b ) ( cell c3 c8 b ) ( cell c5 c1 b ) ( cell c3 c3 b ) ( cell c1 c8 b ) ( cell c7 c5 b ) ( control wolf ) ( cell c3 c2 b ) ( cell c7 c7 b ) ( cell c6 c8 b ) ( cell c1 c6 b ) ( cell c8 c6 b ) ( cell c5 c4 b ) ( cell c3 c5 s ) ( cell c8 c4 s ) ( cell c1 c7 b ) ( cell c8 c7 b ) ( cell c5 c2 b ) ( cell c8 c8 w ) ( cell c5 c8 b ) ( cell c2 c7 b ) ( cell c8 c2 b ) ( cell c2 c1 b ) ( cell c6 c4 b ) ( cell c7 c6 b ) ( cell c3 c4 b ) ( cell c6 c6 b ) ( cell c1 c2 b ) )","( ( cell c3 c1 b ) ( cell c6 c7 b ) ( cell c1 c4 b ) ( cell c4 c4 b ) ( cell c5 c5 b ) ( cell c7 c2 b ) ( cell c7 c8 b ) ( cell c5 c3 s ) ( cell c5 c6 b ) ( cell c3 c6 b ) ( cell c4 c2 b ) ( cell c1 c3 b ) ( cell c3 c7 b ) ( cell c7 c3 b ) ( cell c5 c7 b ) ( cell c6 c5 b ) ( cell c4 c7 b ) ( cell c4 c8 b ) ( cell c8 c1 b ) ( cell c4 c3 b ) ( cell c2 c5 b ) ( cell c2 c3 b ) ( cell c7 c7 w ) ( cell c6 c1 b ) ( cell c2 c4 s ) ( cell c1 c1 b ) ( cell c8 c3 b ) ( cell c7 c1 b ) ( cell c2 c6 b ) ( cell c4 c6 b ) ( cell c6 c2 b ) ( cell c2 c8 b ) ( cell c2 c2 b ) ( cell c8 c8 b ) ( cell c7 c4 b ) ( cell c8 c5 b ) ( cell c4 c5 b ) ( cell c1 c5 b ) ( cell c6 c3 b ) ( cell c4 c1 b ) ( cell c3 c8 b ) ( cell c5 c1 b ) ( cell c3 c3 b ) ( cell c1 c8 b ) ( cell c7 c5 b ) ( control sheep ) ( cell c3 c2 b ) ( cell c6 c8 b ) ( cell c1 c6 b ) ( cell c8 c6 b ) ( cell c5 c4 b ) ( cell c3 c5 s ) ( cell c8 c4 s ) ( cell c1 c7 b ) ( cell c8 c7 b ) ( cell c5 c2 b ) ( cell c5 c8 b ) ( cell c2 c7 b ) ( cell c8 c2 b ) ( cell c2 c1 b ) ( cell c6 c4 b ) ( cell c7 c6 b ) ( cell c3 c4 b ) ( cell c6 c6 b ) ( cell c1 c2 b ) )","( ( cell c3 c1 b ) ( cell c6 c7 b ) ( cell c1 c4 b ) ( cell c4 c4 b ) ( cell c5 c5 b ) ( cell c7 c2 b ) ( cell c7 c8 b ) ( cell c5 c6 b ) ( cell c3 c6 b ) ( cell c4 c2 b ) ( cell c1 c3 b ) ( cell c3 c7 b ) ( cell c7 c3 b ) ( cell c5 c7 b ) ( cell c6 c5 b ) ( cell c4 c7 b ) ( cell c4 c8 b ) ( cell c8 c1 b ) ( cell c4 c3 b ) ( cell c2 c5 b ) ( cell c2 c3 b ) ( cell c7 c7 w ) ( cell c6 c1 b ) ( cell c2 c4 s ) ( cell c1 c1 b ) ( cell c8 c3 b ) ( cell c7 c1 b ) ( cell c2 c6 b ) ( cell c4 c6 b ) ( cell c6 c2 b ) ( cell c2 c8 b ) ( cell c2 c2 b ) ( cell c8 c8 b ) ( cell c7 c4 b ) ( cell c8 c5 b ) ( cell c4 c5 b ) ( cell c1 c5 b ) ( cell c6 c3 b ) ( cell c5 c3 b ) ( cell c4 c1 b ) ( cell c3 c8 b ) ( cell c5 c1 b ) ( cell c3 c3 b ) ( cell c1 c8 b ) ( cell c7 c5 b ) ( control wolf ) ( cell c3 c2 b ) ( cell c6 c8 b ) ( cell c1 c6 b ) ( cell c8 c6 b ) ( cell c5 c4 b ) ( cell c3 c5 s ) ( cell c8 c4 s ) ( cell c1 c7 b ) ( cell c6 c4 s ) ( cell c8 c7 b ) ( cell c5 c2 b ) ( cell c5 c8 b ) ( cell c2 c7 b ) ( cell c8 c2 b ) ( cell c2 c1 b ) ( cell c7 c6 b ) ( cell c3 c4 b ) ( cell c6 c6 b ) ( cell c1 c2 b ) )","( ( cell c3 c1 b ) ( cell c6 c7 b ) ( cell c1 c4 b ) ( cell c4 c4 b ) ( cell c5 c5 b ) ( cell c7 c2 b ) ( cell c7 c8 b ) ( cell c5 c6 b ) ( cell c3 c6 b ) ( cell c4 c2 b ) ( cell c1 c3 b ) ( cell c3 c7 b ) ( cell c7 c3 b ) ( cell c5 c7 b ) ( cell c6 c5 b ) ( cell c4 c7 b ) ( cell c4 c8 b ) ( cell c8 c1 b ) ( cell c4 c3 b ) ( cell c2 c5 b ) ( cell c2 c3 b ) ( cell c6 c1 b ) ( cell c2 c4 s ) ( cell c1 c1 b ) ( cell c8 c3 b ) ( cell c7 c1 b ) ( cell c2 c6 b ) ( cell c4 c6 b ) ( cell c6 c2 b ) ( cell c2 c8 b ) ( cell c2 c2 b ) ( cell c8 c8 b ) ( cell c7 c4 b ) ( cell c8 c5 b ) ( cell c4 c5 b ) ( cell c1 c5 b ) ( cell c6 c3 b ) ( cell c5 c3 b ) ( cell c4 c1 b ) ( cell c3 c8 b ) ( cell c5 c1 b ) ( cell c3 c3 b ) ( cell c1 c8 b ) ( cell c7 c5 b ) ( control sheep ) ( cell c3 c2 b ) ( cell c8 c6 w ) ( cell c7 c7 b ) ( cell c6 c8 b ) ( cell c1 c6 b ) ( cell c5 c4 b ) ( cell c3 c5 s ) ( cell c8 c4 s ) ( cell c1 c7 b ) ( cell c6 c4 s ) ( cell c8 c7 b ) ( cell c5 c2 b ) ( cell c5 c8 b ) ( cell c2 c7 b ) ( cell c8 c2 b ) ( cell c2 c1 b ) ( cell c7 c6 b ) ( cell c3 c4 b ) ( cell c6 c6 b ) ( cell c1 c2 b ) )","( ( cell c3 c1 b ) ( cell c6 c7 b ) ( cell c1 c4 b ) ( cell c4 c4 b ) ( cell c5 c5 b ) ( cell c7 c2 b ) ( cell c7 c8 b ) ( cell c5 c6 b ) ( cell c3 c6 b ) ( cell c4 c2 b ) ( cell c1 c3 b ) ( cell c3 c7 b ) ( cell c7 c3 b ) ( cell c5 c7 b ) ( cell c6 c5 b ) ( cell c4 c7 b ) ( cell c4 c8 b ) ( cell c8 c1 b ) ( cell c4 c3 b ) ( cell c2 c5 b ) ( cell c2 c3 b ) ( cell c6 c1 b ) ( cell c2 c4 s ) ( cell c1 c1 b ) ( cell c8 c3 b ) ( cell c3 c5 b ) ( cell c7 c1 b ) ( cell c4 c6 b ) ( cell c6 c2 b ) ( cell c2 c8 b ) ( cell c2 c2 b ) ( cell c2 c6 s ) ( cell c8 c8 b ) ( cell c7 c4 b ) ( cell c8 c5 b ) ( cell c4 c5 b ) ( cell c1 c5 b ) ( cell c6 c3 b ) ( cell c5 c3 b ) ( cell c4 c1 b ) ( cell c3 c8 b ) ( cell c5 c1 b ) ( cell c3 c3 b ) ( cell c1 c8 b ) ( cell c7 c5 b ) ( control wolf ) ( cell c3 c2 b ) ( cell c8 c6 w ) ( cell c7 c7 b ) ( cell c6 c8 b ) ( cell c1 c6 b ) ( cell c5 c4 b ) ( cell c8 c4 s ) ( cell c1 c7 b ) ( cell c6 c4 s ) ( cell c8 c7 b ) ( cell c5 c2 b ) ( cell c5 c8 b ) ( cell c2 c7 b ) ( cell c8 c2 b ) ( cell c2 c1 b ) ( cell c7 c6 b ) ( cell c3 c4 b ) ( cell c6 c6 b ) ( cell c1 c2 b ) )","( ( cell c3 c1 b ) ( cell c6 c7 b ) ( cell c1 c4 b ) ( cell c4 c4 b ) ( cell c5 c5 b ) ( cell c7 c2 b ) ( cell c7 c8 b ) ( cell c5 c6 b ) ( cell c3 c6 b ) ( cell c4 c2 b ) ( cell c1 c3 b ) ( cell c3 c7 b ) ( cell c7 c3 b ) ( cell c5 c7 b ) ( cell c6 c5 b ) ( cell c4 c7 b ) ( cell c4 c8 b ) ( cell c8 c1 b ) ( cell c4 c3 b ) ( cell c2 c5 b ) ( cell c2 c3 b ) ( cell c6 c1 b ) ( cell c2 c4 s ) ( cell c1 c1 b ) ( cell c8 c3 b ) ( cell c3 c5 b ) ( cell c7 c1 b ) ( cell c4 c6 b ) ( cell c6 c2 b ) ( cell c2 c8 b ) ( cell c2 c2 b ) ( cell c2 c6 s ) ( cell c8 c8 b ) ( cell c7 c4 b ) ( cell c8 c5 b ) ( cell c4 c5 b ) ( cell c1 c5 b ) ( cell c6 c3 b ) ( cell c5 c3 b ) ( cell c4 c1 b ) ( cell c3 c8 b ) ( cell c5 c1 b ) ( cell c3 c3 b ) ( cell c1 c8 b ) ( control sheep ) ( cell c3 c2 b ) ( cell c7 c7 b ) ( cell c6 c8 b ) ( cell c1 c6 b ) ( cell c8 c6 b ) ( cell c5 c4 b ) ( cell c7 c5 w ) ( cell c8 c4 s ) ( cell c1 c7 b ) ( cell c6 c4 s ) ( cell c8 c7 b ) ( cell c5 c2 b ) ( cell c5 c8 b ) ( cell c2 c7 b ) ( cell c8 c2 b ) ( cell c2 c1 b ) ( cell c7 c6 b ) ( cell c3 c4 b ) ( cell c6 c6 b ) ( cell c1 c2 b ) )","( ( cell c3 c1 b ) ( cell c6 c7 b ) ( cell c1 c4 b ) ( cell c4 c4 b ) ( cell c5 c5 b ) ( cell c7 c2 b ) ( cell c7 c8 b ) ( cell c5 c6 b ) ( cell c3 c6 b ) ( cell c4 c2 b ) ( cell c1 c3 b ) ( cell c7 c3 b ) ( cell c5 c7 b ) ( cell c6 c5 b ) ( cell c4 c7 b ) ( cell c4 c8 b ) ( cell c8 c1 b ) ( cell c4 c3 b ) ( cell c2 c5 b ) ( cell c2 c3 b ) ( cell c6 c1 b ) ( cell c2 c4 s ) ( cell c1 c1 b ) ( cell c3 c7 s ) ( cell c8 c3 b ) ( cell c3 c5 b ) ( cell c7 c1 b ) ( cell c2 c6 b ) ( cell c4 c6 b ) ( cell c6 c2 b ) ( cell c2 c8 b ) ( cell c2 c2 b ) ( cell c8 c8 b ) ( cell c7 c4 b ) ( cell c8 c5 b ) ( cell c4 c5 b ) ( cell c1 c5 b ) ( cell c6 c3 b ) ( cell c5 c3 b ) ( cell c4 c1 b ) ( cell c3 c8 b ) ( cell c5 c1 b ) ( cell c3 c3 b ) ( cell c1 c8 b ) ( control wolf ) ( cell c3 c2 b ) ( cell c7 c7 b ) ( cell c6 c8 b ) ( cell c1 c6 b ) ( cell c8 c6 b ) ( cell c5 c4 b ) ( cell c7 c5 w ) ( cell c8 c4 s ) ( cell c1 c7 b ) ( cell c6 c4 s ) ( cell c8 c7 b ) ( cell c5 c2 b ) ( cell c5 c8 b ) ( cell c2 c7 b ) ( cell c8 c2 b ) ( cell c2 c1 b ) ( cell c7 c6 b ) ( cell c3 c4 b ) ( cell c6 c6 b ) ( cell c1 c2 b ) )","( ( cell c3 c1 b ) ( cell c6 c7 b ) ( cell c1 c4 b ) ( cell c4 c4 b ) ( cell c5 c5 b ) ( cell c7 c2 b ) ( cell c7 c8 b ) ( cell c5 c6 b ) ( cell c3 c6 b ) ( cell c4 c2 b ) ( cell c1 c3 b ) ( cell c7 c3 b ) ( cell c5 c7 b ) ( cell c6 c5 b ) ( cell c4 c7 b ) ( cell c4 c8 b ) ( cell c8 c1 b ) ( cell c4 c3 b ) ( cell c2 c5 b ) ( cell c2 c3 b ) ( cell c6 c1 b ) ( cell c2 c4 s ) ( cell c1 c1 b ) ( cell c3 c7 s ) ( cell c8 c3 b ) ( cell c3 c5 b ) ( cell c7 c1 b ) ( cell c2 c6 b ) ( cell c4 c6 b ) ( cell c6 c2 b ) ( cell c2 c8 b ) ( cell c2 c2 b ) ( cell c8 c8 b ) ( cell c7 c4 b ) ( cell c8 c5 b ) ( cell c4 c5 b ) ( cell c1 c5 b ) ( cell c6 c3 b ) ( cell c5 c3 b ) ( cell c4 c1 b ) ( cell c3 c8 b ) ( cell c5 c1 b ) ( cell c3 c3 b ) ( cell c1 c8 b ) ( cell c7 c5 b ) ( control sheep ) ( cell c3 c2 b ) ( cell c8 c6 w ) ( cell c7 c7 b ) ( cell c6 c8 b ) ( cell c1 c6 b ) ( cell c5 c4 b ) ( cell c8 c4 s ) ( cell c1 c7 b ) ( cell c6 c4 s ) ( cell c8 c7 b ) ( cell c5 c2 b ) ( cell c5 c8 b ) ( cell c2 c7 b ) ( cell c8 c2 b ) ( cell c2 c1 b ) ( cell c7 c6 b ) ( cell c3 c4 b ) ( cell c6 c6 b ) ( cell c1 c2 b ) )","( ( cell c3 c1 b ) ( cell c6 c7 b ) ( cell c1 c4 b ) ( cell c4 c4 b ) ( cell c5 c5 b ) ( cell c7 c2 b ) ( cell c7 c8 b ) ( cell c5 c6 b ) ( cell c3 c6 b ) ( cell c4 c2 b ) ( cell c1 c3 b ) ( cell c7 c3 b ) ( cell c5 c7 b ) ( cell c6 c5 b ) ( cell c4 c7 b ) ( cell c4 c8 b ) ( cell c8 c1 b ) ( cell c4 c3 b ) ( cell c2 c5 b ) ( cell c2 c3 b ) ( cell c6 c1 b ) ( cell c1 c1 b ) ( cell c3 c7 s ) ( cell c8 c3 b ) ( cell c7 c1 b ) ( cell c2 c6 b ) ( cell c4 c6 b ) ( cell c6 c2 b ) ( cell c2 c8 b ) ( cell c2 c2 b ) ( cell c8 c8 b ) ( cell c7 c4 b ) ( cell c8 c5 b ) ( cell c4 c5 b ) ( cell c1 c5 b ) ( cell c6 c3 b ) ( cell c5 c3 b ) ( cell c4 c1 b ) ( cell c3 c8 b ) ( cell c5 c1 b ) ( cell c3 c3 b ) ( cell c1 c8 b ) ( cell c7 c5 b ) ( control wolf ) ( cell c3 c2 b ) ( cell c8 c6 w ) ( cell c2 c4 b ) ( cell c7 c7 b ) ( cell c6 c8 b ) ( cell c1 c6 b ) ( cell c5 c4 b ) ( cell c3 c5 s ) ( cell c8 c4 s ) ( cell c1 c7 b ) ( cell c6 c4 s ) ( cell c8 c7 b ) ( cell c5 c2 b ) ( cell c5 c8 b ) ( cell c2 c7 b ) ( cell c8 c2 b ) ( cell c2 c1 b ) ( cell c7 c6 b ) ( cell c3 c4 b ) ( cell c6 c6 b ) ( cell c1 c2 b ) )","( ( cell c3 c1 b ) ( cell c6 c7 b ) ( cell c1 c4 b ) ( cell c4 c4 b ) ( cell c5 c5 b ) ( cell c7 c2 b ) ( cell c7 c8 b ) ( cell c5 c6 b ) ( cell c3 c6 b ) ( cell c4 c2 b ) ( cell c1 c3 b ) ( cell c7 c3 b ) ( cell c5 c7 b ) ( cell c6 c5 b ) ( cell c4 c7 b ) ( cell c4 c8 b ) ( cell c8 c1 b ) ( cell c4 c3 b ) ( cell c2 c5 b ) ( cell c2 c3 b ) ( cell c7 c7 w ) ( cell c6 c1 b ) ( cell c1 c1 b ) ( cell c3 c7 s ) ( cell c8 c3 b ) ( cell c7 c1 b ) ( cell c2 c6 b ) ( cell c4 c6 b ) ( cell c6 c2 b ) ( cell c2 c8 b ) ( cell c2 c2 b ) ( cell c8 c8 b ) ( cell c7 c4 b ) ( cell c8 c5 b ) ( cell c4 c5 b ) ( cell c1 c5 b ) ( cell c6 c3 b ) ( cell c5 c3 b ) ( cell c4 c1 b ) ( cell c3 c8 b ) ( cell c5 c1 b ) ( cell c3 c3 b ) ( cell c1 c8 b ) ( cell c7 c5 b ) ( control sheep ) ( cell c3 c2 b ) ( cell c2 c4 b ) ( cell c6 c8 b ) ( cell c1 c6 b ) ( cell c8 c6 b ) ( cell c5 c4 b ) ( cell c3 c5 s ) ( cell c8 c4 s ) ( cell c1 c7 b ) ( cell c6 c4 s ) ( cell c8 c7 b ) ( cell c5 c2 b ) ( cell c5 c8 b ) ( cell c2 c7 b ) ( cell c8 c2 b ) ( cell c2 c1 b ) ( cell c7 c6 b ) ( cell c3 c4 b ) ( cell c6 c6 b ) ( cell c1 c2 b ) )","( ( cell c3 c1 b ) ( cell c6 c7 b ) ( cell c1 c4 b ) ( cell c4 c4 b ) ( cell c5 c5 b ) ( cell c7 c2 b ) ( cell c7 c8 b ) ( cell c5 c6 b ) ( cell c3 c6 b ) ( cell c4 c2 b ) ( cell c1 c3 b ) ( cell c3 c7 b ) ( cell c7 c3 b ) ( cell c5 c7 b ) ( cell c6 c5 b ) ( cell c4 c7 b ) ( cell c8 c1 b ) ( cell c4 c3 b ) ( cell c2 c5 b ) ( cell c2 c3 b ) ( cell c7 c7 w ) ( cell c6 c1 b ) ( cell c1 c1 b ) ( cell c8 c3 b ) ( cell c7 c1 b ) ( cell c2 c6 b ) ( cell c4 c6 b ) ( cell c6 c2 b ) ( cell c2 c8 b ) ( cell c2 c2 b ) ( cell c8 c8 b ) ( cell c7 c4 b ) ( cell c8 c5 b ) ( cell c4 c5 b ) ( cell c1 c5 b ) ( cell c6 c3 b ) ( cell c5 c3 b ) ( cell c4 c1 b ) ( cell c3 c8 b ) ( cell c5 c1 b ) ( cell c3 c3 b ) ( cell c1 c8 b ) ( cell c7 c5 b ) ( control wolf ) ( cell c4 c8 s ) ( cell c3 c2 b ) ( cell c2 c4 b ) ( cell c6 c8 b ) ( cell c1 c6 b ) ( cell c8 c6 b ) ( cell c5 c4 b ) ( cell c3 c5 s ) ( cell c8 c4 s ) ( cell c1 c7 b ) ( cell c6 c4 s ) ( cell c8 c7 b ) ( cell c5 c2 b ) ( cell c5 c8 b ) ( cell c2 c7 b ) ( cell c8 c2 b ) ( cell c2 c1 b ) ( cell c7 c6 b ) ( cell c3 c4 b ) ( cell c6 c6 b ) ( cell c1 c2 b ) )","( ( cell c3 c1 b ) ( cell c6 c7 b ) ( cell c1 c4 b ) ( cell c4 c4 b ) ( cell c5 c5 b ) ( cell c7 c2 b ) ( cell c7 c8 b ) ( cell c5 c6 b ) ( cell c3 c6 b ) ( cell c4 c2 b ) ( cell c1 c3 b ) ( cell c3 c7 b ) ( cell c7 c3 b ) ( cell c5 c7 b ) ( cell c6 c5 b ) ( cell c4 c7 b ) ( cell c8 c1 b ) ( cell c4 c3 b ) ( cell c2 c5 b ) ( cell c2 c3 b ) ( cell c6 c1 b ) ( cell c6 c8 w ) ( cell c1 c1 b ) ( cell c8 c3 b ) ( cell c7 c1 b ) ( cell c2 c6 b ) ( cell c4 c6 b ) ( cell c6 c2 b ) ( cell c2 c8 b ) ( cell c2 c2 b ) ( cell c8 c8 b ) ( cell c7 c4 b ) ( cell c8 c5 b ) ( cell c4 c5 b ) ( cell c1 c5 b ) ( cell c6 c3 b ) ( cell c5 c3 b ) ( cell c4 c1 b ) ( cell c3 c8 b ) ( cell c5 c1 b ) ( cell c3 c3 b ) ( cell c1 c8 b ) ( cell c7 c5 b ) ( cell c4 c8 s ) ( control sheep ) ( cell c3 c2 b ) ( cell c2 c4 b ) ( cell c7 c7 b ) ( cell c1 c6 b ) ( cell c8 c6 b ) ( cell c5 c4 b ) ( cell c3 c5 s ) ( cell c8 c4 s ) ( cell c1 c7 b ) ( cell c6 c4 s ) ( cell c8 c7 b ) ( cell c5 c2 b ) ( cell c5 c8 b ) ( cell c2 c7 b ) ( cell c8 c2 b ) ( cell c2 c1 b ) ( cell c7 c6 b ) ( cell c3 c4 b ) ( cell c6 c6 b ) ( cell c1 c2 b ) )","( ( cell c3 c1 b ) ( cell c6 c7 b ) ( cell c1 c4 b ) ( cell c4 c4 b ) ( cell c5 c5 b ) ( cell c7 c2 b ) ( cell c7 c8 b ) ( cell c5 c6 b ) ( cell c3 c6 b ) ( cell c4 c2 b ) ( cell c1 c3 b ) ( cell c3 c7 b ) ( cell c7 c3 b ) ( cell c5 c7 b ) ( cell c6 c5 b ) ( cell c4 c7 b ) ( cell c8 c1 b ) ( cell c4 c3 b ) ( cell c2 c5 b ) ( cell c2 c3 b ) ( cell c6 c1 b ) ( cell c6 c8 w ) ( cell c1 c1 b ) ( cell c8 c3 b ) ( cell c3 c5 b ) ( cell c7 c1 b ) ( cell c4 c6 b ) ( cell c6 c2 b ) ( cell c2 c8 b ) ( cell c2 c2 b ) ( cell c2 c6 s ) ( cell c8 c8 b ) ( cell c7 c4 b ) ( cell c8 c5 b ) ( cell c4 c5 b ) ( cell c1 c5 b ) ( cell c6 c3 b ) ( cell c5 c3 b ) ( cell c4 c1 b ) ( cell c3 c8 b ) ( cell c5 c1 b ) ( cell c3 c3 b ) ( cell c1 c8 b ) ( cell c7 c5 b ) ( control wolf ) ( cell c4 c8 s ) ( cell c3 c2 b ) ( cell c2 c4 b ) ( cell c7 c7 b ) ( cell c1 c6 b ) ( cell c8 c6 b ) ( cell c5 c4 b ) ( cell c8 c4 s ) ( cell c1 c7 b ) ( cell c6 c4 s ) ( cell c8 c7 b ) ( cell c5 c2 b ) ( cell c5 c8 b ) ( cell c2 c7 b ) ( cell c8 c2 b ) ( cell c2 c1 b ) ( cell c7 c6 b ) ( cell c3 c4 b ) ( cell c6 c6 b ) ( cell c1 c2 b ) )","( ( cell c3 c1 b ) ( cell c6 c7 b ) ( cell c1 c4 b ) ( cell c4 c4 b ) ( cell c5 c5 b ) ( cell c7 c2 b ) ( cell c7 c8 b ) ( cell c5 c6 b ) ( cell c3 c6 b ) ( cell c4 c2 b ) ( cell c1 c3 b ) ( cell c3 c7 b ) ( cell c7 c3 b ) ( cell c5 c7 b ) ( cell c6 c5 b ) ( cell c4 c7 b ) ( cell c8 c1 b ) ( cell c4 c3 b ) ( cell c2 c5 b ) ( cell c2 c3 b ) ( cell c7 c7 w ) ( cell c6 c1 b ) ( cell c1 c1 b ) ( cell c8 c3 b ) ( cell c3 c5 b ) ( cell c7 c1 b ) ( cell c4 c6 b ) ( cell c6 c2 b ) ( cell c2 c8 b ) ( cell c2 c2 b ) ( cell c2 c6 s ) ( cell c8 c8 b ) ( cell c7 c4 b ) ( cell c8 c5 b ) ( cell c4 c5 b ) ( cell c1 c5 b ) ( cell c6 c3 b ) ( cell c5 c3 b ) ( cell c4 c1 b ) ( cell c3 c8 b ) ( cell c5 c1 b ) ( cell c3 c3 b ) ( cell c1 c8 b ) ( cell c7 c5 b ) ( cell c4 c8 s ) ( control sheep ) ( cell c3 c2 b ) ( cell c2 c4 b ) ( cell c6 c8 b ) ( cell c1 c6 b ) ( cell c8 c6 b ) ( cell c5 c4 b ) ( cell c8 c4 s ) ( cell c1 c7 b ) ( cell c6 c4 s ) ( cell c8 c7 b ) ( cell c5 c2 b ) ( cell c5 c8 b ) ( cell c2 c7 b ) ( cell c8 c2 b ) ( cell c2 c1 b ) ( cell c7 c6 b ) ( cell c3 c4 b ) ( cell c6 c6 b ) ( cell c1 c2 b ) )","( ( cell c3 c1 b ) ( cell c6 c7 b ) ( cell c1 c4 b ) ( cell c4 c4 b ) ( cell c5 c5 b ) ( cell c7 c2 b ) ( cell c7 c8 b ) ( cell c5 c6 b ) ( cell c3 c6 b ) ( cell c4 c2 b ) ( cell c1 c3 b ) ( cell c3 c7 b ) ( cell c7 c3 b ) ( cell c5 c7 b ) ( cell c6 c5 b ) ( cell c4 c7 b ) ( cell c8 c1 b ) ( cell c8 c4 b ) ( cell c4 c3 b ) ( cell c2 c5 b ) ( cell c2 c3 b ) ( cell c7 c7 w ) ( cell c6 c1 b ) ( cell c1 c1 b ) ( cell c8 c3 b ) ( cell c3 c5 b ) ( cell c7 c1 b ) ( cell c4 c6 b ) ( cell c6 c2 b ) ( cell c2 c8 b ) ( cell c2 c2 b ) ( cell c2 c6 s ) ( cell c8 c8 b ) ( cell c7 c4 b ) ( cell c8 c5 b ) ( cell c4 c5 b ) ( cell c1 c5 b ) ( cell c6 c3 b ) ( cell c5 c3 b ) ( cell c4 c1 b ) ( cell c3 c8 b ) ( cell c5 c1 b ) ( cell c3 c3 b ) ( cell c1 c8 b ) ( control wolf ) ( cell c4 c8 s ) ( cell c3 c2 b ) ( cell c2 c4 b ) ( cell c6 c8 b ) ( cell c1 c6 b ) ( cell c8 c6 b ) ( cell c5 c4 b ) ( cell c1 c7 b ) ( cell c6 c4 s ) ( cell c8 c7 b ) ( cell c5 c2 b ) ( cell c5 c8 b ) ( cell c2 c7 b ) ( cell c8 c2 b ) ( cell c2 c1 b ) ( cell c7 c5 s ) ( cell c7 c6 b ) ( cell c3 c4 b ) ( cell c6 c6 b ) ( cell c1 c2 b ) )","( ( cell c3 c1 b ) ( cell c6 c7 b ) ( cell c1 c4 b ) ( cell c4 c4 b ) ( cell c5 c5 b ) ( cell c7 c2 b ) ( cell c7 c8 b ) ( cell c5 c6 b ) ( cell c3 c6 b ) ( cell c4 c2 b ) ( cell c1 c3 b ) ( cell c3 c7 b ) ( cell c7 c3 b ) ( cell c5 c7 b ) ( cell c6 c5 b ) ( cell c4 c7 b ) ( cell c8 c1 b ) ( cell c8 c4 b ) ( cell c4 c3 b ) ( cell c2 c5 b ) ( cell c2 c3 b ) ( cell c6 c1 b ) ( cell c6 c8 w ) ( cell c1 c1 b ) ( cell c8 c3 b ) ( cell c3 c5 b ) ( cell c7 c1 b ) ( cell c4 c6 b ) ( cell c6 c2 b ) ( cell c2 c8 b ) ( cell c2 c2 b ) ( cell c2 c6 s ) ( cell c8 c8 b ) ( cell c7 c4 b ) ( cell c8 c5 b ) ( cell c4 c5 b ) ( cell c1 c5 b ) ( cell c6 c3 b ) ( cell c5 c3 b ) ( cell c4 c1 b ) ( cell c3 c8 b ) ( cell c5 c1 b ) ( cell c3 c3 b ) ( cell c1 c8 b ) ( cell c4 c8 s ) ( control sheep ) ( cell c3 c2 b ) ( cell c2 c4 b ) ( cell c7 c7 b ) ( cell c1 c6 b ) ( cell c8 c6 b ) ( cell c5 c4 b ) ( cell c1 c7 b ) ( cell c6 c4 s ) ( cell c8 c7 b ) ( cell c5 c2 b ) ( cell c5 c8 b ) ( cell c2 c7 b ) ( cell c8 c2 b ) ( cell c2 c1 b ) ( cell c7 c5 s ) ( cell c7 c6 b ) ( cell c3 c4 b ) ( cell c6 c6 b ) ( cell c1 c2 b ) )","( ( cell c3 c1 b ) ( cell c6 c7 b ) ( cell c1 c4 b ) ( cell c4 c4 b ) ( cell c5 c5 b ) ( cell c7 c2 b ) ( cell c7 c8 b ) ( cell c5 c6 b ) ( cell c3 c6 b ) ( cell c4 c2 b ) ( cell c1 c3 b ) ( cell c3 c7 b ) ( cell c7 c3 b ) ( cell c5 c7 b ) ( cell c6 c5 b ) ( cell c4 c7 b ) ( cell c8 c1 b ) ( cell c8 c4 b ) ( cell c4 c3 b ) ( cell c2 c5 b ) ( cell c2 c3 b ) ( cell c6 c1 b ) ( cell c6 c8 w ) ( cell c1 c1 b ) ( cell c8 c3 b ) ( cell c3 c5 b ) ( cell c7 c1 b ) ( cell c2 c6 b ) ( cell c4 c6 b ) ( cell c6 c2 b ) ( cell c2 c8 b ) ( cell c2 c2 b ) ( cell c8 c8 b ) ( cell c7 c4 b ) ( cell c8 c5 b ) ( cell c4 c5 b ) ( cell c1 c5 b ) ( cell c6 c3 b ) ( cell c5 c3 b ) ( cell c4 c1 b ) ( cell c3 c8 b ) ( cell c5 c1 b ) ( cell c3 c3 b ) ( cell c1 c8 b ) ( control wolf ) ( cell c4 c8 s ) ( cell c3 c2 b ) ( cell c2 c4 b ) ( cell c7 c7 b ) ( cell c1 c6 b ) ( cell c8 c6 b ) ( cell c5 c4 b ) ( cell c6 c4 s ) ( cell c8 c7 b ) ( cell c5 c2 b ) ( cell c5 c8 b ) ( cell c2 c7 b ) ( cell c1 c7 s ) ( cell c8 c2 b ) ( cell c2 c1 b ) ( cell c7 c5 s ) ( cell c7 c6 b ) ( cell c3 c4 b ) ( cell c6 c6 b ) ( cell c1 c2 b ) )","( ( cell c3 c1 b ) ( cell c6 c7 b ) ( cell c1 c4 b ) ( cell c4 c4 b ) ( cell c5 c5 b ) ( cell c7 c2 b ) ( cell c7 c8 b ) ( cell c5 c6 b ) ( cell c3 c6 b ) ( cell c4 c2 b ) ( cell c1 c3 b ) ( cell c3 c7 b ) ( cell c7 c3 b ) ( cell c5 c7 b ) ( cell c6 c5 b ) ( cell c4 c7 b ) ( cell c8 c1 b ) ( cell c8 c4 b ) ( cell c4 c3 b ) ( cell c2 c5 b ) ( cell c2 c3 b ) ( cell c7 c7 w ) ( cell c6 c1 b ) ( cell c1 c1 b ) ( cell c8 c3 b ) ( cell c3 c5 b ) ( cell c7 c1 b ) ( cell c2 c6 b ) ( cell c4 c6 b ) ( cell c6 c2 b ) ( cell c2 c8 b ) ( cell c2 c2 b ) ( cell c8 c8 b ) ( cell c7 c4 b ) ( cell c8 c5 b ) ( cell c4 c5 b ) ( cell c1 c5 b ) ( cell c6 c3 b ) ( cell c5 c3 b ) ( cell c4 c1 b ) ( cell c3 c8 b ) ( cell c5 c1 b ) ( cell c3 c3 b ) ( cell c1 c8 b ) ( cell c4 c8 s ) ( control sheep ) ( cell c3 c2 b ) ( cell c2 c4 b ) ( cell c6 c8 b ) ( cell c1 c6 b ) ( cell c8 c6 b ) ( cell c5 c4 b ) ( cell c6 c4 s ) ( cell c8 c7 b ) ( cell c5 c2 b ) ( cell c5 c8 b ) ( cell c2 c7 b ) ( cell c1 c7 s ) ( cell c8 c2 b ) ( cell c2 c1 b ) ( cell c7 c5 s ) ( cell c7 c6 b ) ( cell c3 c4 b ) ( cell c6 c6 b ) ( cell c1 c2 b ) )","( ( cell c8 c6 s ) ( cell c3 c1 b ) ( cell c6 c7 b ) ( cell c1 c4 b ) ( cell c4 c4 b ) ( cell c5 c5 b ) ( cell c7 c2 b ) ( cell c7 c8 b ) ( cell c5 c6 b ) ( cell c3 c6 b ) ( cell c4 c2 b ) ( cell c1 c3 b ) ( cell c3 c7 b ) ( cell c7 c3 b ) ( cell c5 c7 b ) ( cell c6 c5 b ) ( cell c4 c7 b ) ( cell c8 c1 b ) ( cell c8 c4 b ) ( cell c4 c3 b ) ( cell c2 c5 b ) ( cell c2 c3 b ) ( cell c7 c7 w ) ( cell c6 c1 b ) ( cell c1 c1 b ) ( cell c8 c3 b ) ( cell c3 c5 b ) ( cell c7 c1 b ) ( cell c2 c6 b ) ( cell c4 c6 b ) ( cell c6 c2 b ) ( cell c2 c8 b ) ( cell c2 c2 b ) ( cell c8 c8 b ) ( cell c7 c4 b ) ( cell c8 c5 b ) ( cell c4 c5 b ) ( cell c1 c5 b ) ( cell c6 c3 b ) ( cell c5 c3 b ) ( cell c4 c1 b ) ( cell c3 c8 b ) ( cell c5 c1 b ) ( cell c3 c3 b ) ( cell c1 c8 b ) ( cell c7 c5 b ) ( control wolf ) ( cell c4 c8 s ) ( cell c3 c2 b ) ( cell c2 c4 b ) ( cell c6 c8 b ) ( cell c1 c6 b ) ( cell c5 c4 b ) ( cell c6 c4 s ) ( cell c8 c7 b ) ( cell c5 c2 b ) ( cell c5 c8 b ) ( cell c2 c7 b ) ( cell c1 c7 s ) ( cell c8 c2 b ) ( cell c2 c1 b ) ( cell c7 c6 b ) ( cell c3 c4 b ) ( cell c6 c6 b ) ( cell c1 c2 b ) )","( ( cell c8 c6 s ) ( cell c3 c1 b ) ( cell c6 c7 b ) ( cell c1 c4 b ) ( cell c4 c4 b ) ( cell c5 c5 b ) ( cell c7 c2 b ) ( cell c7 c8 b ) ( cell c5 c6 b ) ( cell c3 c6 b ) ( cell c4 c2 b ) ( cell c1 c3 b ) ( cell c3 c7 b ) ( cell c7 c3 b ) ( cell c5 c7 b ) ( cell c6 c5 b ) ( cell c4 c7 b ) ( cell c8 c1 b ) ( cell c8 c4 b ) ( cell c4 c3 b ) ( cell c2 c5 b ) ( cell c2 c3 b ) ( cell c6 c1 b ) ( cell c6 c8 w ) ( cell c1 c1 b ) ( cell c8 c3 b ) ( cell c3 c5 b ) ( cell c7 c1 b ) ( cell c2 c6 b ) ( cell c4 c6 b ) ( cell c6 c2 b ) ( cell c2 c8 b ) ( cell c2 c2 b ) ( cell c8 c8 b ) ( cell c7 c4 b ) ( cell c8 c5 b ) ( cell c4 c5 b ) ( cell c1 c5 b ) ( cell c6 c3 b ) ( cell c5 c3 b ) ( cell c4 c1 b ) ( cell c3 c8 b ) ( cell c5 c1 b ) ( cell c3 c3 b ) ( cell c1 c8 b ) ( cell c7 c5 b ) ( cell c4 c8 s ) ( control sheep ) ( cell c3 c2 b ) ( cell c2 c4 b ) ( cell c7 c7 b ) ( cell c1 c6 b ) ( cell c5 c4 b ) ( cell c6 c4 s ) ( cell c8 c7 b ) ( cell c5 c2 b ) ( cell c5 c8 b ) ( cell c2 c7 b ) ( cell c1 c7 s ) ( cell c8 c2 b ) ( cell c2 c1 b ) ( cell c7 c6 b ) ( cell c3 c4 b ) ( cell c6 c6 b ) ( cell c1 c2 b ) )","( ( cell c8 c6 s ) ( cell c3 c1 b ) ( cell c6 c7 b ) ( cell c1 c4 b ) ( cell c4 c4 b ) ( cell c5 c5 b ) ( cell c7 c2 b ) ( cell c7 c8 b ) ( cell c5 c6 b ) ( cell c3 c6 b ) ( cell c4 c2 b ) ( cell c1 c3 b ) ( cell c3 c7 b ) ( cell c7 c3 b ) ( cell c5 c7 b ) ( cell c6 c5 b ) ( cell c4 c7 b ) ( cell c8 c1 b ) ( cell c8 c4 b ) ( cell c4 c3 b ) ( cell c2 c5 b ) ( cell c2 c3 b ) ( cell c6 c1 b ) ( cell c6 c8 w ) ( cell c1 c1 b ) ( cell c8 c3 b ) ( cell c3 c5 b ) ( cell c7 c1 b ) ( cell c2 c6 b ) ( cell c4 c6 b ) ( cell c6 c2 b ) ( cell c2 c8 b ) ( cell c2 c2 b ) ( cell c8 c8 b ) ( cell c7 c4 b ) ( cell c8 c5 b ) ( cell c4 c5 b ) ( cell c1 c5 b ) ( cell c6 c3 b ) ( cell c5 c3 b ) ( cell c4 c1 b ) ( cell c3 c8 b ) ( cell c5 c1 b ) ( cell c3 c3 b ) ( cell c1 c8 b ) ( control wolf ) ( cell c4 c8 s ) ( cell c3 c2 b ) ( cell c2 c4 b ) ( cell c7 c7 b ) ( cell c1 c6 b ) ( cell c5 c4 b ) ( cell c8 c7 b ) ( cell c5 c2 b ) ( cell c5 c8 b ) ( cell c2 c7 b ) ( cell c1 c7 s ) ( cell c8 c2 b ) ( cell c2 c1 b ) ( cell c7 c5 s ) ( cell c6 c4 b ) ( cell c7 c6 b ) ( cell c3 c4 b ) ( cell c6 c6 b ) ( cell c1 c2 b ) )","( ( cell c8 c6 s ) ( cell c3 c1 b ) ( cell c6 c7 b ) ( cell c1 c4 b ) ( cell c4 c4 b ) ( cell c5 c5 b ) ( cell c7 c2 b ) ( cell c7 c8 b ) ( cell c5 c6 b ) ( cell c3 c6 b ) ( cell c4 c2 b ) ( cell c1 c3 b ) ( cell c3 c7 b ) ( cell c7 c3 b ) ( cell c5 c7 b ) ( cell c6 c5 b ) ( cell c4 c7 b ) ( cell c8 c1 b ) ( cell c8 c4 b ) ( cell c4 c3 b ) ( cell c2 c5 b ) ( cell c2 c3 b ) ( cell c7 c7 w ) ( cell c6 c1 b ) ( cell c1 c1 b ) ( cell c8 c3 b ) ( cell c3 c5 b ) ( cell c7 c1 b ) ( cell c2 c6 b ) ( cell c4 c6 b ) ( cell c6 c2 b ) ( cell c2 c8 b ) ( cell c2 c2 b ) ( cell c8 c8 b ) ( cell c7 c4 b ) ( cell c8 c5 b ) ( cell c4 c5 b ) ( cell c1 c5 b ) ( cell c6 c3 b ) ( cell c5 c3 b ) ( cell c4 c1 b ) ( cell c3 c8 b ) ( cell c5 c1 b ) ( cell c3 c3 b ) ( cell c1 c8 b ) ( cell c4 c8 s ) ( control sheep ) ( cell c3 c2 b ) ( cell c2 c4 b ) ( cell c6 c8 b ) ( cell c1 c6 b ) ( cell c5 c4 b ) ( cell c8 c7 b ) ( cell c5 c2 b ) ( cell c5 c8 b ) ( cell c2 c7 b ) ( cell c1 c7 s ) ( cell c8 c2 b ) ( cell c2 c1 b ) ( cell c7 c5 s ) ( cell c6 c4 b ) ( cell c7 c6 b ) ( cell c3 c4 b ) ( cell c6 c6 b ) ( cell c1 c2 b ) )","( ( cell c8 c6 s ) ( cell c3 c1 b ) ( cell c6 c7 b ) ( cell c1 c4 b ) ( cell c4 c4 b ) ( cell c5 c5 b ) ( cell c7 c2 b ) ( cell c7 c8 b ) ( cell c5 c6 b ) ( cell c3 c6 b ) ( cell c4 c2 b ) ( cell c1 c3 b ) ( cell c3 c7 b ) ( cell c7 c3 b ) ( cell c5 c7 b ) ( cell c6 c5 b ) ( cell c4 c7 b ) ( cell c8 c1 b ) ( cell c8 c4 b ) ( cell c4 c3 b ) ( cell c2 c5 b ) ( cell c2 c3 b ) ( cell c7 c7 w ) ( cell c6 c1 b ) ( cell c1 c1 b ) ( cell c8 c3 b ) ( cell c3 c5 b ) ( cell c7 c1 b ) ( cell c2 c6 b ) ( cell c4 c6 b ) ( cell c6 c2 b ) ( cell c2 c8 b ) ( cell c2 c2 b ) ( cell c8 c8 b ) ( cell c7 c4 b ) ( cell c8 c5 b ) ( cell c4 c5 b ) ( cell c1 c5 b ) ( cell c6 c3 b ) ( cell c5 c3 b ) ( cell c4 c1 b ) ( cell c3 c8 b ) ( cell c6 c6 s ) ( cell c5 c1 b ) ( cell c3 c3 b ) ( cell c1 c8 b ) ( cell c7 c5 b ) ( control wolf ) ( cell c4 c8 s ) ( cell c3 c2 b ) ( cell c2 c4 b ) ( cell c6 c8 b ) ( cell c1 c6 b ) ( cell c5 c4 b ) ( cell c8 c7 b ) ( cell c5 c2 b ) ( cell c5 c8 b ) ( cell c2 c7 b ) ( cell c1 c7 s ) ( cell c8 c2 b ) ( cell c2 c1 b ) ( cell c6 c4 b ) ( cell c7 c6 b ) ( cell c3 c4 b ) ( cell c1 c2 b ) )","( ( cell c8 c6 s ) ( cell c3 c1 b ) ( cell c6 c7 b ) ( cell c1 c4 b ) ( cell c4 c4 b ) ( cell c5 c5 b ) ( cell c7 c2 b ) ( cell c7 c8 b ) ( cell c5 c6 b ) ( cell c3 c6 b ) ( cell c4 c2 b ) ( cell c1 c3 b ) ( cell c3 c7 b ) ( cell c7 c3 b ) ( cell c5 c7 b ) ( cell c6 c5 b ) ( cell c4 c7 b ) ( cell c8 c1 b ) ( cell c8 c4 b ) ( cell c4 c3 b ) ( cell c2 c5 b ) ( cell c2 c3 b ) ( cell c6 c1 b ) ( cell c6 c8 w ) ( cell c1 c1 b ) ( cell c8 c3 b ) ( cell c3 c5 b ) ( cell c7 c1 b ) ( cell c2 c6 b ) ( cell c4 c6 b ) ( cell c6 c2 b ) ( cell c2 c8 b ) ( cell c2 c2 b ) ( cell c8 c8 b ) ( cell c7 c4 b ) ( cell c8 c5 b ) ( cell c4 c5 b ) ( cell c1 c5 b ) ( cell c6 c3 b ) ( cell c5 c3 b ) ( cell c4 c1 b ) ( cell c3 c8 b ) ( cell c6 c6 s ) ( cell c5 c1 b ) ( cell c3 c3 b ) ( cell c1 c8 b ) ( cell c7 c5 b ) ( cell c4 c8 s ) ( control sheep ) ( cell c3 c2 b ) ( cell c2 c4 b ) ( cell c7 c7 b ) ( cell c1 c6 b ) ( cell c5 c4 b ) ( cell c8 c7 b ) ( cell c5 c2 b ) ( cell c5 c8 b ) ( cell c2 c7 b ) ( cell c1 c7 s ) ( cell c8 c2 b ) ( cell c2 c1 b ) ( cell c6 c4 b ) ( cell c7 c6 b ) ( cell c3 c4 b ) ( cell c1 c2 b ) )","( ( cell c3 c1 b ) ( cell c6 c7 b ) ( cell c1 c4 b ) ( cell c4 c4 b ) ( cell c5 c5 b ) ( cell c7 c2 b ) ( cell c7 c8 b ) ( cell c5 c6 b ) ( cell c3 c6 b ) ( cell c4 c2 b ) ( cell c1 c3 b ) ( cell c3 c7 b ) ( cell c7 c3 b ) ( cell c5 c7 b ) ( cell c6 c5 b ) ( cell c4 c7 b ) ( cell c8 c1 b ) ( cell c8 c4 b ) ( cell c4 c3 b ) ( cell c2 c5 b ) ( cell c2 c3 b ) ( cell c6 c1 b ) ( cell c6 c8 w ) ( cell c1 c1 b ) ( cell c8 c3 b ) ( cell c3 c5 b ) ( cell c7 c1 b ) ( cell c2 c6 b ) ( cell c4 c6 b ) ( cell c6 c2 b ) ( cell c2 c8 b ) ( cell c2 c2 b ) ( cell c8 c8 b ) ( cell c7 c4 b ) ( cell c8 c5 b ) ( cell c4 c5 b ) ( cell c1 c5 b ) ( cell c6 c3 b ) ( cell c5 c3 b ) ( cell c4 c1 b ) ( cell c3 c8 b ) ( cell c6 c6 s ) ( cell c5 c1 b ) ( cell c3 c3 b ) ( cell c1 c8 b ) ( cell c7 c5 b ) ( control wolf ) ( cell c4 c8 s ) ( cell c3 c2 b ) ( cell c2 c4 b ) ( cell c1 c6 b ) ( cell c8 c6 b ) ( cell c5 c4 b ) ( cell c7 c7 s ) ( cell c8 c7 b ) ( cell c5 c2 b ) ( cell c5 c8 b ) ( cell c2 c7 b ) ( cell c1 c7 s ) ( cell c8 c2 b ) ( cell c2 c1 b ) ( cell c6 c4 b ) ( cell c7 c6 b ) ( cell c3 c4 b ) ( cell c1 c2 b ) )","( ( cell c3 c1 b ) ( cell c6 c7 b ) ( cell c1 c4 b ) ( cell c4 c4 b ) ( cell c5 c5 b ) ( cell c7 c2 b ) ( cell c7 c8 b ) ( cell c5 c6 b ) ( cell c3 c6 b ) ( cell c4 c2 b ) ( cell c1 c3 b ) ( cell c3 c7 b ) ( cell c7 c3 b ) ( cell c6 c5 b ) ( cell c4 c7 b ) ( cell c8 c1 b ) ( cell c8 c4 b ) ( cell c4 c3 b ) ( cell c2 c5 b ) ( cell c2 c3 b ) ( cell c6 c1 b ) ( cell c1 c1 b ) ( cell c8 c3 b ) ( cell c3 c5 b ) ( cell c7 c1 b ) ( cell c2 c6 b ) ( cell c4 c6 b ) ( cell c6 c2 b ) ( cell c2 c8 b ) ( cell c2 c2 b ) ( cell c8 c8 b ) ( cell c7 c4 b ) ( cell c8 c5 b ) ( cell c4 c5 b ) ( cell c1 c5 b ) ( cell c6 c3 b ) ( cell c5 c3 b ) ( cell c4 c1 b ) ( cell c3 c8 b ) ( cell c6 c6 s ) ( cell c5 c1 b ) ( cell c3 c3 b ) ( cell c1 c8 b ) ( cell c7 c5 b ) ( cell c4 c8 s ) ( control sheep ) ( cell c3 c2 b ) ( cell c2 c4 b ) ( cell c6 c8 b ) ( cell c1 c6 b ) ( cell c8 c6 b ) ( cell c5 c4 b ) ( cell c7 c7 s ) ( cell c8 c7 b ) ( cell c5 c2 b ) ( cell c5 c8 b ) ( cell c2 c7 b ) ( cell c1 c7 s ) ( cell c8 c2 b ) ( cell c2 c1 b ) ( cell c6 c4 b ) ( cell c5 c7 w ) ( cell c7 c6 b ) ( cell c3 c4 b ) ( cell c1 c2 b ) )","( ( cell c3 c1 b ) ( cell c6 c7 b ) ( cell c1 c4 b ) ( cell c4 c4 b ) ( cell c5 c5 b ) ( cell c7 c2 b ) ( cell c7 c8 b ) ( cell c5 c6 b ) ( cell c3 c6 b ) ( cell c4 c2 b ) ( cell c1 c3 b ) ( cell c3 c7 b ) ( cell c7 c3 b ) ( cell c6 c5 b ) ( cell c4 c7 b ) ( cell c8 c1 b ) ( cell c8 c4 b ) ( cell c4 c3 b ) ( cell c2 c5 b ) ( cell c2 c3 b ) ( cell c6 c1 b ) ( cell c1 c1 b ) ( cell c8 c3 b ) ( cell c3 c5 b ) ( cell c7 c1 b ) ( cell c2 c6 b ) ( cell c4 c6 b ) ( cell c6 c2 b ) ( cell c2 c8 b ) ( cell c2 c2 b ) ( cell c8 c8 b ) ( cell c7 c4 b ) ( cell c8 c5 b ) ( cell c4 c5 b ) ( cell c1 c5 b ) ( cell c6 c3 b ) ( cell c5 c3 b ) ( cell c4 c1 b ) ( cell c3 c8 b ) ( cell c6 c6 s ) ( cell c5 c1 b ) ( cell c3 c3 b ) ( cell c1 c8 b ) ( cell c7 c5 b ) ( control wolf ) ( cell c4 c8 s ) ( cell c3 c2 b ) ( cell c2 c4 b ) ( cell c7 c7 b ) ( cell c1 c6 b ) ( cell c8 c6 b ) ( cell c5 c4 b ) ( cell c8 c7 b ) ( cell c5 c2 b ) ( cell c6 c8 s ) ( cell c5 c8 b ) ( cell c2 c7 b ) ( cell c1 c7 s ) ( cell c8 c2 b ) ( cell c2 c1 b ) ( cell c6 c4 b ) ( cell c5 c7 w ) ( cell c7 c6 b ) ( cell c3 c4 b ) ( cell c1 c2 b ) )","( ( cell c3 c1 b ) ( cell c6 c7 b ) ( cell c1 c4 b ) ( cell c4 c4 b ) ( cell c5 c5 b ) ( cell c7 c2 b ) ( cell c7 c8 b ) ( cell c5 c6 b ) ( cell c3 c6 b ) ( cell c4 c2 b ) ( cell c1 c3 b ) ( cell c3 c7 b ) ( cell c7 c3 b ) ( cell c5 c7 b ) ( cell c6 c5 b ) ( cell c4 c7 b ) ( cell c8 c1 b ) ( cell c8 c4 b ) ( cell c4 c3 b ) ( cell c2 c5 b ) ( cell c2 c3 b ) ( cell c6 c1 b ) ( cell c1 c1 b ) ( cell c8 c3 b ) ( cell c3 c5 b ) ( cell c7 c1 b ) ( cell c2 c6 b ) ( cell c6 c2 b ) ( cell c2 c8 b ) ( cell c2 c2 b ) ( cell c8 c8 b ) ( cell c7 c4 b ) ( cell c8 c5 b ) ( cell c4 c5 b ) ( cell c1 c5 b ) ( cell c6 c3 b ) ( cell c5 c3 b ) ( cell c4 c1 b ) ( cell c3 c8 b ) ( cell c6 c6 s ) ( cell c5 c1 b ) ( cell c3 c3 b ) ( cell c1 c8 b ) ( cell c7 c5 b ) ( cell c4 c8 s ) ( control sheep ) ( cell c3 c2 b ) ( cell c2 c4 b ) ( cell c7 c7 b ) ( cell c1 c6 b ) ( cell c8 c6 b ) ( cell c5 c4 b ) ( cell c4 c6 w ) ( cell c8 c7 b ) ( cell c5 c2 b ) ( cell c6 c8 s ) ( cell c5 c8 b ) ( cell c2 c7 b ) ( cell c1 c7 s ) ( cell c8 c2 b ) ( cell c2 c1 b ) ( cell c6 c4 b ) ( cell c7 c6 b ) ( cell c3 c4 b ) ( cell c1 c2 b ) )"],"playClock":15,"gameName":"sheep_and_wolf","moves":[["( move c4 c8 c5 c7 )","noop"],["noop","( move c7 c1 c8 c2 )"],["( move c5 c7 c6 c6 )","noop"],["noop","( move c1 c1 c2 c2 )"],["( move c6 c6 c7 c7 )","noop"],["noop","( move c5 c1 c4 c2 )"],["( move c7 c7 c8 c8 )","noop"],["noop","( move c8 c2 c7 c3 )"],["( move c8 c8 c7 c7 )","noop"],["noop","( move c7 c3 c8 c4 )"],["( move c7 c7 c6 c8 )","noop"],["noop","( move c4 c2 c5 c3 )"],["( move c6 c8 c7 c7 )","noop"],["noop","( move c2 c2 c3 c3 )"],["( move c7 c7 c8 c6 )","noop"],["noop","( move c3 c1 c2 c2 )"],["( move c8 c6 c7 c7 )","noop"],["noop","( move c2 c2 c1 c3 )"],["( move c7 c7 c6 c8 )","noop"],["noop","( move c3 c3 c2 c4 )"],["( move c6 c8 c7 c7 )","noop"],["noop","( move c2 c4 c3 c5 )"],["( move c7 c7 c8 c8 )","noop"],["noop","( move c1 c3 c2 c4 )"],["( move c8 c8 c7 c7 )","noop"],["noop","( move c5 c3 c6 c4 )"],["( move c7 c7 c8 c6 )","noop"],["noop","( move c3 c5 c2 c6 )"],["( move c8 c6 c7 c5 )","noop"],["noop","( move c2 c6 c3 c7 )"],["( move c7 c5 c8 c6 )","noop"],["noop","( move c2 c4 c3 c5 )"],["( move c8 c6 c7 c7 )","noop"],["noop","( move c3 c7 c4 c8 )"],["( move c7 c7 c6 c8 )","noop"],["noop","( move c3 c5 c2 c6 )"],["( move c6 c8 c7 c7 )","noop"],["noop","( move c8 c4 c7 c5 )"],["( move c7 c7 c6 c8 )","noop"],["noop","( move c2 c6 c1 c7 )"],["( move c6 c8 c7 c7 )","noop"],["noop","( move c7 c5 c8 c6 )"],["( move c7 c7 c6 c8 )","noop"],["noop","( move c6 c4 c7 c5 )"],["( move c6 c8 c7 c7 )","noop"],["noop","( move c7 c5 c6 c6 )"],["( move c7 c7 c6 c8 )","noop"],["noop","( move c8 c6 c7 c7 )"],["( move c6 c8 c5 c7 )","noop"],["noop","( move c7 c7 c6 c8 )"],["( move c5 c7 c4 c6 )","noop"]],"startTime":1585828181923,"stateTimes":[1585828181969,1585828182200,1585828182245,1585828182299,1585828182355,1585828182388,1585828182436,1585828182481,1585828182517,1585828182546,1585828182601,1585828182651,1585828182705,1585828182745,1585828182779,1585828182815,1585828182874,1585828182908,1585828182954,1585828182975,1585828182986,1585828183003,1585828183029,1585828183067,1585828183110,1585828183142,1585828183178,1585828183221,1585828183265,1585828183318,1585828183365,1585828183396,1585828183434,1585828183458,1585828183484,1585828183502,1585828183526,1585828183540,1585828183560,1585828183599,1585828183611,1585828183623,1585828183633,1585828183649,1585828183673,1585828183688,1585828183703,1585828183712,1585828183723,1585828183732,1585828183740,1585828183751],"scrambled":false,"matchId":"randomtraces_iggp.sheep_and_wolf.1585828181915","errors":[["",""],["",""],["",""],["",""],["",""],["",""],["",""],["",""],["",""],["",""],["",""],["",""],["",""],["",""],["",""],["",""],["",""],["",""],["",""],["",""],["",""],["",""],["",""],["",""],["",""],["",""],["",""],["",""],["",""],["",""],["",""],["",""],["",""],["",""],["",""],["",""],["",""],["",""],["",""],["",""],["",""],["",""],["",""],["",""],["",""],["",""],["",""],["",""],["",""],["",""],["",""],["",""]],"isCompleted":true,"isAborted":false,"previewClock":-1}